Workbook

Sheet Raw data
A1: Branch Name | B1: Branch Code | C1: BranchLabels | D1: Business Brand | E1: Business Date | F1: Invoice Number | G1: Order Source | H1: Source Order Number | I1: Source Outlet Id | J1: Invoice Date | K1: Invoice Type | L1: Advance Order | M1: Gross Amount | N1: Discounts | O1: Direct Charge Amount | P1: Net Amount | Q1: Other Charge Amount | R1: Taxes | S1: Rounding | T1: Tip | U1: Total | V1: Paid Amount | W1: Balance Due | X1: Payment Modes | Y1: Materials Cost | Z1: Supplies Cost | AA1: Channel | AB1: Channel Label | AC1: Label | AD1: Session | AE1: Customer Id | AF1: Customer Name | AG1: Customer Phone | AH1: Customer Tax Id | AI1: Customer State | AJ1: Statement Number | AK1: Charges Amount (Initial) | AL1: Charges Amount (Removed) | AM1: Payment-Card | AN1: Payment-Cash | AO1: Payment-Dineout Pay | AP1: Payment-magicpin | AQ1: Payment-Magicpin Pay | AR1: Payment-Paytm | AS1: Payment-Swiggy | AT1: Payment-Zomato | AU1: Payment-Zomato District | AV1: CGST 2.5% Value | AW1: CGST 2.5% Amount | AX1: SGST 2.5% Value | AY1: SGST 2.5% Amount | AZ1: Account-Burgrill | BA1: Account-The Sausage Fest | BB1: Charge-Packing Charges | BC1: Charge-Restaurant Packaging Charges
A2: Store 1 | B2: 110027 | C2: Outlet | D2: Burgrill | E2: 45962 | F2: RJ390531 | G2: zomato | H2: 7430059910 | I2: 18528960 | J2: 45962.518 | K2: Sale | L2: No | M2: 257 | N2: 0 | O2: 0 | P2: 257 | Q2: 32 | R2: 0 | S2: 0 | T2: 0 | U2: 289 | V2: 289 | W2: 0 | X2: Zomato | Y2: 52.81 | Z2: 3.92 | AA2: Burgrill-Zomato | AB2: Burgrill | AC2: 9910 | AK2: 32 | AL2: 0 | AT2: 289 | AZ2: 257 | BC2: 32
A3: Store 1 | B3: 110027 | C3: Outlet | D3: Burgrill | E3: 45962 | F3: RJ390532 | G3: swiggy | H3: 220952000000000 | I3: 29811 | J3: 45962.544 | K3: Sale | L3: No | M3: 576 | N3: -93.74 | O3: 0 | P3: 482.26 | Q3: 32 | R3: 0 | S3: -0.26 | T3: 0 | U3: 514 | V3: 514 | W3: 0 | X3: Swiggy | Y3: 126.08 | Z3: 9.76 | AA3: Burgrill-Swiggy | AB3: Burgrill | AC3: 5597 | AK3: 32 | AL3: 0 | AS3: 514 | AZ3: 482.26 | BB3: 32
A4: Store 1 | B4: 110027 | C4: Outlet | D4: Burgrill | E4: 45962 | F4: RJ390530 | G4: POS | J4: 45962.565 | K4: Sale | L4: No | M4: 59 | N4: 0 | O4: 0 | P4: 59 | Q4: 0 | R4: 2.96 | S4: 0.04 | T4: 0 | U4: 62 | V4: 62 | W4: 0 | X4: Cash | Y4: 15.49 | Z4: 1.96 | AA4: Burgrill-Takeaway | AE4: 4VS4ZNEI | AF4: vipin | AG4: 9990930244 | AK4: 0 | AL4: 0 | AN4: 62 | AV4: 59 | AW4: 1.48 | AX4: 59 | AY4: 1.48 | AZ4: 59
A5: Store 1 | B5: 110027 | C5: Outlet | D5: Burgrill | E5: 45962 | F5: RJ390529 | G5: POS | J5: 45962.565 | K5: Sale | L5: No | M5: 159 | N5: 0 | O5: 0 | P5: 159 | Q5: 0 | R5: 7.96 | S5: 0.04 | T5: 0 | U5: 167 | V5: 167 | W5: 0 | X5: Card | Y5: 29.83 | Z5: 2.5 | AA5: Burgrill-Dine In | AB5: Dine In | AE5: R7ZUEYAL | AF5: naman | AG5: 9267927604 | AK5: 0 | AL5: 0 | AM5: 167 | AV5: 159 | AW5: 3.98 | AX5: 159 | AY5: 3.98 | AZ5: 159
A6: Store 1 | B6: 110027 | C6: Outlet | D6: Burgrill | E6: 45962 | F6: RJ390533 | G6: zomato | H6: 7436034135 | I6: 18528960 | J6: 45962.568 | K6: Sale | L6: No | M6: 418 | N6: -75 | O6: 0 | P6: 343 | Q6: 32 | R6: 0 | S6: 0 | T6: 0 | U6: 375 | V6: 375 | W6: 0 | X6: Zomato | Y6: 80.87 | Z6: 4.77 | AA6: Burgrill-Zomato | AB6: Burgrill | AC6: 4135 | AK6: 32 | AL6: 0 | AT6: 375 | AZ6: 343 | BC6: 32
A7: Store 1 | B7: 110027 | C7: Outlet | D7: Burgrill | E7: 45962 | F7: RJ390537 | G7: zomato | H7: 7436304288 | I7: 18528960 | J7: 45962.595 | K7: Sale | L7: No | M7: 359 | N7: -75 | O7: 0 | P7: 284 | Q7: 32 | R7: 0 | S7: 0 | T7: 0 | U7: 316 | V7: 316 | W7: 0 | X7: Zomato | Y7: 77.14 | Z7: 9.82 | AA7: Burgrill-Zomato | AB7: Burgrill | AC7: 4288 | AK7: 32 | AL7: 0 | AT7: 316 | AZ7: 284 | BC7: 32
A8: Store 1 | B8: 110027 | C8: Outlet | D8: Burgrill | E8: 45962 | F8: RJ390538 | G8: swiggy | H8: 220957000000000 | I8: 29811 | J8: 45962.6 | K8: Sale | L8: No | M8: 508 | N8: -200 | O8: 0 | P8: 308 | Q8: 32 | R8: 0 | S8: 0 | T8: 0 | U8: 340 | V8: 340 | W8: 0 | X8: Swiggy | Y8: 74.34 | Z8: 3.38 | AA8: Burgrill-Swiggy | AB8: Burgrill | AC8: 4258 | AK8: 32 | AL8: 0 | AS8: 340 | AZ8: 308 | BB8: 32
A9: Store 1 | B9: 110027 | C9: Outlet | D9: Burgrill | E9: 45962 | F9: RJ390539 | G9: zomato | H9: 7436617919 | I9: 18528960 | J9: 45962.612 | K9: Sale | L9: No | M9: 308 | N9: -100 | O9: 0 | P9: 208 | Q9: 32 | R9: 0 | S9: 0 | T9: 0 | U9: 240 | V9: 240 | W9: 0 | X9: Zomato | Y9: 56.44 | Z9: 10.56 | AA9: Burgrill-Zomato | AB9: Burgrill | AC9: 7919 | AK9: 32 | AL9: 0 | AT9: 240 | AZ9: 208 | BC9: 32
A10: Store 1 | B10: 110027 | C10: Outlet | D10: Burgrill | E10: 45962 | F10: RJ390540 | G10: swiggy | H10: 220958000000000 | I10: 29811 | J10: 45962.617 | K10: Sale | L10: No | M10: 508 | N10: -93.74 | O10: 0 | P10: 414.26 | Q10: 32 | R10: 0 | S10: -0.26 | T10: 0 | U10: 446 | V10: 446 | W10: 0 | X10: Swiggy | Y10: 94.86 | Z10: 13.74 | AA10: Burgrill-Swiggy | AB10: Burgrill | AC10: 7113 | AK10: 32 | AL10: 0 | AS10: 446 | AZ10: 414.26 | BB10: 32
A11: Store 1 | B11: 110027 | C11: Outlet | D11: Burgrill | E11: 45962 | F11: RJ390541 | G11: swiggy | H11: 220959000000000 | I11: 29811 | J11: 45962.624 | K11: Sale | L11: No | M11: 393.28 | N11: -93.75 | O11: 0 | P11: 299.53 | Q11: 32 | R11: 0 | S11: 0.47 | T11: 0 | U11: 332 | V11: 332 | W11: 0 | X11: Swiggy | Y11: 91.25 | Z11: 5.79 | AA11: Burgrill-Swiggy | AB11: Burgrill | AC11: 124 | AK11: 32 | AL11: 0 | AS11: 332 | AZ11: 299.53 | BB11: 32
A12: Store 1 | B12: 110027 | C12: Outlet | D12: Burgrill | E12: 45962 | F12: RJ390542 | G12: swiggy | H12: 220959000000000 | I12: 29811 | J12: 45962.626 | K12: Sale | L12: No | M12: 268 | N12: -93.75 | O12: 0 | P12: 174.25 | Q12: 32 | R12: 0 | S12: -0.25 | T12: 0 | U12: 206 | V12: 206 | W12: 0 | X12: Swiggy | Y12: 49.33 | Z12: 7.46 | AA12: Burgrill-Swiggy | AB12: Burgrill | AC12: 4459 | AK12: 32 | AL12: 0 | AS12: 206 | AZ12: 174.25 | BB12: 32
A13: Store 1 | B13: 110027 | C13: Outlet | D13: Burgrill | E13: 45962 | F13: RJ390543 | G13: zomato | H13: 7435937715 | I13: 18528960 | J13: 45962.64 | K13: Sale | L13: No | M13: 698 | N13: -349 | O13: 0 | P13: 349 | Q13: 32 | R13: 0 | S13: 0 | T13: 0 | U13: 381 | V13: 381 | W13: 0 | X13: Zomato | Y13: 129.66 | Z13: 9.54 | AA13: Burgrill-Zomato | AB13: Burgrill | AC13: 7715 | AK13: 32 | AL13: 0 | AT13: 381 | AZ13: 349 | BC13: 32
A14: Store 1 | B14: 110027 | C14: Outlet | D14: Burgrill | E14: 45962 | F14: RJ390544 | G14: zomato | H14: 7435794679 | I14: 18528960 | J14: 45962.65 | K14: Sale | L14: No | M14: 574.66 | N14: -199.5 | O14: 0 | P14: 375.16 | Q14: 32 | R14: 0 | S14: 0 | T14: 0 | U14: 407.16 | V14: 407.16 | W14: 0 | X14: Zomato | Y14: 99.34 | Z14: 4.06 | AA14: Burgrill-Zomato | AB14: Burgrill | AC14: 4679 | AK14: 32 | AL14: 0 | AT14: 407.16 | AZ14: 375.16 | BC14: 32
A15: Store 1 | B15: 110027 | C15: Outlet | D15: Burgrill | E15: 45962 | F15: RJ390545 | G15: swiggy | H15: 220962000000000 | I15: 29811 | J15: 45962.656 | K15: Sale | L15: No | M15: 258 | N15: -93.75 | O15: 0 | P15: 164.25 | Q15: 32 | R15: 0 | S15: -0.25 | T15: 0 | U15: 196 | V15: 196 | W15: 0 | X15: Swiggy | Y15: 48.54 | Z15: 7.02 | AA15: Burgrill-Swiggy | AB15: Burgrill | AC15: 3213 | AK15: 32 | AL15: 0 | AS15: 196 | AZ15: 164.25 | BB15: 32
A16: Store 1 | B16: 110027 | C16: Outlet | D16: Burgrill | E16: 45962 | F16: RJ390534 | G16: POS | J16: 45962.669 | K16: Sale | L16: No | M16: 288 | N16: 0 | O16: 0 | P16: 288 | Q16: 0 | R16: 14.4 | S16: -0.4 | T16: 0 | U16: 302 | V16: 302 | W16: 0 | X16: Card | Y16: 68.99 | Z16: 3.92 | AA16: Burgrill-Dine In | AB16: Dine In | AE16: RJFXN3YM | AF16: Burgrill | AG16: 8929758003 | AK16: 0 | AL16: 0 | AM16: 302 | AV16: 288 | AW16: 7.2 | AX16: 288 | AY16: 7.2 | AZ16: 288
A17: Store 1 | B17: 110027 | C17: Outlet | D17: Burgrill | E17: 45962 | F17: RJ390535 | G17: POS | J17: 45962.669 | K17: Sale | L17: No | M17: 356 | N17: 0 | O17: 0 | P17: 356 | Q17: 0 | R17: 17.8 | S17: 0.2 | T17: 0 | U17: 374 | V17: 374 | W17: 0 | X17: Card | Y17: 100.44 | Z17: 8.16 | AA17: Burgrill-Dine In | AB17: Dine In | AE17: BCTCUL8A | AF17: ms | AG17: 8171020359 | AK17: 0 | AL17: 0 | AM17: 374 | AV17: 356 | AW17: 8.9 | AX17: 356 | AY17: 8.9 | AZ17: 356
A18: Store 1 | B18: 110027 | C18: Outlet | D18: Burgrill | E18: 45962 | F18: RJ390536 | G18: POS | J18: 45962.669 | K18: Sale | L18: No | M18: 66.66 | N18: 0 | O18: 0 | P18: 66.66 | Q18: 0 | R18: 3.34 | S18: 0 | T18: 0 | U18: 70 | V18: 70 | W18: 0 | X18: Card | Y18: 25 | Z18: 0 | AA18: Burgrill-Dine In | AB18: Dine In | AE18: RJFXN3YM | AF18: Burgrill | AG18: 8929758003 | AK18: 0 | AL18: 0 | AM18: 70 | AV18: 66.66 | AW18: 1.67 | AX18: 66.66 | AY18: 1.67 | AZ18: 66.66
A19: Store 1 | B19: 110027 | C19: Outlet | D19: Burgrill | E19: 45962 | F19: RJ390546 | G19: swiggy | H19: 220963000000000 | I19: 29811 | J19: 45962.676 | K19: Sale | L19: No | M19: 545 | N19: -130 | O19: 0 | P19: 415 | Q19: 32 | R19: 0 | S19: 0 | T19: 0 | U19: 447 | V19: 447 | W19: 0 | X19: Swiggy | Y19: 99.73 | Z19: 9.8 | AA19: Burgrill-Swiggy | AB19: Burgrill | AC19: 5595 | AK19: 32 | AL19: 0 | AS19: 447 | AZ19: 415 | BB19: 32
A20: Store 1 | B20: 110027 | C20: Outlet | D20: Burgrill | E20: 45962 | F20: RJ390547 | G20: swiggy | H20: 220963000000000 | I20: 29811 | J20: 45962.677 | K20: Sale | L20: No | M20: 395 | N20: -74.99 | O20: 0 | P20: 320.01 | Q20: 32 | R20: 0 | S20: -0.01 | T20: 0 | U20: 352 | V20: 352 | W20: 0 | X20: Swiggy | Y20: 74.43 | Z20: 8.88 | AA20: Burgrill-Swiggy | AB20: Burgrill | AC20: 5423 | AK20: 32 | AL20: 0 | AS20: 352 | AZ20: 320.01 | BB20: 32
A21: Store 1 | B21: 110027 | C21: Outlet | D21: Burgrill | E21: 45962 | F21: RJ390549 | G21: POS | J21: 45962.697 | K21: Sale | L21: No | M21: 159 | N21: 0 | O21: 0 | P21: 159 | Q21: 0 | R21: 7.96 | S21: 0.04 | T21: 0 | U21: 167 | V21: 167 | W21: 0 | X21: Cash | Y21: 29.83 | Z21: 2.5 | AA21: Burgrill-Dine In | AB21: Dine In | AE21: E9WZ2UG5 | AF21: sidhi | AG21: 7817653551 | AK21: 0 | AL21: 0 | AN21: 167 | AV21: 159 | AW21: 3.98 | AX21: 159 | AY21: 3.98 | AZ21: 159
A22: Store 1 | B22: 110027 | C22: Outlet | D22: Burgrill | E22: 45962 | F22: RJ390550 | G22: swiggy | H22: 220966000000000 | I22: 29811 | J22: 45962.702 | K22: Sale | L22: No | M22: 646 | N22: -93.75 | O22: 0 | P22: 552.25 | Q22: 32 | R22: 0 | S22: -0.25 | T22: 0 | U22: 584 | V22: 584 | W22: 0 | X22: Swiggy | Y22: 150.41 | Z22: 14.78 | AA22: Burgrill-Swiggy | AB22: Burgrill | AC22: 379 | AK22: 32 | AL22: 0 | AS22: 584 | AZ22: 552.25 | BB22: 32
A23: Store 1 | B23: 110027 | C23: Outlet | D23: Burgrill | E23: 45962 | F23: RJ390551 | G23: POS | J23: 45962.706 | K23: Sale | L23: No | M23: 369 | N23: 0 | O23: 0 | P23: 369 | Q23: 0 | R23: 18.46 | S23: -0.46 | T23: 0 | U23: 387 | V23: 387 | W23: 0 | X23: Cash | Y23: 99.73 | Z23: 8.72 | AA23: Burgrill-Dine In | AB23: Dine In | AE23: GIDIRMS3 | AF23: hare krishna | AG23: 9999669771 | AK23: 0 | AL23: 0 | AN23: 387 | AV23: 369 | AW23: 9.23 | AX23: 369 | AY23: 9.23 | AZ23: 369
A24: Store 1 | B24: 110027 | C24: Outlet | D24: Burgrill | E24: 45962 | F24: RJ390554 | G24: zomato | H24: 7437673579 | I24: 18528960 | J24: 45962.71 | K24: Sale | L24: No | M24: 663.66 | N24: -248.9 | O24: 0 | P24: 414.76 | Q24: 32 | R24: 0 | S24: 0 | T24: 0 | U24: 446.76 | V24: 446.76 | W24: 0 | X24: Zomato | Y24: 135.43 | Z24: 10.95 | AA24: Burgrill-Zomato | AB24: Burgrill | AC24: 3579 | AK24: 32 | AL24: 0 | AT24: 446.76 | AZ24: 414.76 | BC24: 32
A25: Store 1 | B25: 110027 | C25: Outlet | D25: Burgrill | E25: 45962 | F25: RJ390558 | G25: swiggy | H25: 220968000000000 | I25: 29811 | J25: 45962.729 | K25: Sale | L25: No | M25: 318 | N25: -93.75 | O25: 0 | P25: 224.25 | Q25: 32 | R25: 0 | S25: -0.25 | T25: 0 | U25: 256 | V25: 256 | W25: 0 | X25: Swiggy | Y25: 70.61 | Z25: 4.77 | AA25: Burgrill-Swiggy | AB25: Burgrill | AC25: 9697 | AK25: 32 | AL25: 0 | AS25: 256 | AZ25: 224.25 | BB25: 32
A26: Store 1 | B26: 110027 | C26: Outlet | D26: Burgrill | E26: 45962 | F26: RJ390559 | G26: swiggy | H26: 220968000000000 | I26: 29811 | J26: 45962.731 | K26: Sale | L26: No | M26: 178 | N26: -20 | O26: 0 | P26: 158 | Q26: 32 | R26: 0 | S26: 0 | T26: 0 | U26: 190 | V26: 190 | W26: 0 | X26: Swiggy | Y26: 37.92 | Z26: 1.96 | AA26: Burgrill-Swiggy | AB26: Burgrill | AC26: 6720 | AK26: 32 | AL26: 0 | AS26: 190 | AZ26: 158 | BB26: 32
A27: Store 1 | B27: 110027 | C27: Outlet | D27: Burgrill | E27: 45962 | F27: RJ390560 | G27: zomato | H27: 7431959854 | I27: 18528960 | J27: 45962.74 | K27: Sale | L27: No | M27: 1036 | N27: 0 | O27: 0 | P27: 1036 | Q27: 32 | R27: 0 | S27: 0 | T27: 0 | U27: 1068 | V27: 1068 | W27: 0 | X27: Zomato | Y27: 233.97 | Z27: 19.36 | AA27: Burgrill-Zomato | AB27: Burgrill | AC27: 9854 | AK27: 32 | AL27: 0 | AT27: 1068 | AZ27: 1036 | BC27: 32
A28: Store 1 | B28: 110027 | C28: Outlet | D28: Burgrill | E28: 45962 | F28: RJ390564 | G28: POS | J28: 45962.772 | K28: Sale | L28: No | M28: 198 | N28: 0 | O28: 0 | P28: 198 | Q28: 0 | R28: 9.9 | S28: 0.1 | T28: 0 | U28: 208 | V28: 208 | W28: 0 | X28: Cash | Y28: 48.85 | Z28: 3.92 | AA28: Burgrill-Dine In | AB28: Dine In | AE28: RJFXN3YM | AF28: Burgrill | AG28: 8929758003 | AK28: 0 | AL28: 0 | AN28: 208 | AV28: 198 | AW28: 4.95 | AX28: 198 | AY28: 4.95 | AZ28: 198
A29: Store 1 | B29: 110027 | C29: Outlet | D29: Burgrill | E29: 45962 | F29: RJ390563 | G29: POS | J29: 45962.772 | K29: Sale | L29: No | M29: 217 | N29: -15 | O29: 0 | P29: 202 | Q29: 0 | R29: 10.1 | S29: -0.1 | T29: 0 | U29: 212 | V29: 212 | W29: 0 | X29: Cash,Card | Y29: 56.03 | Z29: 5.88 | AA29: Burgrill-Takeaway | AE29: I8Y3EPU8 | AF29: shivam | AG29: 9810206362 | AK29: 0 | AL29: 0 | AM29: 12 | AN29: 200 | AV29: 202 | AW29: 5.05 | AX29: 202 | AY29: 5.05 | AZ29: 202
A30: Store 1 | B30: 110027 | C30: Outlet | D30: Burgrill | E30: 45962 | F30: RJ390562 | G30: POS | J30: 45962.772 | K30: Sale | L30: No | M30: 356 | N30: 0 | O30: 0 | P30: 356 | Q30: 0 | R30: 17.8 | S30: 0.2 | T30: 0 | U30: 374 | V30: 374 | W30: 0 | X30: Card | Y30: 97.33 | Z30: 8.16 | AA30: Burgrill-Dine In | AB30: Dine In | AE30: RJFXN3YM | AF30: Burgrill | AG30: 8929758003 | AK30: 0 | AL30: 0 | AM30: 374 | AV30: 356 | AW30: 8.9 | AX30: 356 | AY30: 8.9 | AZ30: 356
A31: Store 1 | B31: 110027 | C31: Outlet | D31: Burgrill | E31: 45962 | F31: RJ390561 | G31: POS | J31: 45962.772 | K31: Sale | L31: No | M31: 348 | N31: 0 | O31: 0 | P31: 348 | Q31: 0 | R31: 17.4 | S31: -0.4 | T31: 0 | U31: 365 | V31: 365 | W31: 0 | X31: Card | Y31: 97.24 | Z31: 4.52 | AA31: Burgrill-Dine In | AB31: Dine In | AE31: RJFXN3YM | AF31: Burgrill | AG31: 8929758003 | AK31: 0 | AL31: 0 | AM31: 365 | AV31: 348 | AW31: 8.7 | AX31: 348 | AY31: 8.7 | AZ31: 348
A32: Store 1 | B32: 110027 | C32: Outlet | D32: Burgrill | E32: 45962 | F32: RJ390557 | G32: POS | J32: 45962.772 | K32: Sale | L32: No | M32: 597 | N32: 0 | O32: 0 | P32: 597 | Q32: 0 | R32: 29.86 | S32: 0.14 | T32: 0 | U32: 627 | V32: 627 | W32: 0 | X32: Card | Y32: 142.23 | Z32: 7.68 | AA32: Burgrill-Dine In | AB32: Dine In | AE32: MJHTLH2P | AF32: asveed | AG32: 8287834046 | AK32: 0 | AL32: 0 | AM32: 627 | AV32: 597 | AW32: 14.93 | AX32: 597 | AY32: 14.93 | AZ32: 597
A33: Store 1 | B33: 110027 | C33: Outlet | D33: Burgrill | E33: 45962 | F33: RJ390556 | G33: POS | J33: 45962.773 | K33: Sale | L33: No | M33: 594.1 | N33: 0 | O33: 0 | P33: 594.1 | Q33: 0 | R33: 29.7 | S33: 0.2 | T33: 0 | U33: 624 | V33: 624 | W33: 0 | X33: Cash,Card | Y33: 171.65 | Z33: 8.86 | AA33: Burgrill-Dine In | AB33: Dine In | AE33: RJFXN3YM | AF33: Burgrill | AG33: 8929758003 | AK33: 0 | AL33: 0 | AM33: 124 | AN33: 500 | AV33: 594.1 | AW33: 14.85 | AX33: 594.1 | AY33: 14.85 | AZ33: 594.1
A34: Store 1 | B34: 110027 | C34: Outlet | D34: Burgrill | E34: 45962 | F34: RJ390553 | G34: POS | J34: 45962.773 | K34: Sale | L34: No | M34: 369 | N34: 0 | O34: 0 | P34: 369 | Q34: 0 | R34: 18.46 | S34: -0.46 | T34: 0 | U34: 387 | V34: 387 | W34: 0 | X34: Cash | Y34: 81.84 | Z34: 8.72 | AA34: Burgrill-Dine In | AB34: Dine In | AE34: ZQVQWXQQ | AF34: new | AG34: 9717033322 | AK34: 0 | AL34: 0 | AN34: 387 | AV34: 369 | AW34: 9.23 | AX34: 369 | AY34: 9.23 | AZ34: 369
A35: Store 1 | B35: 110027 | C35: Outlet | D35: Burgrill | E35: 45962 | F35: RJ390555 | G35: POS | J35: 45962.773 | K35: Sale | L35: No | M35: 59 | N35: 0 | O35: 0 | P35: 59 | Q35: 0 | R35: 2.96 | S35: 0.04 | T35: 0 | U35: 62 | V35: 62 | W35: 0 | X35: Card | Y35: 15.49 | Z35: 2.14 | AA35: Burgrill-Dine In | AB35: Dine In | AE35: RJFXN3YM | AF35: Burgrill | AG35: 8929758003 | AK35: 0 | AL35: 0 | AM35: 62 | AV35: 59 | AW35: 1.48 | AX35: 59 | AY35: 1.48 | AZ35: 59
A36: Store 1 | B36: 110027 | C36: Outlet | D36: Burgrill | E36: 45962 | F36: RJ390552 | G36: POS | J36: 45962.773 | K36: Sale | L36: No | M36: 507 | N36: 0 | O36: 0 | P36: 507 | Q36: 0 | R36: 25.36 | S36: -0.36 | T36: 0 | U36: 532 | V36: 532 | W36: 0 | X36: Card | Y36: 107.54 | Z36: 12.83 | AA36: Burgrill-Dine In | AB36: Dine In | AE36: RJFXN3YM | AF36: Burgrill | AG36: 8929758003 | AK36: 0 | AL36: 0 | AM36: 532 | AV36: 507 | AW36: 12.68 | AX36: 507 | AY36: 12.68 | AZ36: 507
A37: Store 1 | B37: 110027 | C37: Outlet | D37: Burgrill | E37: 45962 | F37: RJ390548 | G37: POS | J37: 45962.773 | K37: Sale | L37: No | M37: 398 | N37: 0 | O37: 0 | P37: 398 | Q37: 0 | R37: 19.9 | S37: 0.1 | T37: 0 | U37: 418 | V37: 418 | W37: 0 | X37: Card | Y37: 108.44 | Z37: 10.46 | AA37: Burgrill-Dine In | AB37: Dine In | AE37: RJFXN3YM | AF37: Burgrill | AG37: 8929758003 | AK37: 0 | AL37: 0 | AM37: 418 | AV37: 398 | AW37: 9.95 | AX37: 398 | AY37: 9.95 | AZ37: 398
A38: Store 1 | B38: 110027 | C38: Outlet | D38: Burgrill | E38: 45962 | F38: RJ390566 | G38: zomato | H38: 7433349559 | I38: 18528960 | J38: 45962.78 | K38: Sale | L38: No | M38: 349 | N38: -174.5 | O38: 0 | P38: 174.5 | Q38: 32 | R38: 0 | S38: 0 | T38: 0 | U38: 206.5 | V38: 206.5 | W38: 0 | X38: Zomato | Y38: 64.83 | Z38: 4.77 | AA38: Burgrill-Zomato | AB38: Burgrill | AC38: 9559 | AK38: 32 | AL38: 0 | AT38: 206.5 | AZ38: 174.5 | BC38: 32
A39: Store 1 | B39: 110027 | C39: Outlet | D39: Burgrill | E39: 45962 | F39: RJ390567 | G39: zomato | H39: 7431662061 | I39: 18528960 | J39: 45962.79 | K39: Sale | L39: No | M39: 1583.57 | N39: -677.59 | O39: 0 | P39: 905.98 | Q39: 32 | R39: 0 | S39: 0 | T39: 0 | U39: 937.98 | V39: 937.98 | W39: 0 | X39: Zomato | Y39: 288.31 | Z39: 26.97 | AA39: Burgrill-Zomato | AB39: Burgrill | AC39: 2061 | AK39: 32 | AL39: 0 | AT39: 937.98 | AZ39: 905.99 | BC39: 32
A40: Store 1 | B40: 110027 | C40: Outlet | D40: Burgrill | E40: 45962 | F40: RJ390568 | G40: zomato | H40: 7436694056 | I40: 18528960 | J40: 45962.792 | K40: Sale | L40: No | M40: 399 | N40: -75 | O40: 0 | P40: 324 | Q40: 32 | R40: 0 | S40: 0 | T40: 0 | U40: 356 | V40: 356 | W40: 0 | X40: Zomato | Y40: 88.74 | Z40: 4.96 | AA40: Burgrill-Zomato | AB40: Burgrill | AC40: 4056 | AK40: 32 | AL40: 0 | AT40: 356 | AZ40: 324 | BC40: 32
A41: Store 1 | B41: 110027 | C41: Outlet | D41: Burgrill | E41: 45962 | F41: RJ390569 | G41: swiggy | H41: 220974000000000 | I41: 29811 | J41: 45962.792 | K41: Sale | L41: No | M41: 644 | N41: -123.74 | O41: 0 | P41: 520.26 | Q41: 32 | R41: 0 | S41: -0.26 | T41: 0 | U41: 552 | V41: 552 | W41: 0 | X41: Swiggy | Y41: 122.06 | Z41: 22.03 | AA41: Burgrill-Swiggy | AB41: Burgrill | AC41: 7691 | AK41: 32 | AL41: 0 | AS41: 552 | AZ41: 520.26 | BB41: 32
A42: Store 1 | B42: 110027 | C42: Outlet | D42: Burgrill | E42: 45962 | F42: RJ390572 | G42: swiggy | H42: 220975000000000 | I42: 29811 | J42: 45962.81 | K42: Sale | L42: No | M42: 349 | N42: -175 | O42: 0 | P42: 174 | Q42: 32 | R42: 0 | S42: 0 | T42: 0 | U42: 206 | V42: 206 | W42: 0 | X42: Swiggy | Y42: 64.83 | Z42: 4.77 | AA42: Burgrill-Swiggy | AB42: Burgrill | AC42: 7405 | AK42: 32 | AL42: 0 | AS42: 206 | AZ42: 174 | BB42: 32
A43: Store 1 | B43: 110027 | C43: Outlet | D43: Burgrill | E43: 45962 | F43: RJ390575 | G43: swiggy | H43: 220975000000000 | I43: 29811 | J43: 45962.812 | K43: Sale | L43: No | M43: 437 | N43: -113.75 | O43: 0 | P43: 323.25 | Q43: 32 | R43: 0 | S43: -0.25 | T43: 0 | U43: 355 | V43: 355 | W43: 0 | X43: Swiggy | Y43: 79.68 | Z43: 11.79 | AA43: Burgrill-Swiggy | AB43: Burgrill | AC43: 248 | AK43: 32 | AL43: 0 | AS43: 355 | AZ43: 323.25 | BB43: 32
A44: Store 1 | B44: 110027 | C44: Outlet | D44: Burgrill | E44: 45962 | F44: RJ390576 | G44: swiggy | H44: 220976000000000 | I44: 29811 | J44: 45962.818 | K44: Sale | L44: No | M44: 287 | N44: -70 | O44: 0 | P44: 217 | Q44: 32 | R44: 0 | S44: 0 | T44: 0 | U44: 249 | V44: 249 | W44: 0 | X44: Swiggy | Y44: 53.91 | Z44: 5.88 | AA44: Burgrill-Swiggy | AB44: Burgrill | AC44: 43 | AK44: 32 | AL44: 0 | AS44: 249 | AZ44: 217 | BB44: 32
A45: Store 1 | B45: 110027 | C45: Outlet | D45: Burgrill | E45: 45962 | F45: RJ390577 | G45: POS | J45: 45962.822 | K45: Sale | L45: No | M45: 118 | N45: 0 | O45: 0 | P45: 118 | Q45: 0 | R45: 5.9 | S45: 0.1 | T45: 0 | U45: 124 | V45: 124 | W45: 0 | X45: Cash | Y45: 30.99 | Z45: 3.92 | AA45: Burgrill-Takeaway | AE45: RJFXN3YM | AF45: Burgrill | AG45: 8929758003 | AK45: 0 | AL45: 0 | AN45: 124 | AV45: 118 | AW45: 2.95 | AX45: 118 | AY45: 2.95 | AZ45: 118
A46: Store 1 | B46: 110027 | C46: Outlet | D46: Burgrill | E46: 45962 | F46: RJ390574 | G46: POS | J46: 45962.822 | K46: Sale | L46: No | M46: 79 | N46: 0 | O46: 0 | P46: 79 | Q46: 0 | R46: 3.96 | S46: 0.04 | T46: 0 | U46: 83 | V46: 83 | W46: 0 | X46: Card | Y46: 19.5 | Z46: 1.96 | AA46: Burgrill-Dine In | AB46: Dine In | AE46: RJFXN3YM | AF46: Burgrill | AG46: 8929758003 | AK46: 0 | AL46: 0 | AM46: 83 | AV46: 79 | AW46: 1.98 | AX46: 79 | AY46: 1.98 | AZ46: 79
A47: Store 1 | B47: 110027 | C47: Outlet | D47: Burgrill | E47: 45962 | F47: RJ390573 | G47: POS | J47: 45962.822 | K47: Sale | L47: No | M47: 159 | N47: 0 | O47: 0 | P47: 159 | Q47: 0 | R47: 7.96 | S47: 0.04 | T47: 0 | U47: 167 | V47: 167 | W47: 0 | X47: Cash | Y47: 29.83 | Z47: 5.5 | AA47: Burgrill-Takeaway | AE47: RJFXN3YM | AF47: Burgrill | AG47: 8929758003 | AK47: 0 | AL47: 0 | AN47: 167 | AV47: 159 | AW47: 3.98 | AX47: 159 | AY47: 3.98 | AZ47: 159
A48: Store 1 | B48: 110027 | C48: Outlet | D48: Burgrill | E48: 45962 | F48: RJ390578 | G48: zomato | H48: 7436526153 | I48: 18528960 | J48: 45962.822 | K48: Sale | L48: No | M48: 698 | N48: -349 | O48: 0 | P48: 349 | Q48: 32 | R48: 0 | S48: 0 | T48: 0 | U48: 381 | V48: 381 | W48: 0 | X48: Zomato | Y48: 131.54 | Z48: 9.54 | AA48: Burgrill-Zomato | AB48: Burgrill | AC48: 6153 | AK48: 32 | AL48: 0 | AT48: 381 | AZ48: 349 | BC48: 32
A49: Store 1 | B49: 110027 | C49: Outlet | D49: Burgrill | E49: 45962 | F49: RJ390579 | G49: swiggy | H49: 220976000000000 | I49: 29811 | J49: 45962.824 | K49: Sale | L49: No | M49: 586 | N49: -93.74 | O49: 0 | P49: 492.26 | Q49: 32 | R49: 0 | S49: -0.26 | T49: 0 | U49: 524 | V49: 524 | W49: 0 | X49: Swiggy | Y49: 98.21 | Z49: 17.65 | AA49: Burgrill-Swiggy | AB49: Burgrill | AC49: 7894 | AK49: 32 | AL49: 0 | AS49: 524 | AZ49: 492.26 | BB49: 32
A50: Store 1 | B50: 110027 | C50: Outlet | D50: Burgrill | E50: 45962 | F50: RJ390583 | G50: zomato | H50: 7432335619 | I50: 18528960 | J50: 45962.842 | K50: Sale | L50: No | M50: 885 | N50: -140 | O50: 0 | P50: 745 | Q50: 32 | R50: 0 | S50: 0 | T50: 0 | U50: 777 | V50: 777 | W50: 0 | X50: Zomato | Y50: 206.52 | Z50: 13.83 | AA50: Burgrill-Zomato | AB50: Burgrill | AC50: 5619 | AK50: 32 | AL50: 0 | AT50: 777 | AZ50: 745 | BC50: 32
A51: Store 1 | B51: 110027 | C51: Outlet | D51: Burgrill | E51: 45962 | F51: RJ390584 | G51: swiggy | H51: 220978000000000 | I51: 29811 | J51: 45962.845 | K51: Sale | L51: No | M51: 995 | N51: -298.75 | O51: 0 | P51: 696.25 | Q51: 32 | R51: 0 | S51: -0.25 | T51: 0 | U51: 728 | V51: 728 | W51: 0 | X51: Swiggy | Y51: 197.3 | Z51: 16.53 | AA51: Burgrill-Swiggy | AB51: Burgrill | AC51: 5670 | AK51: 32 | AL51: 0 | AS51: 728 | AZ51: 696.25 | BB51: 32
A52: Store 1 | B52: 110027 | C52: Outlet | D52: Burgrill | E52: 45962 | F52: RJ390586 | G52: magicpin | H52: 280270765 | J52: 45962.847 | K52: Sale | L52: No | M52: 247 | N52: -100 | O52: 0 | P52: 147 | Q52: 0 | R52: 0 | S52: 0 | T52: 0 | U52: 147 | V52: 147 | W52: 0 | X52: magicpin | Y52: 47.58 | Z52: 5.88 | AA52: magicpin Burgrill | AC52: 765 | AE52: D8MDIGHA | AF52: Hargun | AG52: 8700771033 | AI52: New Delhi | AK52: 0 | AL52: 0 | AP52: 147 | AZ52: 147
A53: Store 1 | B53: 110027 | C53: Outlet | D53: Burgrill | E53: 45962 | F53: RJ390587 | G53: swiggy | H53: 220978000000000 | I53: 29811 | J53: 45962.847 | K53: Sale | L53: No | M53: 219 | N53: -90 | O53: 0 | P53: 129 | Q53: 32 | R53: 0 | S53: 0 | T53: 0 | U53: 161 | V53: 161 | W53: 0 | X53: Swiggy | Y53: 41.16 | Z53: 4.26 | AA53: Burgrill-Swiggy | AB53: Burgrill | AC53: 424 | AK53: 32 | AL53: 0 | AS53: 161 | AZ53: 129 | BB53: 32
A54: Store 1 | B54: 110027 | C54: Outlet | D54: Burgrill | E54: 45962 | F54: RJ390588 | G54: zomato | H54: 7435510209 | I54: 18528960 | J54: 45962.851 | K54: Sale | L54: No | M54: 717 | N54: -75 | O54: 0 | P54: 642 | Q54: 32 | R54: 0 | S54: 0 | T54: 0 | U54: 674 | V54: 674 | W54: 0 | X54: Zomato | Y54: 141.82 | Z54: 13.65 | AA54: Burgrill-Zomato | AB54: Burgrill | AC54: 209 | AK54: 32 | AL54: 0 | AT54: 674 | AZ54: 642 | BC54: 32
A55: Store 1 | B55: 110027 | C55: Outlet | D55: Burgrill | E55: 45962 | F55: RJ390589 | G55: zomato | H55: 7435637642 | I55: 18528960 | J55: 45962.857 | K55: Sale | L55: No | M55: 349 | N55: -75 | O55: 0 | P55: 274 | Q55: 32 | R55: 0 | S55: 0 | T55: 0 | U55: 306 | V55: 306 | W55: 0 | X55: Zomato | Y55: 72.32 | Z55: 9.82 | AA55: Burgrill-Zomato | AB55: Burgrill | AC55: 7642 | AK55: 32 | AL55: 0 | AT55: 306 | AZ55: 274 | BC55: 32
A56: Store 1 | B56: 110027 | C56: Outlet | D56: Burgrill | E56: 45962 | F56: RJ390590 | G56: swiggy | H56: 220979000000000 | I56: 29811 | J56: 45962.859 | K56: Sale | L56: No | M56: 448 | N56: -93.74 | O56: 0 | P56: 354.26 | Q56: 32 | R56: 0 | S56: -0.26 | T56: 0 | U56: 386 | V56: 386 | W56: 0 | X56: Swiggy | Y56: 87.84 | Z56: 8.69 | AA56: Burgrill-Swiggy | AB56: Burgrill | AC56: 7472 | AK56: 32 | AL56: 0 | AS56: 386 | AZ56: 354.26 | BB56: 32
A57: Store 1 | B57: 110027 | C57: Outlet | D57: Burgrill | E57: 45962 | F57: RJ390585 | G57: POS | J57: 45962.867 | K57: Sale | L57: No | M57: 369 | N57: 0 | O57: 0 | P57: 369 | Q57: 0 | R57: 18.46 | S57: -0.46 | T57: 0 | U57: 387 | V57: 387 | W57: 0 | X57: Cash | Y57: 99.73 | Z57: 8.72 | AA57: Burgrill-Dine In | AB57: Dine In | AE57: RJFXN3YM | AF57: Burgrill | AG57: 8929758003 | AK57: 0 | AL57: 0 | AN57: 387 | AV57: 369 | AW57: 9.23 | AX57: 369 | AY57: 9.23 | AZ57: 369
A58: Store 1 | B58: 110027 | C58: Outlet | D58: Burgrill | E58: 45962 | F58: RJ390592 | G58: swiggy | H58: 220980000000000 | I58: 29811 | J58: 45962.869 | K58: Sale | L58: No | M58: 348 | N58: -120 | O58: 0 | P58: 228 | Q58: 32 | R58: 0 | S58: 0 | T58: 0 | U58: 260 | V58: 260 | W58: 0 | X58: Swiggy | Y58: 67.56 | Z58: 11.79 | AA58: Burgrill-Swiggy | AB58: Burgrill | AC58: 545 | AK58: 32 | AL58: 0 | AS58: 260 | AZ58: 228 | BB58: 32
A59: Store 1 | B59: 110027 | C59: Outlet | D59: Burgrill | E59: 45962 | F59: RJ390593 | G59: swiggy | H59: 220980000000000 | I59: 29811 | J59: 45962.869 | K59: Sale | L59: No | M59: 328 | N59: -75 | O59: 0 | P59: 253 | Q59: 32 | R59: 0 | S59: 0 | T59: 0 | U59: 285 | V59: 285 | W59: 0 | X59: Swiggy | Y59: 65.96 | Z59: 8.34 | AA59: Burgrill-Swiggy | AB59: Burgrill | AC59: 3459 | AK59: 32 | AL59: 0 | AS59: 285 | AZ59: 253 | BB59: 32
A60: Store 1 | B60: 110027 | C60: Outlet | D60: Burgrill | E60: 45962 | F60: RJ390594 | G60: swiggy | H60: 220980000000000 | I60: 29811 | J60: 45962.872 | K60: Sale | L60: No | M60: 614 | N60: -93.74 | O60: 0 | P60: 520.26 | Q60: 32 | R60: 0 | S60: -0.26 | T60: 0 | U60: 552 | V60: 552 | W60: 0 | X60: Swiggy | Y60: 124.83 | Z60: 12.23 | AA60: Burgrill-Swiggy | AB60: Burgrill | AC60: 4214 | AK60: 32 | AL60: 0 | AS60: 552 | AZ60: 520.26 | BB60: 32
A61: Store 1 | B61: 110027 | C61: Outlet | D61: Burgrill | E61: 45962 | F61: RJ390595 | G61: zomato | H61: 7437789894 | I61: 18528960 | J61: 45962.873 | K61: Sale | L61: No | M61: 656 | N61: -174.5 | O61: 0 | P61: 481.5 | Q61: 32 | R61: 0 | S61: 0 | T61: 0 | U61: 513.5 | V61: 513.5 | W61: 0 | X61: Zomato | Y61: 112.32 | Z61: 12.07 | AA61: Burgrill-Zomato | AB61: Burgrill | AC61: 9894 | AK61: 32 | AL61: 0 | AT61: 513.5 | AZ61: 481.5 | BC61: 32
A62: Store 1 | B62: 110027 | C62: Outlet | D62: Burgrill | E62: 45962 | F62: RJ390597 | G62: zomato | H62: 7434342785 | I62: 18528960 | J62: 45962.874 | K62: Sale | L62: No | M62: 1075 | N62: -314.5 | O62: 0 | P62: 760.5 | Q62: 32 | R62: 0 | S62: 0 | T62: 0 | U62: 792.5 | V62: 792.5 | W62: 0 | X62: Zomato | Y62: 208.85 | Z62: 22.86 | AA62: Burgrill-Zomato | AB62: Burgrill | AC62: 2785 | AK62: 32 | AL62: 0 | AT62: 792.5 | AZ62: 760.5 | BC62: 32
A63: Store 1 | B63: 110027 | C63: Outlet | D63: Burgrill | E63: 45962 | F63: RJ390598 | G63: POS | J63: 45962.887 | K63: Sale | L63: No | M63: 189 | N63: 0 | O63: 0 | P63: 189 | Q63: 0 | R63: 9.46 | S63: -0.46 | T63: 0 | U63: 198 | V63: 198 | W63: 0 | X63: Cash | Y63: 51.15 | Z63: 4.96 | AA63: Burgrill-Takeaway | AE63: RJFXN3YM | AF63: Burgrill | AG63: 8929758003 | AK63: 0 | AL63: 0 | AN63: 198 | AV63: 189 | AW63: 4.73 | AX63: 189 | AY63: 4.73 | AZ63: 189
A64: Store 1 | B64: 110027 | C64: Outlet | D64: Burgrill | E64: 45962 | F64: RJ390591 | G64: POS | J64: 45962.887 | K64: Sale | L64: No | M64: 307 | N64: 0 | O64: 0 | P64: 307 | Q64: 0 | R64: 15.36 | S64: -0.36 | T64: 0 | U64: 322 | V64: 322 | W64: 0 | X64: Card | Y64: 78.05 | Z64: 6.24 | AA64: Burgrill-Dine In | AB64: Dine In | AE64: RJFXN3YM | AF64: Burgrill | AG64: 8929758003 | AK64: 0 | AL64: 0 | AM64: 322 | AV64: 307 | AW64: 7.68 | AX64: 307 | AY64: 7.68 | AZ64: 307
A65: Store 1 | B65: 110027 | C65: Outlet | D65: Burgrill | E65: 45962 | F65: RJ390601 | G65: zomato | H65: 7421841456 | I65: 18528960 | J65: 45962.888 | K65: Sale | L65: No | M65: 229 | N65: -75 | O65: 0 | P65: 154 | Q65: 32 | R65: 0 | S65: 0 | T65: 0 | U65: 186 | V65: 186 | W65: 0 | X65: Zomato | Y65: 48.21 | Z65: 4.77 | AA65: Burgrill-Zomato | AB65: Burgrill | AC65: 1456 | AK65: 32 | AL65: 0 | AT65: 186 | AZ65: 154 | BC65: 32
A66: Store 1 | B66: 110027 | C66: Outlet | D66: Burgrill | E66: 45962 | F66: RJ390602 | G66: zomato | H66: 7432744523 | I66: 18528960 | J66: 45962.89 | K66: Sale | L66: No | M66: 319 | N66: -75 | O66: 0 | P66: 244 | Q66: 32 | R66: 0 | S66: 0 | T66: 0 | U66: 276 | V66: 276 | W66: 0 | X66: Zomato | Y66: 62.5 | Z66: 4.96 | AA66: Burgrill-Zomato | AB66: Burgrill | AC66: 4523 | AK66: 32 | AL66: 0 | AT66: 276 | AZ66: 244 | BC66: 32
A67: Store 1 | B67: 110027 | C67: Outlet | D67: Burgrill | E67: 45962 | F67: RJ390600 | G67: POS | J67: 45962.894 | K67: Sale | L67: No | M67: 339.43 | N67: 0 | O67: 0 | P67: 339.43 | Q67: 0 | R67: 16.98 | S67: -0.41 | T67: 0 | U67: 356 | V67: 356 | W67: 0 | X67: Cash | Y67: 77.59 | Z67: 4.24 | AA67: Burgrill-Dine In | AB67: Dine In | AE67: CSNWY5P7 | AF67: APAR | AG67: 9711820046 | AK67: 0 | AL67: 0 | AN67: 356 | AV67: 339.43 | AW67: 8.49 | AX67: 339.43 | AY67: 8.49 | AZ67: 339.43
A68: Store 1 | B68: 110027 | C68: Outlet | D68: Burgrill | E68: 45962 | F68: RJ390603 | G68: POS | J68: 45962.896 | K68: Sale | L68: No | M68: 189 | N68: 0 | O68: 0 | P68: 189 | Q68: 0 | R68: 9.46 | S68: -0.46 | T68: 0 | U68: 198 | V68: 198 | W68: 0 | X68: Cash | Y68: 51.15 | Z68: 1.96 | AA68: Burgrill-Dine In | AB68: Dine In | AE68: RJFXN3YM | AF68: Burgrill | AG68: 8929758003 | AK68: 0 | AL68: 0 | AN68: 198 | AV68: 189 | AW68: 4.73 | AX68: 189 | AY68: 4.73 | AZ68: 189
A69: Store 1 | B69: 110027 | C69: Outlet | D69: Burgrill | E69: 45962 | F69: RJ390599 | G69: POS | J69: 45962.897 | K69: Sale | L69: No | M69: 438 | N69: 0 | O69: 0 | P69: 438 | Q69: 0 | R69: 21.9 | S69: 0.1 | T69: 0 | U69: 460 | V69: 460 | W69: 0 | X69: Card | Y69: 104.26 | Z69: 3.92 | AA69: Burgrill-Dine In | AB69: Dine In | AE69: RJFXN3YM | AF69: Burgrill | AG69: 8929758003 | AK69: 0 | AL69: 0 | AM69: 460 | AV69: 438 | AW69: 10.95 | AX69: 438 | AY69: 10.95 | AZ69: 438
A70: Store 1 | B70: 110027 | C70: Outlet | D70: Burgrill | E70: 45962 | F70: RJ390581 | G70: POS | J70: 45962.897 | K70: Sale | L70: No | M70: 159 | N70: 0 | O70: 0 | P70: 159 | Q70: 0 | R70: 7.96 | S70: 0.04 | T70: 0 | U70: 167 | V70: 167 | W70: 0 | X70: Card | Y70: 29.83 | Z70: 5.5 | AA70: Burgrill-Takeaway | AE70: RJFXN3YM | AF70: Burgrill | AG70: 8929758003 | AK70: 0 | AL70: 0 | AM70: 167 | AV70: 159 | AW70: 3.98 | AX70: 159 | AY70: 3.98 | AZ70: 159
A71: Store 1 | B71: 110027 | C71: Outlet | D71: Burgrill | E71: 45962 | F71: RJ390580 | G71: POS | J71: 45962.897 | K71: Sale | L71: No | M71: 109 | N71: 0 | O71: 0 | P71: 109 | Q71: 0 | R71: 5.46 | S71: -0.46 | T71: 0 | U71: 114 | V71: 114 | W71: 0 | X71: Card | Y71: 24.63 | Z71: 4.96 | AA71: Burgrill-Takeaway | AE71: RJFXN3YM | AF71: Burgrill | AG71: 8929758003 | AK71: 0 | AL71: 0 | AM71: 114 | AV71: 109 | AW71: 2.73 | AX71: 109 | AY71: 2.73 | AZ71: 109
A72: Store 1 | B72: 110027 | C72: Outlet | D72: Burgrill | E72: 45962 | F72: RJ390571 | G72: POS | J72: 45962.898 | K72: Sale | L72: No | M72: 199 | N72: 0 | O72: 0 | P72: 199 | Q72: 0 | R72: 9.96 | S72: 0.04 | T72: 0 | U72: 209 | V72: 209 | W72: 0 | X72: Card | Y72: 44.84 | Z72: 2.82 | AA72: Burgrill-Dine In | AB72: Dine In | AE72: RJFXN3YM | AF72: Burgrill | AG72: 8929758003 | AK72: 0 | AL72: 0 | AM72: 209 | AV72: 199 | AW72: 4.98 | AX72: 199 | AY72: 4.98 | AZ72: 199
A73: Store 1 | B73: 110027 | C73: Outlet | D73: Burgrill | E73: 45962 | F73: RJ390596 | G73: POS | J73: 45962.898 | K73: Sale | L73: No | M73: 583.66 | N73: 0 | O73: 0 | P73: 583.66 | Q73: 0 | R73: 29.18 | S73: 0.16 | T73: 0 | U73: 613 | V73: 613 | W73: 0 | X73: Card | Y73: 141.79 | Z73: 9.14 | AA73: Burgrill-Dine In | AB73: Dine In | AE73: RJFXN3YM | AF73: Burgrill | AG73: 8929758003 | AK73: 0 | AL73: 0 | AM73: 613 | AV73: 583.66 | AW73: 14.59 | AX73: 583.66 | AY73: 14.59 | AZ73: 583.66
A74: Store 1 | B74: 110027 | C74: Outlet | D74: Burgrill | E74: 45962 | F74: RJ390605 | G74: zomato | H74: 7424855590 | I74: 18528960 | J74: 45962.899 | K74: Sale | L74: No | M74: 557 | N74: -100 | O74: 0 | P74: 457 | Q74: 32 | R74: 0 | S74: 0 | T74: 0 | U74: 489 | V74: 489 | W74: 0 | X74: Zomato | Y74: 122.27 | Z74: 13.74 | AA74: Burgrill-Zomato | AB74: Burgrill | AC74: 5590 | AK74: 32 | AL74: 0 | AT74: 489 | AZ74: 457 | BC74: 32
A75: Store 1 | B75: 110027 | C75: Outlet | D75: Burgrill | E75: 45962 | F75: RJ390606 | G75: swiggy | H75: 220983000000000 | I75: 29811 | J75: 45962.901 | K75: Sale | L75: No | M75: 258 | N75: -60 | O75: 0 | P75: 198 | Q75: 32 | R75: 0 | S75: 0 | T75: 0 | U75: 230 | V75: 230 | W75: 0 | X75: Swiggy | Y75: 45.84 | Z75: 3.92 | AA75: Burgrill-Swiggy | AB75: Burgrill | AC75: 7573 | AK75: 32 | AL75: 0 | AS75: 230 | AZ75: 198 | BB75: 32
A76: Store 1 | B76: 110027 | C76: Outlet | D76: Burgrill | E76: 45962 | F76: RJ390608 | G76: zomato | H76: 7436428619 | I76: 18528960 | J76: 45962.906 | K76: Sale | L76: No | M76: 366 | N76: -100 | O76: 0 | P76: 266 | Q76: 32 | R76: 0 | S76: 0 | T76: 0 | U76: 298 | V76: 298 | W76: 0 | X76: Zomato | Y76: 85.48 | Z76: 4.96 | AA76: Burgrill-Zomato | AB76: Burgrill | AC76: 8619 | AK76: 32 | AL76: 0 | AT76: 298 | AZ76: 266 | BC76: 32
A77: Store 1 | B77: 110027 | C77: Outlet | D77: Burgrill | E77: 45962 | F77: RJ390609 | G77: POS | J77: 45962.908 | K77: Sale | L77: No | M77: 177 | N77: 0 | O77: 0 | P77: 177 | Q77: 0 | R77: 8.86 | S77: 0.14 | T77: 0 | U77: 186 | V77: 186 | W77: 0 | X77: Cash | Y77: 46.48 | Z77: 5.88 | AA77: Burgrill-Takeaway | AE77: RJFXN3YM | AF77: Burgrill | AG77: 8929758003 | AK77: 0 | AL77: 0 | AN77: 186 | AV77: 177 | AW77: 4.43 | AX77: 177 | AY77: 4.43 | AZ77: 177
A78: Store 1 | B78: 110027 | C78: Outlet | D78: Burgrill | E78: 45962 | F78: RJ390610 | G78: swiggy | H78: 220984000000000 | I78: 29811 | J78: 45962.908 | K78: Sale | L78: No | M78: 646 | N78: -93.75 | O78: 0 | P78: 552.25 | Q78: 32 | R78: 0 | S78: -0.25 | T78: 0 | U78: 584 | V78: 584 | W78: 0 | X78: Swiggy | Y78: 136.41 | Z78: 8.34 | AA78: Burgrill-Swiggy | AB78: Burgrill | AC78: 8408 | AK78: 32 | AL78: 0 | AS78: 584 | AZ78: 552.25 | BB78: 32
A79: Store 1 | B79: 110027 | C79: Outlet | D79: Burgrill | E79: 45962 | F79: RJ390604 | G79: POS | J79: 45962.909 | K79: Sale | L79: No | M79: 299 | N79: 0 | O79: 0 | P79: 299 | Q79: 0 | R79: 14.96 | S79: 0.04 | T79: 0 | U79: 314 | V79: 314 | W79: 0 | X79: Cash | Y79: 77.14 | Z79: 8.72 | AA79: Burgrill-Dine In | AB79: Dine In | AE79: RJFXN3YM | AF79: Burgrill | AG79: 8929758003 | AK79: 0 | AL79: 0 | AN79: 314 | AV79: 299 | AW79: 7.48 | AX79: 299 | AY79: 7.48 | AZ79: 299
A80: Store 1 | B80: 110027 | C80: Outlet | D80: Burgrill | E80: 45962 | F80: RJ390612 | G80: swiggy | H80: 220984000000000 | I80: 29811 | J80: 45962.916 | K80: Sale | L80: No | M80: 404.66 | N80: -93.73 | O80: 0 | P80: 310.93 | Q80: 32 | R80: 0 | S80: 0.07 | T80: 0 | U80: 343 | V80: 343 | W80: 0 | X80: Swiggy | Y80: 87.21 | Z80: 10.41 | AA80: Burgrill-Swiggy | AB80: Burgrill | AC80: 5963 | AK80: 32 | AL80: 0 | AS80: 343 | AZ80: 310.93 | BB80: 32
A81: Store 1 | B81: 110027 | C81: Outlet | D81: Burgrill | E81: 45962 | F81: RJ390613 | G81: zomato | H81: 7434931967 | I81: 18528960 | J81: 45962.916 | K81: Sale | L81: No | M81: 449 | N81: -100 | O81: 0 | P81: 349 | Q81: 32 | R81: 0 | S81: 0 | T81: 0 | U81: 381 | V81: 381 | W81: 0 | X81: Zomato | Y81: 81.84 | Z81: 9.82 | AA81: Burgrill-Zomato | AB81: Burgrill | AC81: 1967 | AK81: 32 | AL81: 0 | AT81: 381 | AZ81: 349 | BC81: 32
A82: Store 1 | B82: 110027 | C82: Outlet | D82: Burgrill | E82: 45962 | F82: RJ390615 | G82: swiggy | H82: 220984000000000 | I82: 29811 | J82: 45962.919 | K82: Sale | L82: No | M82: 269 | N82: -93.75 | O82: 0 | P82: 175.25 | Q82: 32 | R82: 0 | S82: -0.25 | T82: 0 | U82: 207 | V82: 207 | W82: 0 | X82: Swiggy | Y82: 70.93 | Z82: 6.51 | AA82: Burgrill-Swiggy | AB82: Burgrill | AC82: 8457 | AK82: 32 | AL82: 0 | AS82: 207 | AZ82: 175.25 | BB82: 32
A83: Store 1 | B83: 110027 | C83: Outlet | D83: Burgrill | E83: 45962 | F83: RJ390617 | G83: zomato | H83: 7435517225 | I83: 18528960 | J83: 45962.926 | K83: Sale | L83: No | M83: 646 | N83: -174.5 | O83: 0 | P83: 471.5 | Q83: 32 | R83: 0 | S83: 0 | T83: 0 | U83: 503.5 | V83: 503.5 | W83: 0 | X83: Zomato | Y83: 127.44 | Z83: 12.36 | AA83: Burgrill-Zomato | AB83: Burgrill | AC83: 7225 | AK83: 32 | AL83: 0 | AT83: 503.5 | AZ83: 471.5 | BC83: 32
A84: Store 1 | B84: 110027 | C84: Outlet | D84: Burgrill | E84: 45962 | F84: RJ390618 | G84: zomato | H84: 7434136750 | I84: 18528960 | J84: 45962.926 | K84: Sale | L84: No | M84: 458 | N84: -100 | O84: 0 | P84: 358 | Q84: 32 | R84: 0 | S84: 0 | T84: 0 | U84: 390 | V84: 390 | W84: 0 | X84: Zomato | Y84: 95.27 | Z84: 9.73 | AA84: Burgrill-Zomato | AB84: Burgrill | AC84: 6750 | AK84: 32 | AL84: 0 | AT84: 390 | AZ84: 358 | BC84: 32
A85: Store 1 | B85: 110027 | C85: Outlet | D85: Burgrill | E85: 45962 | F85: RJ390619 | G85: swiggy | H85: 220985000000000 | I85: 29811 | J85: 45962.928 | K85: Sale | L85: No | M85: 238 | N85: -90 | O85: 0 | P85: 148 | Q85: 32 | R85: 0 | S85: 0 | T85: 0 | U85: 180 | V85: 180 | W85: 0 | X85: Swiggy | Y85: 43.9 | Z85: 3.92 | AA85: Burgrill-Swiggy | AB85: Burgrill | AC85: 9512 | AK85: 32 | AL85: 0 | AS85: 180 | AZ85: 148 | BB85: 32
A86: Store 1 | B86: 110027 | C86: Outlet | D86: Burgrill | E86: 45962 | F86: RJ390620 | G86: POS | J86: 45962.931 | K86: Sale | L86: No | M86: 179 | N86: 0 | O86: 0 | P86: 179 | Q86: 0 | R86: 8.96 | S86: 0.04 | T86: 0 | U86: 188 | V86: 188 | W86: 0 | X86: Card | Y86: 37.58 | Z86: 2.56 | AA86: Burgrill-Dine In | AB86: Dine In | AE86: RJFXN3YM | AF86: Burgrill | AG86: 8929758003 | AK86: 0 | AL86: 0 | AM86: 188 | AV86: 179 | AW86: 4.48 | AX86: 179 | AY86: 4.48 | AZ86: 179
A87: Store 1 | B87: 110027 | C87: Outlet | D87: Burgrill | E87: 45962 | F87: RJ390611 | G87: POS | J87: 45962.933 | K87: Sale | L87: No | M87: 1023 | N87: 0 | O87: 0 | P87: 1023 | Q87: 0 | R87: 51.16 | S87: -0.16 | T87: 0 | U87: 1074 | V87: 1074 | W87: 0 | X87: Card | Y87: 268.97 | Z87: 11.54 | AA87: Burgrill-Dine In | AB87: Dine In | AE87: RJFXN3YM | AF87: Burgrill | AG87: 8929758003 | AK87: 0 | AL87: 0 | AM87: 1074 | AV87: 1023 | AW87: 25.58 | AX87: 1023 | AY87: 25.58 | AZ87: 1023
A88: Store 1 | B88: 110027 | C88: Outlet | D88: Burgrill | E88: 45962 | F88: RJ390607 | G88: POS | J88: 45962.933 | K88: Sale | L88: No | M88: 625.43 | N88: 0 | O88: 0 | P88: 625.43 | Q88: 0 | R88: 31.28 | S88: 0.29 | T88: 0 | U88: 657 | V88: 657 | W88: 0 | X88: Card | Y88: 138.79 | Z88: 10.5 | AA88: Burgrill-Dine In | AB88: Dine In | AE88: RJFXN3YM | AF88: Burgrill | AG88: 8929758003 | AK88: 0 | AL88: 0 | AM88: 657 | AV88: 625.43 | AW88: 15.64 | AX88: 625.43 | AY88: 15.64 | AZ88: 625.43
A89: Store 1 | B89: 110027 | C89: Outlet | D89: Burgrill | E89: 45962 | F89: RJ390570 | G89: POS | J89: 45962.933 | K89: Sale | L89: No | M89: 1055 | N89: 0 | O89: 0 | P89: 1055 | Q89: 0 | R89: 52.76 | S89: 0.24 | T89: 0 | U89: 1108 | V89: 1108 | W89: 0 | X89: Card | Y89: 259.15 | Z89: 28.39 | AA89: Burgrill-Takeaway | AE89: GFCWJ7BX | AF89: karan | AG89: 9818679848 | AK89: 0 | AL89: 0 | AM89: 1108 | AV89: 1055 | AW89: 26.38 | AX89: 1055 | AY89: 26.38 | AZ89: 1055
A90: Store 1 | B90: 110027 | C90: Outlet | D90: Burgrill | E90: 45962 | F90: RJ390616 | G90: POS | J90: 45962.935 | K90: Sale | L90: No | M90: 196 | N90: 0 | O90: 0 | P90: 196 | Q90: 0 | R90: 9.8 | S90: 0.2 | T90: 0 | U90: 206 | V90: 206 | W90: 0 | X90: Card | Y90: 50.23 | Z90: 4.1 | AA90: Burgrill-Dine In | AB90: Dine In | AE90: Z3PZWUEE | AF90: dhruv | AG90: 9213555055 | AK90: 0 | AL90: 0 | AM90: 206 | AV90: 196 | AW90: 4.9 | AX90: 196 | AY90: 4.9 | AZ90: 196
A91: Store 1 | B91: 110027 | C91: Outlet | D91: Burgrill | E91: 45962 | F91: RJ390614 | G91: POS | J91: 45962.936 | K91: Sale | L91: No | M91: 189 | N91: 0 | O91: 0 | P91: 189 | Q91: 0 | R91: 9.46 | S91: -0.46 | T91: 0 | U91: 198 | V91: 198 | W91: 0 | X91: Cash | Y91: 47.06 | Z91: 1.96 | AA91: Burgrill-Dine In | AB91: Dine In | AE91: 7111VIGN | AF91: burgrill | AG91: 8929728003 | AK91: 0 | AL91: 0 | AN91: 198 | AV91: 189 | AW91: 4.73 | AX91: 189 | AY91: 4.73 | AZ91: 189
A92: Store 1 | B92: 110027 | C92: Outlet | D92: Burgrill | E92: 45962 | F92: RJ390565 | G92: POS | J92: 45962.936 | K92: Sale | L92: No | M92: 379 | N92: 0 | O92: 0 | P92: 379 | Q92: 0 | R92: 18.96 | S92: 0.04 | T92: 0 | U92: 398 | V92: 398 | W92: 0 | X92: Card | Y92: 98.28 | Z92: 8.72 | AA92: Burgrill-Dine In | AB92: Dine In | AE92: RZF7ACWG | AF92: sarabjeet | AG92: 9990003553 | AK92: 0 | AL92: 0 | AM92: 398 | AV92: 379 | AW92: 9.48 | AX92: 379 | AY92: 9.48 | AZ92: 379
A93: Store 1 | B93: 110027 | C93: Outlet | D93: Burgrill | E93: 45962 | F93: RJ390582 | G93: POS | J93: 45962.938 | K93: Sale | L93: No | M93: 356 | N93: 0 | O93: 0 | P93: 356 | Q93: 0 | R93: 17.8 | S93: 0.2 | T93: 0 | U93: 374 | V93: 374 | W93: 0 | X93: Card | Y93: 95.75 | Z93: 9.26 | AA93: Burgrill-Takeaway | AE93: RJFXN3YM | AF93: Burgrill | AG93: 8929758003 | AK93: 0 | AL93: 0 | AM93: 374 | AV93: 356 | AW93: 8.9 | AX93: 356 | AY93: 8.9 | AZ93: 356
A94: Store 1 | B94: 110027 | C94: Outlet | D94: Burgrill | E94: 45962 | F94: RJ390622 | G94: zomato | H94: 7439223267 | I94: 18528960 | J94: 45962.944 | K94: Sale | L94: No | M94: 478.43 | N94: -75 | O94: 0 | P94: 403.43 | Q94: 32 | R94: 0 | S94: 0 | T94: 0 | U94: 435.43 | V94: 435.43 | W94: 0 | X94: Zomato | Y94: 94.18 | Z94: 10.1 | AA94: Burgrill-Zomato | AB94: Burgrill | AC94: 3267 | AK94: 32 | AL94: 0 | AT94: 435.43 | AZ94: 403.43 | BC94: 32
A95: Store 1 | B95: 110027 | C95: Outlet | D95: Burgrill | E95: 45962 | F95: RJ390626 | G95: swiggy | H95: 220988000000000 | I95: 29811 | J95: 45962.96 | K95: Sale | L95: No | M95: 417 | N95: -93.75 | O95: 0 | P95: 323.25 | Q95: 32 | R95: 0 | S95: -0.25 | T95: 0 | U95: 355 | V95: 355 | W95: 0 | X95: Swiggy | Y95: 81.96 | Z95: 10.46 | AA95: Burgrill-Swiggy | AB95: Burgrill | AC95: 4044 | AK95: 32 | AL95: 0 | AS95: 355 | AZ95: 323.25 | BB95: 32
A96: Store 1 | B96: 110027 | C96: Outlet | D96: Burgrill | E96: 45962 | F96: RJ390627 | G96: POS | J96: 45962.968 | K96: Sale | L96: No | M96: 379 | N96: 0 | O96: 0 | P96: 379 | Q96: 0 | R96: 18.96 | S96: 0.04 | T96: 0 | U96: 398 | V96: 398 | W96: 0 | X96: Cash | Y96: 98.28 | Z96: 8.72 | AA96: Burgrill-Dine In | AB96: Dine In | AE96: RJFXN3YM | AF96: Burgrill | AG96: 8929758003 | AK96: 0 | AL96: 0 | AN96: 398 | AV96: 379 | AW96: 9.48 | AX96: 379 | AY96: 9.48 | AZ96: 379
A97: Store 1 | B97: 110027 | C97: Outlet | D97: Burgrill | E97: 45962 | F97: RJ390630 | G97: swiggy | H97: 220989000000000 | I97: 29811 | J97: 45962.97 | K97: Sale | L97: No | M97: 218 | N97: -90 | O97: 0 | P97: 128 | Q97: 32 | R97: 0 | S97: 0 | T97: 0 | U97: 160 | V97: 160 | W97: 0 | X97: Swiggy | Y97: 41.43 | Z97: 3.92 | AA97: Burgrill-Swiggy | AB97: Burgrill | AC97: 2888 | AK97: 32 | AL97: 0 | AS97: 160 | AZ97: 128 | BB97: 32
A98: Store 1 | B98: 110027 | C98: Outlet | D98: Burgrill | E98: 45962 | F98: RJ390631 | G98: POS | J98: 45962.974 | K98: Sale | L98: No | M98: 239 | N98: 0 | O98: 0 | P98: 239 | Q98: 0 | R98: 11.96 | S98: 0.04 | T98: 0 | U98: 251 | V98: 251 | W98: 0 | X98: Card | Y98: 67.25 | Z98: 2.9 | AA98: Burgrill-Dine In | AB98: Dine In | AE98: RJFXN3YM | AF98: Burgrill | AG98: 8929758003 | AK98: 0 | AL98: 0 | AM98: 251 | AV98: 239 | AW98: 5.98 | AX98: 239 | AY98: 5.98 | AZ98: 239
A99: Store 1 | B99: 110027 | C99: Outlet | D99: Burgrill | E99: 45962 | F99: RJ390632 | G99: POS | J99: 45962.974 | K99: Sale | L99: No | M99: 179 | N99: 0 | O99: 0 | P99: 179 | Q99: 0 | R99: 8.96 | S99: 0.04 | T99: 0 | U99: 188 | V99: 188 | W99: 0 | X99: Card | Y99: 35.27 | Z99: 8.05 | AA99: Burgrill-Dine In | AB99: Dine In | AE99: RJFXN3YM | AF99: Burgrill | AG99: 8929758003 | AK99: 0 | AL99: 0 | AM99: 188 | AV99: 179 | AW99: 4.48 | AX99: 179 | AY99: 4.48 | AZ99: 179
A100: Store 1 | B100: 110027 | C100: Outlet | D100: Burgrill | E100: 45962 | F100: RJ390629 | G100: POS | J100: 45962.974 | K100: Sale | L100: No | M100: 627 | N100: 0 | O100: 0 | P100: 627 | Q100: 0 | R100: 31.36 | S100: -0.36 | T100: 0 | U100: 658 | V100: 658 | W100: 0 | X100: Card | Y100: 188.73 | Z100: 7.76 | AA100: Burgrill-Dine In | AB100: Dine In | AE100: RJFXN3YM | AF100: Burgrill | AG100: 8929758003 | AK100: 0 | AL100: 0 | AM100: 658 | AV100: 627 | AW100: 15.68 | AX100: 627 | AY100: 15.68 | AZ100: 627
...

Sheet Main
A1: Branch Name | B1: Branch Code | C1: BranchLabels | D1: Business Brand | E1: Business Date | F1: Invoice Number | G1: Order Source | H1: Order_source_1 | I1: Source Order Number | J1: Source Outlet Id | K1: Invoice Date | L1: Date | M1: Day | N1: Month | O1: Hours | P1: Week | Q1: Advance Order | R1: Gross Amount | S1: Discounts | T1: Discount % | U1: Net Amount | V1: Other Charge Amount | W1: Taxes | X1: Rounding | Y1: Total | Z1: Paid Amount | AA1: Payment Modes | AB1: Materials Cost | AC1: Supplies Cost | AD1: Channel | AE1: Channel Label | AF1: Label | AG1: Label | AH1: Session | AI1: Customer Id | AJ1: Customer Name | AK1: Customer Phone | AL1: Customer Tax Id | AM1: Customer State | AN1: Statement Number | AO1: Charges Amount (Initial) | AP1: Charges Amount (Removed) | AQ1: Payment-Card | AR1: Payment-Cash | AS1: Payment-Dineout Pay | AT1: Payment-magicpin | AU1: Payment-Magicpin Pay | AV1: Payment-Paytm | AW1: Payment-Swiggy | AX1: Payment-Zomato | AY1: Payment-Zomato District | AZ1: CGST 2.5% Value | BA1: CGST 2.5% Amount | BB1: SGST 2.5% Value | BC1: SGST 2.5% Amount | BD1: Paid Amount | BE1: Account-Burgrill | BF1: Account-The Sausage Fest | BG1: Consolidated revenue to Burgrill | BH1: Charge-Packing Charges | BI1: Charge-Restaurant Packaging Charges
A2: Store 1 | B2: 110027 | C2: Outlet | D2: Burgrill | E2: 45962 | F2: RJ390531 | G2: zomato | H2: =IF(G2="POS","Direct Sale","Aggregator") -> Aggregator | I2: 7430059910 | J2: 18528960 | K2: 45962.518 | L2: =VALUE(DAY(K2)) -> 1 | M2: =TEXT(K2,"dddd") -> Saturday | N2: =TEXT(K2,"MMMM") -> November | O2: 0.51805556 | P2: =_xlfn.IFS(L2<=7,"Week 1",L2<=15, "Week 2",L2<=23,"Week 3",L2<=30,"Week 4") -> Week 1 | Q2: No | R2: 257 | S2: 0 | T2: =ABS((S2/R2)*100) -> 0 | U2: 257 | V2: 32 | W2: 0 | X2: 0 | Y2: 289 | Z2: 289 | AA2: Zomato | AB2: 52.81 | AC2: 3.92 | AD2: Zomato | AE2: Burgrill | AF2: 9910 | AG2: 9910 | AO2: 32 | AP2: 0 | AX2: 289 | BD2: 289 | BE2: 257 | BG2: =BE2+BF2 -> 257 | BI2: 32
A3: Store 1 | B3: 110027 | C3: Outlet | D3: Burgrill | E3: 45962 | F3: RJ390532 | G3: swiggy | H3: =IF(G3="POS","Direct Sale","Aggregator") -> Aggregator | I3: 220952000000000 | J3: 29811 | K3: 45962.544 | L3: =VALUE(DAY(K3)) -> 1 | M3: =TEXT(K3,"dddd") -> Saturday | N3: =TEXT(K3,"MMMM") -> November | O3: 0.54375 | P3: =_xlfn.IFS(L3<=7,"Week 1",L3<=15, "Week 2",L3<=23,"Week 3",L3<=30,"Week 4") -> Week 1 | Q3: No | R3: 576 | S3: -93.74 | T3: =ABS((S3/R3)*100) -> 16.274306 | U3: 482.26 | V3: 32 | W3: 0 | X3: -0.26 | Y3: 514 | Z3: 514 | AA3: Swiggy | AB3: 126.08 | AC3: 9.76 | AD3: Swiggy | AE3: Burgrill | AF3: 5597 | AG3: 5597 | AO3: 32 | AP3: 0 | AW3: 514 | BD3: 514 | BE3: 482.26 | BG3: =BE3+BF3 -> 482.26 | BH3: 32
A4: Store 1 | B4: 110027 | C4: Outlet | D4: Burgrill | E4: 45962 | F4: RJ390530 | G4: POS | H4: =IF(G4="POS","Direct Sale","Aggregator") -> Direct Sale | K4: 45962.565 | L4: =VALUE(DAY(K4)) -> 1 | M4: =TEXT(K4,"dddd") -> Saturday | N4: =TEXT(K4,"MMMM") -> November | O4: 0.56458333 | P4: =_xlfn.IFS(L4<=7,"Week 1",L4<=15, "Week 2",L4<=23,"Week 3",L4<=30,"Week 4") -> Week 1 | Q4: No | R4: 59 | S4: 0 | T4: =ABS((S4/R4)*100) -> 0 | U4: 59 | V4: 0 | W4: 2.96 | X4: 0.04 | Y4: 62 | Z4: 62 | AA4: Cash | AB4: 15.49 | AC4: 1.96 | AD4: Takeaway | AI4: 4VS4ZNEI | AJ4: vipin | AK4: 9990930244 | AO4: 0 | AP4: 0 | AR4: 62 | AZ4: 59 | BA4: 1.48 | BB4: 59 | BC4: 1.48 | BD4: 62 | BE4: 59 | BG4: =BE4+BF4 -> 59
A5: Store 1 | B5: 110027 | C5: Outlet | D5: Burgrill | E5: 45962 | F5: RJ390529 | G5: POS | H5: =IF(G5="POS","Direct Sale","Aggregator") -> Direct Sale | K5: 45962.565 | L5: =VALUE(DAY(K5)) -> 1 | M5: =TEXT(K5,"dddd") -> Saturday | N5: =TEXT(K5,"MMMM") -> November | O5: 0.56458333 | P5: =_xlfn.IFS(L5<=7,"Week 1",L5<=15, "Week 2",L5<=23,"Week 3",L5<=30,"Week 4") -> Week 1 | Q5: No | R5: 159 | S5: 0 | T5: =ABS((S5/R5)*100) -> 0 | U5: 159 | V5: 0 | W5: 7.96 | X5: 0.04 | Y5: 167 | Z5: 167 | AA5: Card | AB5: 29.83 | AC5: 2.5 | AD5: Burgrill Dine In | AE5: Dine In | AI5: R7ZUEYAL | AJ5: naman | AK5: 9267927604 | AO5: 0 | AP5: 0 | AQ5: 167 | AZ5: 159 | BA5: 3.98 | BB5: 159 | BC5: 3.98 | BD5: 167 | BE5: 159 | BG5: =BE5+BF5 -> 159
A6: Store 1 | B6: 110027 | C6: Outlet | D6: Burgrill | E6: 45962 | F6: RJ390533 | G6: zomato | H6: =IF(G6="POS","Direct Sale","Aggregator") -> Aggregator | I6: 7436034135 | J6: 18528960 | K6: 45962.568 | L6: =VALUE(DAY(K6)) -> 1 | M6: =TEXT(K6,"dddd") -> Saturday | N6: =TEXT(K6,"MMMM") -> November | O6: 0.56805556 | P6: =_xlfn.IFS(L6<=7,"Week 1",L6<=15, "Week 2",L6<=23,"Week 3",L6<=30,"Week 4") -> Week 1 | Q6: No | R6: 418 | S6: -75 | T6: =ABS((S6/R6)*100) -> 17.942584 | U6: 343 | V6: 32 | W6: 0 | X6: 0 | Y6: 375 | Z6: 375 | AA6: Zomato | AB6: 80.87 | AC6: 4.77 | AD6: Zomato | AE6: Burgrill | AF6: 4135 | AG6: 4135 | AO6: 32 | AP6: 0 | AX6: 375 | BD6: 375 | BE6: 343 | BG6: =BE6+BF6 -> 343 | BI6: 32
A7: Store 1 | B7: 110027 | C7: Outlet | D7: Burgrill | E7: 45962 | F7: RJ390537 | G7: zomato | H7: =IF(G7="POS","Direct Sale","Aggregator") -> Aggregator | I7: 7436304288 | J7: 18528960 | K7: 45962.595 | L7: =VALUE(DAY(K7)) -> 1 | M7: =TEXT(K7,"dddd") -> Saturday | N7: =TEXT(K7,"MMMM") -> November | O7: 0.59513889 | P7: =_xlfn.IFS(L7<=7,"Week 1",L7<=15, "Week 2",L7<=23,"Week 3",L7<=30,"Week 4") -> Week 1 | Q7: No | R7: 359 | S7: -75 | T7: =ABS((S7/R7)*100) -> 20.891365 | U7: 284 | V7: 32 | W7: 0 | X7: 0 | Y7: 316 | Z7: 316 | AA7: Zomato | AB7: 77.14 | AC7: 9.82 | AD7: Zomato | AE7: Burgrill | AF7: 4288 | AG7: 4288 | AO7: 32 | AP7: 0 | AX7: 316 | BD7: 316 | BE7: 284 | BG7: =BE7+BF7 -> 284 | BI7: 32
A8: Store 1 | B8: 110027 | C8: Outlet | D8: Burgrill | E8: 45962 | F8: RJ390538 | G8: swiggy | H8: =IF(G8="POS","Direct Sale","Aggregator") -> Aggregator | I8: 220957000000000 | J8: 29811 | K8: 45962.6 | L8: =VALUE(DAY(K8)) -> 1 | M8: =TEXT(K8,"dddd") -> Saturday | N8: =TEXT(K8,"MMMM") -> November | O8: 0.6 | P8: =_xlfn.IFS(L8<=7,"Week 1",L8<=15, "Week 2",L8<=23,"Week 3",L8<=30,"Week 4") -> Week 1 | Q8: No | R8: 508 | S8: -200 | T8: =ABS((S8/R8)*100) -> 39.370079 | U8: 308 | V8: 32 | W8: 0 | X8: 0 | Y8: 340 | Z8: 340 | AA8: Swiggy | AB8: 74.34 | AC8: 3.38 | AD8: Swiggy | AE8: Burgrill | AF8: 4258 | AG8: 4258 | AO8: 32 | AP8: 0 | AW8: 340 | BD8: 340 | BE8: 308 | BG8: =BE8+BF8 -> 308 | BH8: 32
A9: Store 1 | B9: 110027 | C9: Outlet | D9: Burgrill | E9: 45962 | F9: RJ390539 | G9: zomato | H9: =IF(G9="POS","Direct Sale","Aggregator") -> Aggregator | I9: 7436617919 | J9: 18528960 | K9: 45962.612 | L9: =VALUE(DAY(K9)) -> 1 | M9: =TEXT(K9,"dddd") -> Saturday | N9: =TEXT(K9,"MMMM") -> November | O9: 0.61180556 | P9: =_xlfn.IFS(L9<=7,"Week 1",L9<=15, "Week 2",L9<=23,"Week 3",L9<=30,"Week 4") -> Week 1 | Q9: No | R9: 308 | S9: -100 | T9: =ABS((S9/R9)*100) -> 32.467532 | U9: 208 | V9: 32 | W9: 0 | X9: 0 | Y9: 240 | Z9: 240 | AA9: Zomato | AB9: 56.44 | AC9: 10.56 | AD9: Zomato | AE9: Burgrill | AF9: 7919 | AG9: 7919 | AO9: 32 | AP9: 0 | AX9: 240 | BD9: 240 | BE9: 208 | BG9: =BE9+BF9 -> 208 | BI9: 32
A10: Store 1 | B10: 110027 | C10: Outlet | D10: Burgrill | E10: 45962 | F10: RJ390540 | G10: swiggy | H10: =IF(G10="POS","Direct Sale","Aggregator") -> Aggregator | I10: 220958000000000 | J10: 29811 | K10: 45962.617 | L10: =VALUE(DAY(K10)) -> 1 | M10: =TEXT(K10,"dddd") -> Saturday | N10: =TEXT(K10,"MMMM") -> November | O10: 0.61666667 | P10: =_xlfn.IFS(L10<=7,"Week 1",L10<=15, "Week 2",L10<=23,"Week 3",L10<=30,"Week 4") -> Week 1 | Q10: No | R10: 508 | S10: -93.74 | T10: =ABS((S10/R10)*100) -> 18.452756 | U10: 414.26 | V10: 32 | W10: 0 | X10: -0.26 | Y10: 446 | Z10: 446 | AA10: Swiggy | AB10: 94.86 | AC10: 13.74 | AD10: Swiggy | AE10: Burgrill | AF10: 7113 | AG10: 7113 | AO10: 32 | AP10: 0 | AW10: 446 | BD10: 446 | BE10: 414.26 | BG10: =BE10+BF10 -> 414.26 | BH10: 32
A11: Store 1 | B11: 110027 | C11: Outlet | D11: Burgrill | E11: 45962 | F11: RJ390541 | G11: swiggy | H11: =IF(G11="POS","Direct Sale","Aggregator") -> Aggregator | I11: 220959000000000 | J11: 29811 | K11: 45962.624 | L11: =VALUE(DAY(K11)) -> 1 | M11: =TEXT(K11,"dddd") -> Saturday | N11: =TEXT(K11,"MMMM") -> November | O11: 0.62430556 | P11: =_xlfn.IFS(L11<=7,"Week 1",L11<=15, "Week 2",L11<=23,"Week 3",L11<=30,"Week 4") -> Week 1 | Q11: No | R11: 393.28 | S11: -93.75 | T11: =ABS((S11/R11)*100) -> 23.837978 | U11: 299.53 | V11: 32 | W11: 0 | X11: 0.47 | Y11: 332 | Z11: 332 | AA11: Swiggy | AB11: 91.25 | AC11: 5.79 | AD11: Swiggy | AE11: Burgrill | AF11: 124 | AG11: 124 | AO11: 32 | AP11: 0 | AW11: 332 | BD11: 332 | BE11: 299.53 | BG11: =BE11+BF11 -> 299.53 | BH11: 32
A12: Store 1 | B12: 110027 | C12: Outlet | D12: Burgrill | E12: 45962 | F12: RJ390542 | G12: swiggy | H12: =IF(G12="POS","Direct Sale","Aggregator") -> Aggregator | I12: 220959000000000 | J12: 29811 | K12: 45962.626 | L12: =VALUE(DAY(K12)) -> 1 | M12: =TEXT(K12,"dddd") -> Saturday | N12: =TEXT(K12,"MMMM") -> November | O12: 0.62569444 | P12: =_xlfn.IFS(L12<=7,"Week 1",L12<=15, "Week 2",L12<=23,"Week 3",L12<=30,"Week 4") -> Week 1 | Q12: No | R12: 268 | S12: -93.75 | T12: =ABS((S12/R12)*100) -> 34.981343 | U12: 174.25 | V12: 32 | W12: 0 | X12: -0.25 | Y12: 206 | Z12: 206 | AA12: Swiggy | AB12: 49.33 | AC12: 7.46 | AD12: Swiggy | AE12: Burgrill | AF12: 4459 | AG12: 4459 | AO12: 32 | AP12: 0 | AW12: 206 | BD12: 206 | BE12: 174.25 | BG12: =BE12+BF12 -> 174.25 | BH12: 32
A13: Store 1 | B13: 110027 | C13: Outlet | D13: Burgrill | E13: 45962 | F13: RJ390543 | G13: zomato | H13: =IF(G13="POS","Direct Sale","Aggregator") -> Aggregator | I13: 7435937715 | J13: 18528960 | K13: 45962.64 | L13: =VALUE(DAY(K13)) -> 1 | M13: =TEXT(K13,"dddd") -> Saturday | N13: =TEXT(K13,"MMMM") -> November | O13: 0.64027778 | P13: =_xlfn.IFS(L13<=7,"Week 1",L13<=15, "Week 2",L13<=23,"Week 3",L13<=30,"Week 4") -> Week 1 | Q13: No | R13: 698 | S13: -349 | T13: =ABS((S13/R13)*100) -> 50 | U13: 349 | V13: 32 | W13: 0 | X13: 0 | Y13: 381 | Z13: 381 | AA13: Zomato | AB13: 129.66 | AC13: 9.54 | AD13: Zomato | AE13: Burgrill | AF13: 7715 | AG13: 7715 | AO13: 32 | AP13: 0 | AX13: 381 | BD13: 381 | BE13: 349 | BG13: =BE13+BF13 -> 349 | BI13: 32
A14: Store 1 | B14: 110027 | C14: Outlet | D14: Burgrill | E14: 45962 | F14: RJ390544 | G14: zomato | H14: =IF(G14="POS","Direct Sale","Aggregator") -> Aggregator | I14: 7435794679 | J14: 18528960 | K14: 45962.65 | L14: =VALUE(DAY(K14)) -> 1 | M14: =TEXT(K14,"dddd") -> Saturday | N14: =TEXT(K14,"MMMM") -> November | O14: 0.65 | P14: =_xlfn.IFS(L14<=7,"Week 1",L14<=15, "Week 2",L14<=23,"Week 3",L14<=30,"Week 4") -> Week 1 | Q14: No | R14: 574.66 | S14: -199.5 | T14: =ABS((S14/R14)*100) -> 34.71618 | U14: 375.16 | V14: 32 | W14: 0 | X14: 0 | Y14: 407.16 | Z14: 407.16 | AA14: Zomato | AB14: 99.34 | AC14: 4.06 | AD14: Zomato | AE14: Burgrill | AF14: 4679 | AG14: 4679 | AO14: 32 | AP14: 0 | AX14: 407.16 | BD14: 407.16 | BE14: 375.16 | BG14: =BE14+BF14 -> 375.16 | BI14: 32
A15: Store 1 | B15: 110027 | C15: Outlet | D15: Burgrill | E15: 45962 | F15: RJ390545 | G15: swiggy | H15: =IF(G15="POS","Direct Sale","Aggregator") -> Aggregator | I15: 220962000000000 | J15: 29811 | K15: 45962.656 | L15: =VALUE(DAY(K15)) -> 1 | M15: =TEXT(K15,"dddd") -> Saturday | N15: =TEXT(K15,"MMMM") -> November | O15: 0.65625 | P15: =_xlfn.IFS(L15<=7,"Week 1",L15<=15, "Week 2",L15<=23,"Week 3",L15<=30,"Week 4") -> Week 1 | Q15: No | R15: 258 | S15: -93.75 | T15: =ABS((S15/R15)*100) -> 36.337209 | U15: 164.25 | V15: 32 | W15: 0 | X15: -0.25 | Y15: 196 | Z15: 196 | AA15: Swiggy | AB15: 48.54 | AC15: 7.02 | AD15: Swiggy | AE15: Burgrill | AF15: 3213 | AG15: 3213 | AO15: 32 | AP15: 0 | AW15: 196 | BD15: 196 | BE15: 164.25 | BG15: =BE15+BF15 -> 164.25 | BH15: 32
A16: Store 1 | B16: 110027 | C16: Outlet | D16: Burgrill | E16: 45962 | F16: RJ390534 | G16: POS | H16: =IF(G16="POS","Direct Sale","Aggregator") -> Direct Sale | K16: 45962.669 | L16: =VALUE(DAY(K16)) -> 1 | M16: =TEXT(K16,"dddd") -> Saturday | N16: =TEXT(K16,"MMMM") -> November | O16: 0.66875 | P16: =_xlfn.IFS(L16<=7,"Week 1",L16<=15, "Week 2",L16<=23,"Week 3",L16<=30,"Week 4") -> Week 1 | Q16: No | R16: 288 | S16: 0 | T16: =ABS((S16/R16)*100) -> 0 | U16: 288 | V16: 0 | W16: 14.4 | X16: -0.4 | Y16: 302 | Z16: 302 | AA16: Card | AB16: 68.99 | AC16: 3.92 | AD16: Burgrill Dine In | AE16: Dine In | AI16: RJFXN3YM | AJ16: Burgrill | AK16: 8929758003 | AO16: 0 | AP16: 0 | AQ16: 302 | AZ16: 288 | BA16: 7.2 | BB16: 288 | BC16: 7.2 | BD16: 302 | BE16: 288 | BG16: =BE16+BF16 -> 288
A17: Store 1 | B17: 110027 | C17: Outlet | D17: Burgrill | E17: 45962 | F17: RJ390535 | G17: POS | H17: =IF(G17="POS","Direct Sale","Aggregator") -> Direct Sale | K17: 45962.669 | L17: =VALUE(DAY(K17)) -> 1 | M17: =TEXT(K17,"dddd") -> Saturday | N17: =TEXT(K17,"MMMM") -> November | O17: 0.66944444 | P17: =_xlfn.IFS(L17<=7,"Week 1",L17<=15, "Week 2",L17<=23,"Week 3",L17<=30,"Week 4") -> Week 1 | Q17: No | R17: 356 | S17: 0 | T17: =ABS((S17/R17)*100) -> 0 | U17: 356 | V17: 0 | W17: 17.8 | X17: 0.2 | Y17: 374 | Z17: 374 | AA17: Card | AB17: 100.44 | AC17: 8.16 | AD17: Burgrill Dine In | AE17: Dine In | AI17: BCTCUL8A | AJ17: ms | AK17: 8171020359 | AO17: 0 | AP17: 0 | AQ17: 374 | AZ17: 356 | BA17: 8.9 | BB17: 356 | BC17: 8.9 | BD17: 374 | BE17: 356 | BG17: =BE17+BF17 -> 356
A18: Store 1 | B18: 110027 | C18: Outlet | D18: Burgrill | E18: 45962 | F18: RJ390536 | G18: POS | H18: =IF(G18="POS","Direct Sale","Aggregator") -> Direct Sale | K18: 45962.669 | L18: =VALUE(DAY(K18)) -> 1 | M18: =TEXT(K18,"dddd") -> Saturday | N18: =TEXT(K18,"MMMM") -> November | O18: 0.66944444 | P18: =_xlfn.IFS(L18<=7,"Week 1",L18<=15, "Week 2",L18<=23,"Week 3",L18<=30,"Week 4") -> Week 1 | Q18: No | R18: 66.66 | S18: 0 | T18: =ABS((S18/R18)*100) -> 0 | U18: 66.66 | V18: 0 | W18: 3.34 | X18: 0 | Y18: 70 | Z18: 70 | AA18: Card | AB18: 25 | AC18: 0 | AD18: Burgrill Dine In | AE18: Dine In | AI18: RJFXN3YM | AJ18: Burgrill | AK18: 8929758003 | AO18: 0 | AP18: 0 | AQ18: 70 | AZ18: 66.66 | BA18: 1.67 | BB18: 66.66 | BC18: 1.67 | BD18: 70 | BE18: 66.66 | BG18: =BE18+BF18 -> 66.66
A19: Store 1 | B19: 110027 | C19: Outlet | D19: Burgrill | E19: 45962 | F19: RJ390546 | G19: swiggy | H19: =IF(G19="POS","Direct Sale","Aggregator") -> Aggregator | I19: 220963000000000 | J19: 29811 | K19: 45962.676 | L19: =VALUE(DAY(K19)) -> 1 | M19: =TEXT(K19,"dddd") -> Saturday | N19: =TEXT(K19,"MMMM") -> November | O19: 0.67638889 | P19: =_xlfn.IFS(L19<=7,"Week 1",L19<=15, "Week 2",L19<=23,"Week 3",L19<=30,"Week 4") -> Week 1 | Q19: No | R19: 545 | S19: -130 | T19: =ABS((S19/R19)*100) -> 23.853211 | U19: 415 | V19: 32 | W19: 0 | X19: 0 | Y19: 447 | Z19: 447 | AA19: Swiggy | AB19: 99.73 | AC19: 9.8 | AD19: Swiggy | AE19: Burgrill | AF19: 5595 | AG19: 5595 | AO19: 32 | AP19: 0 | AW19: 447 | BD19: 447 | BE19: 415 | BG19: =BE19+BF19 -> 415 | BH19: 32
A20: Store 1 | B20: 110027 | C20: Outlet | D20: Burgrill | E20: 45962 | F20: RJ390547 | G20: swiggy | H20: =IF(G20="POS","Direct Sale","Aggregator") -> Aggregator | I20: 220963000000000 | J20: 29811 | K20: 45962.677 | L20: =VALUE(DAY(K20)) -> 1 | M20: =TEXT(K20,"dddd") -> Saturday | N20: =TEXT(K20,"MMMM") -> November | O20: 0.67708333 | P20: =_xlfn.IFS(L20<=7,"Week 1",L20<=15, "Week 2",L20<=23,"Week 3",L20<=30,"Week 4") -> Week 1 | Q20: No | R20: 395 | S20: -74.99 | T20: =ABS((S20/R20)*100) -> 18.98481 | U20: 320.01 | V20: 32 | W20: 0 | X20: -0.01 | Y20: 352 | Z20: 352 | AA20: Swiggy | AB20: 74.43 | AC20: 8.88 | AD20: Swiggy | AE20: Burgrill | AF20: 5423 | AG20: 5423 | AO20: 32 | AP20: 0 | AW20: 352 | BD20: 352 | BE20: 320.01 | BG20: =BE20+BF20 -> 320.01 | BH20: 32
A21: Store 1 | B21: 110027 | C21: Outlet | D21: Burgrill | E21: 45962 | F21: RJ390549 | G21: POS | H21: =IF(G21="POS","Direct Sale","Aggregator") -> Direct Sale | K21: 45962.697 | L21: =VALUE(DAY(K21)) -> 1 | M21: =TEXT(K21,"dddd") -> Saturday | N21: =TEXT(K21,"MMMM") -> November | O21: 0.69652778 | P21: =_xlfn.IFS(L21<=7,"Week 1",L21<=15, "Week 2",L21<=23,"Week 3",L21<=30,"Week 4") -> Week 1 | Q21: No | R21: 159 | S21: 0 | T21: =ABS((S21/R21)*100) -> 0 | U21: 159 | V21: 0 | W21: 7.96 | X21: 0.04 | Y21: 167 | Z21: 167 | AA21: Cash | AB21: 29.83 | AC21: 2.5 | AD21: Burgrill Dine In | AE21: Dine In | AI21: E9WZ2UG5 | AJ21: sidhi | AK21: 7817653551 | AO21: 0 | AP21: 0 | AR21: 167 | AZ21: 159 | BA21: 3.98 | BB21: 159 | BC21: 3.98 | BD21: 167 | BE21: 159 | BG21: =BE21+BF21 -> 159
A22: Store 1 | B22: 110027 | C22: Outlet | D22: Burgrill | E22: 45962 | F22: RJ390550 | G22: swiggy | H22: =IF(G22="POS","Direct Sale","Aggregator") -> Aggregator | I22: 220966000000000 | J22: 29811 | K22: 45962.702 | L22: =VALUE(DAY(K22)) -> 1 | M22: =TEXT(K22,"dddd") -> Saturday | N22: =TEXT(K22,"MMMM") -> November | O22: 0.70208333 | P22: =_xlfn.IFS(L22<=7,"Week 1",L22<=15, "Week 2",L22<=23,"Week 3",L22<=30,"Week 4") -> Week 1 | Q22: No | R22: 646 | S22: -93.75 | T22: =ABS((S22/R22)*100) -> 14.512384 | U22: 552.25 | V22: 32 | W22: 0 | X22: -0.25 | Y22: 584 | Z22: 584 | AA22: Swiggy | AB22: 150.41 | AC22: 14.78 | AD22: Swiggy | AE22: Burgrill | AF22: 379 | AG22: 379 | AO22: 32 | AP22: 0 | AW22: 584 | BD22: 584 | BE22: 552.25 | BG22: =BE22+BF22 -> 552.25 | BH22: 32
A23: Store 1 | B23: 110027 | C23: Outlet | D23: Burgrill | E23: 45962 | F23: RJ390551 | G23: POS | H23: =IF(G23="POS","Direct Sale","Aggregator") -> Direct Sale | K23: 45962.706 | L23: =VALUE(DAY(K23)) -> 1 | M23: =TEXT(K23,"dddd") -> Saturday | N23: =TEXT(K23,"MMMM") -> November | O23: 0.70555556 | P23: =_xlfn.IFS(L23<=7,"Week 1",L23<=15, "Week 2",L23<=23,"Week 3",L23<=30,"Week 4") -> Week 1 | Q23: No | R23: 369 | S23: 0 | T23: =ABS((S23/R23)*100) -> 0 | U23: 369 | V23: 0 | W23: 18.46 | X23: -0.46 | Y23: 387 | Z23: 387 | AA23: Cash | AB23: 99.73 | AC23: 8.72 | AD23: Burgrill Dine In | AE23: Dine In | AI23: GIDIRMS3 | AJ23: hare krishna | AK23: 9999669771 | AO23: 0 | AP23: 0 | AR23: 387 | AZ23: 369 | BA23: 9.23 | BB23: 369 | BC23: 9.23 | BD23: 387 | BE23: 369 | BG23: =BE23+BF23 -> 369
A24: Store 1 | B24: 110027 | C24: Outlet | D24: Burgrill | E24: 45962 | F24: RJ390554 | G24: zomato | H24: =IF(G24="POS","Direct Sale","Aggregator") -> Aggregator | I24: 7437673579 | J24: 18528960 | K24: 45962.71 | L24: =VALUE(DAY(K24)) -> 1 | M24: =TEXT(K24,"dddd") -> Saturday | N24: =TEXT(K24,"MMMM") -> November | O24: 0.70972222 | P24: =_xlfn.IFS(L24<=7,"Week 1",L24<=15, "Week 2",L24<=23,"Week 3",L24<=30,"Week 4") -> Week 1 | Q24: No | R24: 663.66 | S24: -248.9 | T24: =ABS((S24/R24)*100) -> 37.504144 | U24: 414.76 | V24: 32 | W24: 0 | X24: 0 | Y24: 446.76 | Z24: 446.76 | AA24: Zomato | AB24: 135.43 | AC24: 10.95 | AD24: Zomato | AE24: Burgrill | AF24: 3579 | AG24: 3579 | AO24: 32 | AP24: 0 | AX24: 446.76 | BD24: 446.76 | BE24: 414.76 | BG24: =BE24+BF24 -> 414.76 | BI24: 32
A25: Store 1 | B25: 110027 | C25: Outlet | D25: Burgrill | E25: 45962 | F25: RJ390558 | G25: swiggy | H25: =IF(G25="POS","Direct Sale","Aggregator") -> Aggregator | I25: 220968000000000 | J25: 29811 | K25: 45962.729 | L25: =VALUE(DAY(K25)) -> 1 | M25: =TEXT(K25,"dddd") -> Saturday | N25: =TEXT(K25,"MMMM") -> November | O25: 0.72916667 | P25: =_xlfn.IFS(L25<=7,"Week 1",L25<=15, "Week 2",L25<=23,"Week 3",L25<=30,"Week 4") -> Week 1 | Q25: No | R25: 318 | S25: -93.75 | T25: =ABS((S25/R25)*100) -> 29.481132 | U25: 224.25 | V25: 32 | W25: 0 | X25: -0.25 | Y25: 256 | Z25: 256 | AA25: Swiggy | AB25: 70.61 | AC25: 4.77 | AD25: Swiggy | AE25: Burgrill | AF25: 9697 | AG25: 9697 | AO25: 32 | AP25: 0 | AW25: 256 | BD25: 256 | BE25: 224.25 | BG25: =BE25+BF25 -> 224.25 | BH25: 32
A26: Store 1 | B26: 110027 | C26: Outlet | D26: Burgrill | E26: 45962 | F26: RJ390559 | G26: swiggy | H26: =IF(G26="POS","Direct Sale","Aggregator") -> Aggregator | I26: 220968000000000 | J26: 29811 | K26: 45962.731 | L26: =VALUE(DAY(K26)) -> 1 | M26: =TEXT(K26,"dddd") -> Saturday | N26: =TEXT(K26,"MMMM") -> November | O26: 0.73055556 | P26: =_xlfn.IFS(L26<=7,"Week 1",L26<=15, "Week 2",L26<=23,"Week 3",L26<=30,"Week 4") -> Week 1 | Q26: No | R26: 178 | S26: -20 | T26: =ABS((S26/R26)*100) -> 11.235955 | U26: 158 | V26: 32 | W26: 0 | X26: 0 | Y26: 190 | Z26: 190 | AA26: Swiggy | AB26: 37.92 | AC26: 1.96 | AD26: Swiggy | AE26: Burgrill | AF26: 6720 | AG26: 6720 | AO26: 32 | AP26: 0 | AW26: 190 | BD26: 190 | BE26: 158 | BG26: =BE26+BF26 -> 158 | BH26: 32
A27: Store 1 | B27: 110027 | C27: Outlet | D27: Burgrill | E27: 45962 | F27: RJ390560 | G27: zomato | H27: =IF(G27="POS","Direct Sale","Aggregator") -> Aggregator | I27: 7431959854 | J27: 18528960 | K27: 45962.74 | L27: =VALUE(DAY(K27)) -> 1 | M27: =TEXT(K27,"dddd") -> Saturday | N27: =TEXT(K27,"MMMM") -> November | O27: 0.73958333 | P27: =_xlfn.IFS(L27<=7,"Week 1",L27<=15, "Week 2",L27<=23,"Week 3",L27<=30,"Week 4") -> Week 1 | Q27: No | R27: 1036 | S27: 0 | T27: =ABS((S27/R27)*100) -> 0 | U27: 1036 | V27: 32 | W27: 0 | X27: 0 | Y27: 1068 | Z27: 1068 | AA27: Zomato | AB27: 233.97 | AC27: 19.36 | AD27: Zomato | AE27: Burgrill | AF27: 9854 | AG27: 9854 | AO27: 32 | AP27: 0 | AX27: 1068 | BD27: 1068 | BE27: 1036 | BG27: =BE27+BF27 -> 1036 | BI27: 32
A28: Store 1 | B28: 110027 | C28: Outlet | D28: Burgrill | E28: 45962 | F28: RJ390564 | G28: POS | H28: =IF(G28="POS","Direct Sale","Aggregator") -> Direct Sale | K28: 45962.772 | L28: =VALUE(DAY(K28)) -> 1 | M28: =TEXT(K28,"dddd") -> Saturday | N28: =TEXT(K28,"MMMM") -> November | O28: 0.77152778 | P28: =_xlfn.IFS(L28<=7,"Week 1",L28<=15, "Week 2",L28<=23,"Week 3",L28<=30,"Week 4") -> Week 1 | Q28: No | R28: 198 | S28: 0 | T28: =ABS((S28/R28)*100) -> 0 | U28: 198 | V28: 0 | W28: 9.9 | X28: 0.1 | Y28: 208 | Z28: 208 | AA28: Cash | AB28: 48.85 | AC28: 3.92 | AD28: Burgrill Dine In | AE28: Dine In | AI28: RJFXN3YM | AJ28: Burgrill | AK28: 8929758003 | AO28: 0 | AP28: 0 | AR28: 208 | AZ28: 198 | BA28: 4.95 | BB28: 198 | BC28: 4.95 | BD28: 208 | BE28: 198 | BG28: =BE28+BF28 -> 198
A29: Store 1 | B29: 110027 | C29: Outlet | D29: Burgrill | E29: 45962 | F29: RJ390563 | G29: POS | H29: =IF(G29="POS","Direct Sale","Aggregator") -> Direct Sale | K29: 45962.772 | L29: =VALUE(DAY(K29)) -> 1 | M29: =TEXT(K29,"dddd") -> Saturday | N29: =TEXT(K29,"MMMM") -> November | O29: 0.77152778 | P29: =_xlfn.IFS(L29<=7,"Week 1",L29<=15, "Week 2",L29<=23,"Week 3",L29<=30,"Week 4") -> Week 1 | Q29: No | R29: 217 | S29: -15 | T29: =ABS((S29/R29)*100) -> 6.9124424 | U29: 202 | V29: 0 | W29: 10.1 | X29: -0.1 | Y29: 212 | Z29: 212 | AA29: Cash,Card | AB29: 56.03 | AC29: 5.88 | AD29: Takeaway | AI29: I8Y3EPU8 | AJ29: shivam | AK29: 9810206362 | AO29: 0 | AP29: 0 | AQ29: 12 | AR29: 200 | AZ29: 202 | BA29: 5.05 | BB29: 202 | BC29: 5.05 | BD29: 212 | BE29: 202 | BG29: =BE29+BF29 -> 202
A30: Store 1 | B30: 110027 | C30: Outlet | D30: Burgrill | E30: 45962 | F30: RJ390562 | G30: POS | H30: =IF(G30="POS","Direct Sale","Aggregator") -> Direct Sale | K30: 45962.772 | L30: =VALUE(DAY(K30)) -> 1 | M30: =TEXT(K30,"dddd") -> Saturday | N30: =TEXT(K30,"MMMM") -> November | O30: 0.77222222 | P30: =_xlfn.IFS(L30<=7,"Week 1",L30<=15, "Week 2",L30<=23,"Week 3",L30<=30,"Week 4") -> Week 1 | Q30: No | R30: 356 | S30: 0 | T30: =ABS((S30/R30)*100) -> 0 | U30: 356 | V30: 0 | W30: 17.8 | X30: 0.2 | Y30: 374 | Z30: 374 | AA30: Card | AB30: 97.33 | AC30: 8.16 | AD30: Burgrill Dine In | AE30: Dine In | AI30: RJFXN3YM | AJ30: Burgrill | AK30: 8929758003 | AO30: 0 | AP30: 0 | AQ30: 374 | AZ30: 356 | BA30: 8.9 | BB30: 356 | BC30: 8.9 | BD30: 374 | BE30: 356 | BG30: =BE30+BF30 -> 356
A31: Store 1 | B31: 110027 | C31: Outlet | D31: Burgrill | E31: 45962 | F31: RJ390561 | G31: POS | H31: =IF(G31="POS","Direct Sale","Aggregator") -> Direct Sale | K31: 45962.772 | L31: =VALUE(DAY(K31)) -> 1 | M31: =TEXT(K31,"dddd") -> Saturday | N31: =TEXT(K31,"MMMM") -> November | O31: 0.77222222 | P31: =_xlfn.IFS(L31<=7,"Week 1",L31<=15, "Week 2",L31<=23,"Week 3",L31<=30,"Week 4") -> Week 1 | Q31: No | R31: 348 | S31: 0 | T31: =ABS((S31/R31)*100) -> 0 | U31: 348 | V31: 0 | W31: 17.4 | X31: -0.4 | Y31: 365 | Z31: 365 | AA31: Card | AB31: 97.24 | AC31: 4.52 | AD31: Burgrill Dine In | AE31: Dine In | AI31: RJFXN3YM | AJ31: Burgrill | AK31: 8929758003 | AO31: 0 | AP31: 0 | AQ31: 365 | AZ31: 348 | BA31: 8.7 | BB31: 348 | BC31: 8.7 | BD31: 365 | BE31: 348 | BG31: =BE31+BF31 -> 348
A32: Store 1 | B32: 110027 | C32: Outlet | D32: Burgrill | E32: 45962 | F32: RJ390557 | G32: POS | H32: =IF(G32="POS","Direct Sale","Aggregator") -> Direct Sale | K32: 45962.772 | L32: =VALUE(DAY(K32)) -> 1 | M32: =TEXT(K32,"dddd") -> Saturday | N32: =TEXT(K32,"MMMM") -> November | O32: 0.77222222 | P32: =_xlfn.IFS(L32<=7,"Week 1",L32<=15, "Week 2",L32<=23,"Week 3",L32<=30,"Week 4") -> Week 1 | Q32: No | R32: 597 | S32: 0 | T32: =ABS((S32/R32)*100) -> 0 | U32: 597 | V32: 0 | W32: 29.86 | X32: 0.14 | Y32: 627 | Z32: 627 | AA32: Card | AB32: 142.23 | AC32: 7.68 | AD32: Burgrill Dine In | AE32: Dine In | AI32: MJHTLH2P | AJ32: asveed | AK32: 8287834046 | AO32: 0 | AP32: 0 | AQ32: 627 | AZ32: 597 | BA32: 14.93 | BB32: 597 | BC32: 14.93 | BD32: 627 | BE32: 597 | BG32: =BE32+BF32 -> 597
A33: Store 1 | B33: 110027 | C33: Outlet | D33: Burgrill | E33: 45962 | F33: RJ390556 | G33: POS | H33: =IF(G33="POS","Direct Sale","Aggregator") -> Direct Sale | K33: 45962.773 | L33: =VALUE(DAY(K33)) -> 1 | M33: =TEXT(K33,"dddd") -> Saturday | N33: =TEXT(K33,"MMMM") -> November | O33: 0.77291667 | P33: =_xlfn.IFS(L33<=7,"Week 1",L33<=15, "Week 2",L33<=23,"Week 3",L33<=30,"Week 4") -> Week 1 | Q33: No | R33: 594.1 | S33: 0 | T33: =ABS((S33/R33)*100) -> 0 | U33: 594.1 | V33: 0 | W33: 29.7 | X33: 0.2 | Y33: 624 | Z33: 624 | AA33: Cash,Card | AB33: 171.65 | AC33: 8.86 | AD33: Burgrill Dine In | AE33: Dine In | AI33: RJFXN3YM | AJ33: Burgrill | AK33: 8929758003 | AO33: 0 | AP33: 0 | AQ33: 124 | AR33: 500 | AZ33: 594.1 | BA33: 14.85 | BB33: 594.1 | BC33: 14.85 | BD33: 624 | BE33: 594.1 | BG33: =BE33+BF33 -> 594.1
A34: Store 1 | B34: 110027 | C34: Outlet | D34: Burgrill | E34: 45962 | F34: RJ390553 | G34: POS | H34: =IF(G34="POS","Direct Sale","Aggregator") -> Direct Sale | K34: 45962.773 | L34: =VALUE(DAY(K34)) -> 1 | M34: =TEXT(K34,"dddd") -> Saturday | N34: =TEXT(K34,"MMMM") -> November | O34: 0.77291667 | P34: =_xlfn.IFS(L34<=7,"Week 1",L34<=15, "Week 2",L34<=23,"Week 3",L34<=30,"Week 4") -> Week 1 | Q34: No | R34: 369 | S34: 0 | T34: =ABS((S34/R34)*100) -> 0 | U34: 369 | V34: 0 | W34: 18.46 | X34: -0.46 | Y34: 387 | Z34: 387 | AA34: Cash | AB34: 81.84 | AC34: 8.72 | AD34: Burgrill Dine In | AE34: Dine In | AI34: ZQVQWXQQ | AJ34: new | AK34: 9717033322 | AO34: 0 | AP34: 0 | AR34: 387 | AZ34: 369 | BA34: 9.23 | BB34: 369 | BC34: 9.23 | BD34: 387 | BE34: 369 | BG34: =BE34+BF34 -> 369
A35: Store 1 | B35: 110027 | C35: Outlet | D35: Burgrill | E35: 45962 | F35: RJ390555 | G35: POS | H35: =IF(G35="POS","Direct Sale","Aggregator") -> Direct Sale | K35: 45962.773 | L35: =VALUE(DAY(K35)) -> 1 | M35: =TEXT(K35,"dddd") -> Saturday | N35: =TEXT(K35,"MMMM") -> November | O35: 0.77291667 | P35: =_xlfn.IFS(L35<=7,"Week 1",L35<=15, "Week 2",L35<=23,"Week 3",L35<=30,"Week 4") -> Week 1 | Q35: No | R35: 59 | S35: 0 | T35: =ABS((S35/R35)*100) -> 0 | U35: 59 | V35: 0 | W35: 2.96 | X35: 0.04 | Y35: 62 | Z35: 62 | AA35: Card | AB35: 15.49 | AC35: 2.14 | AD35: Burgrill Dine In | AE35: Dine In | AI35: RJFXN3YM | AJ35: Burgrill | AK35: 8929758003 | AO35: 0 | AP35: 0 | AQ35: 62 | AZ35: 59 | BA35: 1.48 | BB35: 59 | BC35: 1.48 | BD35: 62 | BE35: 59 | BG35: =BE35+BF35 -> 59
A36: Store 1 | B36: 110027 | C36: Outlet | D36: Burgrill | E36: 45962 | F36: RJ390552 | G36: POS | H36: =IF(G36="POS","Direct Sale","Aggregator") -> Direct Sale | K36: 45962.773 | L36: =VALUE(DAY(K36)) -> 1 | M36: =TEXT(K36,"dddd") -> Saturday | N36: =TEXT(K36,"MMMM") -> November | O36: 0.77291667 | P36: =_xlfn.IFS(L36<=7,"Week 1",L36<=15, "Week 2",L36<=23,"Week 3",L36<=30,"Week 4") -> Week 1 | Q36: No | R36: 507 | S36: 0 | T36: =ABS((S36/R36)*100) -> 0 | U36: 507 | V36: 0 | W36: 25.36 | X36: -0.36 | Y36: 532 | Z36: 532 | AA36: Card | AB36: 107.54 | AC36: 12.83 | AD36: Burgrill Dine In | AE36: Dine In | AI36: RJFXN3YM | AJ36: Burgrill | AK36: 8929758003 | AO36: 0 | AP36: 0 | AQ36: 532 | AZ36: 507 | BA36: 12.68 | BB36: 507 | BC36: 12.68 | BD36: 532 | BE36: 507 | BG36: =BE36+BF36 -> 507
A37: Store 1 | B37: 110027 | C37: Outlet | D37: Burgrill | E37: 45962 | F37: RJ390548 | G37: POS | H37: =IF(G37="POS","Direct Sale","Aggregator") -> Direct Sale | K37: 45962.773 | L37: =VALUE(DAY(K37)) -> 1 | M37: =TEXT(K37,"dddd") -> Saturday | N37: =TEXT(K37,"MMMM") -> November | O37: 0.77291667 | P37: =_xlfn.IFS(L37<=7,"Week 1",L37<=15, "Week 2",L37<=23,"Week 3",L37<=30,"Week 4") -> Week 1 | Q37: No | R37: 398 | S37: 0 | T37: =ABS((S37/R37)*100) -> 0 | U37: 398 | V37: 0 | W37: 19.9 | X37: 0.1 | Y37: 418 | Z37: 418 | AA37: Card | AB37: 108.44 | AC37: 10.46 | AD37: Burgrill Dine In | AE37: Dine In | AI37: RJFXN3YM | AJ37: Burgrill | AK37: 8929758003 | AO37: 0 | AP37: 0 | AQ37: 418 | AZ37: 398 | BA37: 9.95 | BB37: 398 | BC37: 9.95 | BD37: 418 | BE37: 398 | BG37: =BE37+BF37 -> 398
A38: Store 1 | B38: 110027 | C38: Outlet | D38: Burgrill | E38: 45962 | F38: RJ390566 | G38: zomato | H38: =IF(G38="POS","Direct Sale","Aggregator") -> Aggregator | I38: 7433349559 | J38: 18528960 | K38: 45962.78 | L38: =VALUE(DAY(K38)) -> 1 | M38: =TEXT(K38,"dddd") -> Saturday | N38: =TEXT(K38,"MMMM") -> November | O38: 0.77986111 | P38: =_xlfn.IFS(L38<=7,"Week 1",L38<=15, "Week 2",L38<=23,"Week 3",L38<=30,"Week 4") -> Week 1 | Q38: No | R38: 349 | S38: -174.5 | T38: =ABS((S38/R38)*100) -> 50 | U38: 174.5 | V38: 32 | W38: 0 | X38: 0 | Y38: 206.5 | Z38: 206.5 | AA38: Zomato | AB38: 64.83 | AC38: 4.77 | AD38: Zomato | AE38: Burgrill | AF38: 9559 | AG38: 9559 | AO38: 32 | AP38: 0 | AX38: 206.5 | BD38: 206.5 | BE38: 174.5 | BG38: =BE38+BF38 -> 174.5 | BI38: 32
A39: Store 1 | B39: 110027 | C39: Outlet | D39: Burgrill | E39: 45962 | F39: RJ390567 | G39: zomato | H39: =IF(G39="POS","Direct Sale","Aggregator") -> Aggregator | I39: 7431662061 | J39: 18528960 | K39: 45962.79 | L39: =VALUE(DAY(K39)) -> 1 | M39: =TEXT(K39,"dddd") -> Saturday | N39: =TEXT(K39,"MMMM") -> November | O39: 0.78958333 | P39: =_xlfn.IFS(L39<=7,"Week 1",L39<=15, "Week 2",L39<=23,"Week 3",L39<=30,"Week 4") -> Week 1 | Q39: No | R39: 1583.57 | S39: -677.59 | T39: =ABS((S39/R39)*100) -> 42.788762 | U39: 905.98 | V39: 32 | W39: 0 | X39: 0 | Y39: 937.98 | Z39: 937.98 | AA39: Zomato | AB39: 288.31 | AC39: 26.97 | AD39: Zomato | AE39: Burgrill | AF39: 2061 | AG39: 2061 | AO39: 32 | AP39: 0 | AX39: 937.98 | BD39: 937.98 | BE39: 905.99 | BG39: =BE39+BF39 -> 905.99 | BI39: 32
A40: Store 1 | B40: 110027 | C40: Outlet | D40: Burgrill | E40: 45962 | F40: RJ390568 | G40: zomato | H40: =IF(G40="POS","Direct Sale","Aggregator") -> Aggregator | I40: 7436694056 | J40: 18528960 | K40: 45962.792 | L40: =VALUE(DAY(K40)) -> 1 | M40: =TEXT(K40,"dddd") -> Saturday | N40: =TEXT(K40,"MMMM") -> November | O40: 0.79236111 | P40: =_xlfn.IFS(L40<=7,"Week 1",L40<=15, "Week 2",L40<=23,"Week 3",L40<=30,"Week 4") -> Week 1 | Q40: No | R40: 399 | S40: -75 | T40: =ABS((S40/R40)*100) -> 18.796992 | U40: 324 | V40: 32 | W40: 0 | X40: 0 | Y40: 356 | Z40: 356 | AA40: Zomato | AB40: 88.74 | AC40: 4.96 | AD40: Zomato | AE40: Burgrill | AF40: 4056 | AG40: 4056 | AO40: 32 | AP40: 0 | AX40: 356 | BD40: 356 | BE40: 324 | BG40: =BE40+BF40 -> 324 | BI40: 32
A41: Store 1 | B41: 110027 | C41: Outlet | D41: Burgrill | E41: 45962 | F41: RJ390569 | G41: swiggy | H41: =IF(G41="POS","Direct Sale","Aggregator") -> Aggregator | I41: 220974000000000 | J41: 29811 | K41: 45962.792 | L41: =VALUE(DAY(K41)) -> 1 | M41: =TEXT(K41,"dddd") -> Saturday | N41: =TEXT(K41,"MMMM") -> November | O41: 0.79236111 | P41: =_xlfn.IFS(L41<=7,"Week 1",L41<=15, "Week 2",L41<=23,"Week 3",L41<=30,"Week 4") -> Week 1 | Q41: No | R41: 644 | S41: -123.74 | T41: =ABS((S41/R41)*100) -> 19.214286 | U41: 520.26 | V41: 32 | W41: 0 | X41: -0.26 | Y41: 552 | Z41: 552 | AA41: Swiggy | AB41: 122.06 | AC41: 22.03 | AD41: Swiggy | AE41: Burgrill | AF41: 7691 | AG41: 7691 | AO41: 32 | AP41: 0 | AW41: 552 | BD41: 552 | BE41: 520.26 | BG41: =BE41+BF41 -> 520.26 | BH41: 32
A42: Store 1 | B42: 110027 | C42: Outlet | D42: Burgrill | E42: 45962 | F42: RJ390572 | G42: swiggy | H42: =IF(G42="POS","Direct Sale","Aggregator") -> Aggregator | I42: 220975000000000 | J42: 29811 | K42: 45962.81 | L42: =VALUE(DAY(K42)) -> 1 | M42: =TEXT(K42,"dddd") -> Saturday | N42: =TEXT(K42,"MMMM") -> November | O42: 0.80972222 | P42: =_xlfn.IFS(L42<=7,"Week 1",L42<=15, "Week 2",L42<=23,"Week 3",L42<=30,"Week 4") -> Week 1 | Q42: No | R42: 349 | S42: -175 | T42: =ABS((S42/R42)*100) -> 50.143266 | U42: 174 | V42: 32 | W42: 0 | X42: 0 | Y42: 206 | Z42: 206 | AA42: Swiggy | AB42: 64.83 | AC42: 4.77 | AD42: Swiggy | AE42: Burgrill | AF42: 7405 | AG42: 7405 | AO42: 32 | AP42: 0 | AW42: 206 | BD42: 206 | BE42: 174 | BG42: =BE42+BF42 -> 174 | BH42: 32
A43: Store 1 | B43: 110027 | C43: Outlet | D43: Burgrill | E43: 45962 | F43: RJ390575 | G43: swiggy | H43: =IF(G43="POS","Direct Sale","Aggregator") -> Aggregator | I43: 220975000000000 | J43: 29811 | K43: 45962.812 | L43: =VALUE(DAY(K43)) -> 1 | M43: =TEXT(K43,"dddd") -> Saturday | N43: =TEXT(K43,"MMMM") -> November | O43: 0.81180556 | P43: =_xlfn.IFS(L43<=7,"Week 1",L43<=15, "Week 2",L43<=23,"Week 3",L43<=30,"Week 4") -> Week 1 | Q43: No | R43: 437 | S43: -113.75 | T43: =ABS((S43/R43)*100) -> 26.029748 | U43: 323.25 | V43: 32 | W43: 0 | X43: -0.25 | Y43: 355 | Z43: 355 | AA43: Swiggy | AB43: 79.68 | AC43: 11.79 | AD43: Swiggy | AE43: Burgrill | AF43: 248 | AG43: 248 | AO43: 32 | AP43: 0 | AW43: 355 | BD43: 355 | BE43: 323.25 | BG43: =BE43+BF43 -> 323.25 | BH43: 32
A44: Store 1 | B44: 110027 | C44: Outlet | D44: Burgrill | E44: 45962 | F44: RJ390576 | G44: swiggy | H44: =IF(G44="POS","Direct Sale","Aggregator") -> Aggregator | I44: 220976000000000 | J44: 29811 | K44: 45962.818 | L44: =VALUE(DAY(K44)) -> 1 | M44: =TEXT(K44,"dddd") -> Saturday | N44: =TEXT(K44,"MMMM") -> November | O44: 0.81805556 | P44: =_xlfn.IFS(L44<=7,"Week 1",L44<=15, "Week 2",L44<=23,"Week 3",L44<=30,"Week 4") -> Week 1 | Q44: No | R44: 287 | S44: -70 | T44: =ABS((S44/R44)*100) -> 24.390244 | U44: 217 | V44: 32 | W44: 0 | X44: 0 | Y44: 249 | Z44: 249 | AA44: Swiggy | AB44: 53.91 | AC44: 5.88 | AD44: Swiggy | AE44: Burgrill | AF44: 43 | AG44: 43 | AO44: 32 | AP44: 0 | AW44: 249 | BD44: 249 | BE44: 217 | BG44: =BE44+BF44 -> 217 | BH44: 32
A45: Store 1 | B45: 110027 | C45: Outlet | D45: Burgrill | E45: 45962 | F45: RJ390577 | G45: POS | H45: =IF(G45="POS","Direct Sale","Aggregator") -> Direct Sale | K45: 45962.822 | L45: =VALUE(DAY(K45)) -> 1 | M45: =TEXT(K45,"dddd") -> Saturday | N45: =TEXT(K45,"MMMM") -> November | O45: 0.82152778 | P45: =_xlfn.IFS(L45<=7,"Week 1",L45<=15, "Week 2",L45<=23,"Week 3",L45<=30,"Week 4") -> Week 1 | Q45: No | R45: 118 | S45: 0 | T45: =ABS((S45/R45)*100) -> 0 | U45: 118 | V45: 0 | W45: 5.9 | X45: 0.1 | Y45: 124 | Z45: 124 | AA45: Cash | AB45: 30.99 | AC45: 3.92 | AD45: Takeaway | AI45: RJFXN3YM | AJ45: Burgrill | AK45: 8929758003 | AO45: 0 | AP45: 0 | AR45: 124 | AZ45: 118 | BA45: 2.95 | BB45: 118 | BC45: 2.95 | BD45: 124 | BE45: 118 | BG45: =BE45+BF45 -> 118
A46: Store 1 | B46: 110027 | C46: Outlet | D46: Burgrill | E46: 45962 | F46: RJ390574 | G46: POS | H46: =IF(G46="POS","Direct Sale","Aggregator") -> Direct Sale | K46: 45962.822 | L46: =VALUE(DAY(K46)) -> 1 | M46: =TEXT(K46,"dddd") -> Saturday | N46: =TEXT(K46,"MMMM") -> November | O46: 0.82152778 | P46: =_xlfn.IFS(L46<=7,"Week 1",L46<=15, "Week 2",L46<=23,"Week 3",L46<=30,"Week 4") -> Week 1 | Q46: No | R46: 79 | S46: 0 | T46: =ABS((S46/R46)*100) -> 0 | U46: 79 | V46: 0 | W46: 3.96 | X46: 0.04 | Y46: 83 | Z46: 83 | AA46: Card | AB46: 19.5 | AC46: 1.96 | AD46: Burgrill Dine In | AE46: Dine In | AI46: RJFXN3YM | AJ46: Burgrill | AK46: 8929758003 | AO46: 0 | AP46: 0 | AQ46: 83 | AZ46: 79 | BA46: 1.98 | BB46: 79 | BC46: 1.98 | BD46: 83 | BE46: 79 | BG46: =BE46+BF46 -> 79
A47: Store 1 | B47: 110027 | C47: Outlet | D47: Burgrill | E47: 45962 | F47: RJ390573 | G47: POS | H47: =IF(G47="POS","Direct Sale","Aggregator") -> Direct Sale | K47: 45962.822 | L47: =VALUE(DAY(K47)) -> 1 | M47: =TEXT(K47,"dddd") -> Saturday | N47: =TEXT(K47,"MMMM") -> November | O47: 0.82222222 | P47: =_xlfn.IFS(L47<=7,"Week 1",L47<=15, "Week 2",L47<=23,"Week 3",L47<=30,"Week 4") -> Week 1 | Q47: No | R47: 159 | S47: 0 | T47: =ABS((S47/R47)*100) -> 0 | U47: 159 | V47: 0 | W47: 7.96 | X47: 0.04 | Y47: 167 | Z47: 167 | AA47: Cash | AB47: 29.83 | AC47: 5.5 | AD47: Takeaway | AI47: RJFXN3YM | AJ47: Burgrill | AK47: 8929758003 | AO47: 0 | AP47: 0 | AR47: 167 | AZ47: 159 | BA47: 3.98 | BB47: 159 | BC47: 3.98 | BD47: 167 | BE47: 159 | BG47: =BE47+BF47 -> 159
A48: Store 1 | B48: 110027 | C48: Outlet | D48: Burgrill | E48: 45962 | F48: RJ390578 | G48: zomato | H48: =IF(G48="POS","Direct Sale","Aggregator") -> Aggregator | I48: 7436526153 | J48: 18528960 | K48: 45962.822 | L48: =VALUE(DAY(K48)) -> 1 | M48: =TEXT(K48,"dddd") -> Saturday | N48: =TEXT(K48,"MMMM") -> November | O48: 0.82222222 | P48: =_xlfn.IFS(L48<=7,"Week 1",L48<=15, "Week 2",L48<=23,"Week 3",L48<=30,"Week 4") -> Week 1 | Q48: No | R48: 698 | S48: -349 | T48: =ABS((S48/R48)*100) -> 50 | U48: 349 | V48: 32 | W48: 0 | X48: 0 | Y48: 381 | Z48: 381 | AA48: Zomato | AB48: 131.54 | AC48: 9.54 | AD48: Zomato | AE48: Burgrill | AF48: 6153 | AG48: 6153 | AO48: 32 | AP48: 0 | AX48: 381 | BD48: 381 | BE48: 349 | BG48: =BE48+BF48 -> 349 | BI48: 32
A49: Store 1 | B49: 110027 | C49: Outlet | D49: Burgrill | E49: 45962 | F49: RJ390579 | G49: swiggy | H49: =IF(G49="POS","Direct Sale","Aggregator") -> Aggregator | I49: 220976000000000 | J49: 29811 | K49: 45962.824 | L49: =VALUE(DAY(K49)) -> 1 | M49: =TEXT(K49,"dddd") -> Saturday | N49: =TEXT(K49,"MMMM") -> November | O49: 0.82361111 | P49: =_xlfn.IFS(L49<=7,"Week 1",L49<=15, "Week 2",L49<=23,"Week 3",L49<=30,"Week 4") -> Week 1 | Q49: No | R49: 586 | S49: -93.74 | T49: =ABS((S49/R49)*100) -> 15.996587 | U49: 492.26 | V49: 32 | W49: 0 | X49: -0.26 | Y49: 524 | Z49: 524 | AA49: Swiggy | AB49: 98.21 | AC49: 17.65 | AD49: Swiggy | AE49: Burgrill | AF49: 7894 | AG49: 7894 | AO49: 32 | AP49: 0 | AW49: 524 | BD49: 524 | BE49: 492.26 | BG49: =BE49+BF49 -> 492.26 | BH49: 32
A50: Store 1 | B50: 110027 | C50: Outlet | D50: Burgrill | E50: 45962 | F50: RJ390583 | G50: zomato | H50: =IF(G50="POS","Direct Sale","Aggregator") -> Aggregator | I50: 7432335619 | J50: 18528960 | K50: 45962.842 | L50: =VALUE(DAY(K50)) -> 1 | M50: =TEXT(K50,"dddd") -> Saturday | N50: =TEXT(K50,"MMMM") -> November | O50: 0.84236111 | P50: =_xlfn.IFS(L50<=7,"Week 1",L50<=15, "Week 2",L50<=23,"Week 3",L50<=30,"Week 4") -> Week 1 | Q50: No | R50: 885 | S50: -140 | T50: =ABS((S50/R50)*100) -> 15.819209 | U50: 745 | V50: 32 | W50: 0 | X50: 0 | Y50: 777 | Z50: 777 | AA50: Zomato | AB50: 206.52 | AC50: 13.83 | AD50: Zomato | AE50: Burgrill | AF50: 5619 | AG50: 5619 | AO50: 32 | AP50: 0 | AX50: 777 | BD50: 777 | BE50: 745 | BG50: =BE50+BF50 -> 745 | BI50: 32
A51: Store 1 | B51: 110027 | C51: Outlet | D51: Burgrill | E51: 45962 | F51: RJ390584 | G51: swiggy | H51: =IF(G51="POS","Direct Sale","Aggregator") -> Aggregator | I51: 220978000000000 | J51: 29811 | K51: 45962.845 | L51: =VALUE(DAY(K51)) -> 1 | M51: =TEXT(K51,"dddd") -> Saturday | N51: =TEXT(K51,"MMMM") -> November | O51: 0.84513889 | P51: =_xlfn.IFS(L51<=7,"Week 1",L51<=15, "Week 2",L51<=23,"Week 3",L51<=30,"Week 4") -> Week 1 | Q51: No | R51: 995 | S51: -298.75 | T51: =ABS((S51/R51)*100) -> 30.025126 | U51: 696.25 | V51: 32 | W51: 0 | X51: -0.25 | Y51: 728 | Z51: 728 | AA51: Swiggy | AB51: 197.3 | AC51: 16.53 | AD51: Swiggy | AE51: Burgrill | AF51: 5670 | AG51: 5670 | AO51: 32 | AP51: 0 | AW51: 728 | BD51: 728 | BE51: 696.25 | BG51: =BE51+BF51 -> 696.25 | BH51: 32
A52: Store 1 | B52: 110027 | C52: Outlet | D52: Burgrill | E52: 45962 | F52: RJ390586 | G52: magicpin | H52: =IF(G52="POS","Direct Sale","Aggregator") -> Aggregator | I52: 280270765 | K52: 45962.847 | L52: =VALUE(DAY(K52)) -> 1 | M52: =TEXT(K52,"dddd") -> Saturday | N52: =TEXT(K52,"MMMM") -> November | O52: 0.84652778 | P52: =_xlfn.IFS(L52<=7,"Week 1",L52<=15, "Week 2",L52<=23,"Week 3",L52<=30,"Week 4") -> Week 1 | Q52: No | R52: 247 | S52: -100 | T52: =ABS((S52/R52)*100) -> 40.48583 | U52: 147 | V52: 0 | W52: 0 | X52: 0 | Y52: 147 | Z52: 147 | AA52: magicpin | AB52: 47.58 | AC52: 5.88 | AD52: magicpin | AF52: 765 | AG52: 765 | AI52: D8MDIGHA | AJ52: Hargun | AK52: 8700771033 | AM52: New Delhi | AO52: 0 | AP52: 0 | AT52: 147 | BD52: 147 | BE52: 147 | BG52: =BE52+BF52 -> 147
A53: Store 1 | B53: 110027 | C53: Outlet | D53: Burgrill | E53: 45962 | F53: RJ390587 | G53: swiggy | H53: =IF(G53="POS","Direct Sale","Aggregator") -> Aggregator | I53: 220978000000000 | J53: 29811 | K53: 45962.847 | L53: =VALUE(DAY(K53)) -> 1 | M53: =TEXT(K53,"dddd") -> Saturday | N53: =TEXT(K53,"MMMM") -> November | O53: 0.84722222 | P53: =_xlfn.IFS(L53<=7,"Week 1",L53<=15, "Week 2",L53<=23,"Week 3",L53<=30,"Week 4") -> Week 1 | Q53: No | R53: 219 | S53: -90 | T53: =ABS((S53/R53)*100) -> 41.09589 | U53: 129 | V53: 32 | W53: 0 | X53: 0 | Y53: 161 | Z53: 161 | AA53: Swiggy | AB53: 41.16 | AC53: 4.26 | AD53: Swiggy | AE53: Burgrill | AF53: 424 | AG53: 424 | AO53: 32 | AP53: 0 | AW53: 161 | BD53: 161 | BE53: 129 | BG53: =BE53+BF53 -> 129 | BH53: 32
A54: Store 1 | B54: 110027 | C54: Outlet | D54: Burgrill | E54: 45962 | F54: RJ390588 | G54: zomato | H54: =IF(G54="POS","Direct Sale","Aggregator") -> Aggregator | I54: 7435510209 | J54: 18528960 | K54: 45962.851 | L54: =VALUE(DAY(K54)) -> 1 | M54: =TEXT(K54,"dddd") -> Saturday | N54: =TEXT(K54,"MMMM") -> November | O54: 0.85069444 | P54: =_xlfn.IFS(L54<=7,"Week 1",L54<=15, "Week 2",L54<=23,"Week 3",L54<=30,"Week 4") -> Week 1 | Q54: No | R54: 717 | S54: -75 | T54: =ABS((S54/R54)*100) -> 10.460251 | U54: 642 | V54: 32 | W54: 0 | X54: 0 | Y54: 674 | Z54: 674 | AA54: Zomato | AB54: 141.82 | AC54: 13.65 | AD54: Zomato | AE54: Burgrill | AF54: 209 | AG54: 209 | AO54: 32 | AP54: 0 | AX54: 674 | BD54: 674 | BE54: 642 | BG54: =BE54+BF54 -> 642 | BI54: 32
A55: Store 1 | B55: 110027 | C55: Outlet | D55: Burgrill | E55: 45962 | F55: RJ390589 | G55: zomato | H55: =IF(G55="POS","Direct Sale","Aggregator") -> Aggregator | I55: 7435637642 | J55: 18528960 | K55: 45962.857 | L55: =VALUE(DAY(K55)) -> 1 | M55: =TEXT(K55,"dddd") -> Saturday | N55: =TEXT(K55,"MMMM") -> November | O55: 0.85694444 | P55: =_xlfn.IFS(L55<=7,"Week 1",L55<=15, "Week 2",L55<=23,"Week 3",L55<=30,"Week 4") -> Week 1 | Q55: No | R55: 349 | S55: -75 | T55: =ABS((S55/R55)*100) -> 21.489971 | U55: 274 | V55: 32 | W55: 0 | X55: 0 | Y55: 306 | Z55: 306 | AA55: Zomato | AB55: 72.32 | AC55: 9.82 | AD55: Zomato | AE55: Burgrill | AF55: 7642 | AG55: 7642 | AO55: 32 | AP55: 0 | AX55: 306 | BD55: 306 | BE55: 274 | BG55: =BE55+BF55 -> 274 | BI55: 32
A56: Store 1 | B56: 110027 | C56: Outlet | D56: Burgrill | E56: 45962 | F56: RJ390590 | G56: swiggy | H56: =IF(G56="POS","Direct Sale","Aggregator") -> Aggregator | I56: 220979000000000 | J56: 29811 | K56: 45962.859 | L56: =VALUE(DAY(K56)) -> 1 | M56: =TEXT(K56,"dddd") -> Saturday | N56: =TEXT(K56,"MMMM") -> November | O56: 0.85902778 | P56: =_xlfn.IFS(L56<=7,"Week 1",L56<=15, "Week 2",L56<=23,"Week 3",L56<=30,"Week 4") -> Week 1 | Q56: No | R56: 448 | S56: -93.74 | T56: =ABS((S56/R56)*100) -> 20.924107 | U56: 354.26 | V56: 32 | W56: 0 | X56: -0.26 | Y56: 386 | Z56: 386 | AA56: Swiggy | AB56: 87.84 | AC56: 8.69 | AD56: Swiggy | AE56: Burgrill | AF56: 7472 | AG56: 7472 | AO56: 32 | AP56: 0 | AW56: 386 | BD56: 386 | BE56: 354.26 | BG56: =BE56+BF56 -> 354.26 | BH56: 32
A57: Store 1 | B57: 110027 | C57: Outlet | D57: Burgrill | E57: 45962 | F57: RJ390585 | G57: POS | H57: =IF(G57="POS","Direct Sale","Aggregator") -> Direct Sale | K57: 45962.867 | L57: =VALUE(DAY(K57)) -> 1 | M57: =TEXT(K57,"dddd") -> Saturday | N57: =TEXT(K57,"MMMM") -> November | O57: 0.86736111 | P57: =_xlfn.IFS(L57<=7,"Week 1",L57<=15, "Week 2",L57<=23,"Week 3",L57<=30,"Week 4") -> Week 1 | Q57: No | R57: 369 | S57: 0 | T57: =ABS((S57/R57)*100) -> 0 | U57: 369 | V57: 0 | W57: 18.46 | X57: -0.46 | Y57: 387 | Z57: 387 | AA57: Cash | AB57: 99.73 | AC57: 8.72 | AD57: Burgrill Dine In | AE57: Dine In | AI57: RJFXN3YM | AJ57: Burgrill | AK57: 8929758003 | AO57: 0 | AP57: 0 | AR57: 387 | AZ57: 369 | BA57: 9.23 | BB57: 369 | BC57: 9.23 | BD57: 387 | BE57: 369 | BG57: =BE57+BF57 -> 369
A58: Store 1 | B58: 110027 | C58: Outlet | D58: Burgrill | E58: 45962 | F58: RJ390592 | G58: swiggy | H58: =IF(G58="POS","Direct Sale","Aggregator") -> Aggregator | I58: 220980000000000 | J58: 29811 | K58: 45962.869 | L58: =VALUE(DAY(K58)) -> 1 | M58: =TEXT(K58,"dddd") -> Saturday | N58: =TEXT(K58,"MMMM") -> November | O58: 0.86875 | P58: =_xlfn.IFS(L58<=7,"Week 1",L58<=15, "Week 2",L58<=23,"Week 3",L58<=30,"Week 4") -> Week 1 | Q58: No | R58: 348 | S58: -120 | T58: =ABS((S58/R58)*100) -> 34.482759 | U58: 228 | V58: 32 | W58: 0 | X58: 0 | Y58: 260 | Z58: 260 | AA58: Swiggy | AB58: 67.56 | AC58: 11.79 | AD58: Swiggy | AE58: Burgrill | AF58: 545 | AG58: 545 | AO58: 32 | AP58: 0 | AW58: 260 | BD58: 260 | BE58: 228 | BG58: =BE58+BF58 -> 228 | BH58: 32
A59: Store 1 | B59: 110027 | C59: Outlet | D59: Burgrill | E59: 45962 | F59: RJ390593 | G59: swiggy | H59: =IF(G59="POS","Direct Sale","Aggregator") -> Aggregator | I59: 220980000000000 | J59: 29811 | K59: 45962.869 | L59: =VALUE(DAY(K59)) -> 1 | M59: =TEXT(K59,"dddd") -> Saturday | N59: =TEXT(K59,"MMMM") -> November | O59: 0.86944444 | P59: =_xlfn.IFS(L59<=7,"Week 1",L59<=15, "Week 2",L59<=23,"Week 3",L59<=30,"Week 4") -> Week 1 | Q59: No | R59: 328 | S59: -75 | T59: =ABS((S59/R59)*100) -> 22.865854 | U59: 253 | V59: 32 | W59: 0 | X59: 0 | Y59: 285 | Z59: 285 | AA59: Swiggy | AB59: 65.96 | AC59: 8.34 | AD59: Swiggy | AE59: Burgrill | AF59: 3459 | AG59: 3459 | AO59: 32 | AP59: 0 | AW59: 285 | BD59: 285 | BE59: 253 | BG59: =BE59+BF59 -> 253 | BH59: 32
A60: Store 1 | B60: 110027 | C60: Outlet | D60: Burgrill | E60: 45962 | F60: RJ390594 | G60: swiggy | H60: =IF(G60="POS","Direct Sale","Aggregator") -> Aggregator | I60: 220980000000000 | J60: 29811 | K60: 45962.872 | L60: =VALUE(DAY(K60)) -> 1 | M60: =TEXT(K60,"dddd") -> Saturday | N60: =TEXT(K60,"MMMM") -> November | O60: 0.87222222 | P60: =_xlfn.IFS(L60<=7,"Week 1",L60<=15, "Week 2",L60<=23,"Week 3",L60<=30,"Week 4") -> Week 1 | Q60: No | R60: 614 | S60: -93.74 | T60: =ABS((S60/R60)*100) -> 15.267101 | U60: 520.26 | V60: 32 | W60: 0 | X60: -0.26 | Y60: 552 | Z60: 552 | AA60: Swiggy | AB60: 124.83 | AC60: 12.23 | AD60: Swiggy | AE60: Burgrill | AF60: 4214 | AG60: 4214 | AO60: 32 | AP60: 0 | AW60: 552 | BD60: 552 | BE60: 520.26 | BG60: =BE60+BF60 -> 520.26 | BH60: 32
A61: Store 1 | B61: 110027 | C61: Outlet | D61: Burgrill | E61: 45962 | F61: RJ390595 | G61: zomato | H61: =IF(G61="POS","Direct Sale","Aggregator") -> Aggregator | I61: 7437789894 | J61: 18528960 | K61: 45962.873 | L61: =VALUE(DAY(K61)) -> 1 | M61: =TEXT(K61,"dddd") -> Saturday | N61: =TEXT(K61,"MMMM") -> November | O61: 0.87291667 | P61: =_xlfn.IFS(L61<=7,"Week 1",L61<=15, "Week 2",L61<=23,"Week 3",L61<=30,"Week 4") -> Week 1 | Q61: No | R61: 656 | S61: -174.5 | T61: =ABS((S61/R61)*100) -> 26.60061 | U61: 481.5 | V61: 32 | W61: 0 | X61: 0 | Y61: 513.5 | Z61: 513.5 | AA61: Zomato | AB61: 112.32 | AC61: 12.07 | AD61: Zomato | AE61: Burgrill | AF61: 9894 | AG61: 9894 | AO61: 32 | AP61: 0 | AX61: 513.5 | BD61: 513.5 | BE61: 481.5 | BG61: =BE61+BF61 -> 481.5 | BI61: 32
A62: Store 1 | B62: 110027 | C62: Outlet | D62: Burgrill | E62: 45962 | F62: RJ390597 | G62: zomato | H62: =IF(G62="POS","Direct Sale","Aggregator") -> Aggregator | I62: 7434342785 | J62: 18528960 | K62: 45962.874 | L62: =VALUE(DAY(K62)) -> 1 | M62: =TEXT(K62,"dddd") -> Saturday | N62: =TEXT(K62,"MMMM") -> November | O62: 0.87430556 | P62: =_xlfn.IFS(L62<=7,"Week 1",L62<=15, "Week 2",L62<=23,"Week 3",L62<=30,"Week 4") -> Week 1 | Q62: No | R62: 1075 | S62: -314.5 | T62: =ABS((S62/R62)*100) -> 29.255814 | U62: 760.5 | V62: 32 | W62: 0 | X62: 0 | Y62: 792.5 | Z62: 792.5 | AA62: Zomato | AB62: 208.85 | AC62: 22.86 | AD62: Zomato | AE62: Burgrill | AF62: 2785 | AG62: 2785 | AO62: 32 | AP62: 0 | AX62: 792.5 | BD62: 792.5 | BE62: 760.5 | BG62: =BE62+BF62 -> 760.5 | BI62: 32
A63: Store 1 | B63: 110027 | C63: Outlet | D63: Burgrill | E63: 45962 | F63: RJ390598 | G63: POS | H63: =IF(G63="POS","Direct Sale","Aggregator") -> Direct Sale | K63: 45962.887 | L63: =VALUE(DAY(K63)) -> 1 | M63: =TEXT(K63,"dddd") -> Saturday | N63: =TEXT(K63,"MMMM") -> November | O63: 0.8875 | P63: =_xlfn.IFS(L63<=7,"Week 1",L63<=15, "Week 2",L63<=23,"Week 3",L63<=30,"Week 4") -> Week 1 | Q63: No | R63: 189 | S63: 0 | T63: =ABS((S63/R63)*100) -> 0 | U63: 189 | V63: 0 | W63: 9.46 | X63: -0.46 | Y63: 198 | Z63: 198 | AA63: Cash | AB63: 51.15 | AC63: 4.96 | AD63: Takeaway | AI63: RJFXN3YM | AJ63: Burgrill | AK63: 8929758003 | AO63: 0 | AP63: 0 | AR63: 198 | AZ63: 189 | BA63: 4.73 | BB63: 189 | BC63: 4.73 | BD63: 198 | BE63: 189 | BG63: =BE63+BF63 -> 189
A64: Store 1 | B64: 110027 | C64: Outlet | D64: Burgrill | E64: 45962 | F64: RJ390591 | G64: POS | H64: =IF(G64="POS","Direct Sale","Aggregator") -> Direct Sale | K64: 45962.887 | L64: =VALUE(DAY(K64)) -> 1 | M64: =TEXT(K64,"dddd") -> Saturday | N64: =TEXT(K64,"MMMM") -> November | O64: 0.8875 | P64: =_xlfn.IFS(L64<=7,"Week 1",L64<=15, "Week 2",L64<=23,"Week 3",L64<=30,"Week 4") -> Week 1 | Q64: No | R64: 307 | S64: 0 | T64: =ABS((S64/R64)*100) -> 0 | U64: 307 | V64: 0 | W64: 15.36 | X64: -0.36 | Y64: 322 | Z64: 322 | AA64: Card | AB64: 78.05 | AC64: 6.24 | AD64: Burgrill Dine In | AE64: Dine In | AI64: RJFXN3YM | AJ64: Burgrill | AK64: 8929758003 | AO64: 0 | AP64: 0 | AQ64: 322 | AZ64: 307 | BA64: 7.68 | BB64: 307 | BC64: 7.68 | BD64: 322 | BE64: 307 | BG64: =BE64+BF64 -> 307
A65: Store 1 | B65: 110027 | C65: Outlet | D65: Burgrill | E65: 45962 | F65: RJ390601 | G65: zomato | H65: =IF(G65="POS","Direct Sale","Aggregator") -> Aggregator | I65: 7421841456 | J65: 18528960 | K65: 45962.888 | L65: =VALUE(DAY(K65)) -> 1 | M65: =TEXT(K65,"dddd") -> Saturday | N65: =TEXT(K65,"MMMM") -> November | O65: 0.88819444 | P65: =_xlfn.IFS(L65<=7,"Week 1",L65<=15, "Week 2",L65<=23,"Week 3",L65<=30,"Week 4") -> Week 1 | Q65: No | R65: 229 | S65: -75 | T65: =ABS((S65/R65)*100) -> 32.751092 | U65: 154 | V65: 32 | W65: 0 | X65: 0 | Y65: 186 | Z65: 186 | AA65: Zomato | AB65: 48.21 | AC65: 4.77 | AD65: Zomato | AE65: Burgrill | AF65: 1456 | AG65: 1456 | AO65: 32 | AP65: 0 | AX65: 186 | BD65: 186 | BE65: 154 | BG65: =BE65+BF65 -> 154 | BI65: 32
A66: Store 1 | B66: 110027 | C66: Outlet | D66: Burgrill | E66: 45962 | F66: RJ390602 | G66: zomato | H66: =IF(G66="POS","Direct Sale","Aggregator") -> Aggregator | I66: 7432744523 | J66: 18528960 | K66: 45962.89 | L66: =VALUE(DAY(K66)) -> 1 | M66: =TEXT(K66,"dddd") -> Saturday | N66: =TEXT(K66,"MMMM") -> November | O66: 0.89027778 | P66: =_xlfn.IFS(L66<=7,"Week 1",L66<=15, "Week 2",L66<=23,"Week 3",L66<=30,"Week 4") -> Week 1 | Q66: No | R66: 319 | S66: -75 | T66: =ABS((S66/R66)*100) -> 23.510972 | U66: 244 | V66: 32 | W66: 0 | X66: 0 | Y66: 276 | Z66: 276 | AA66: Zomato | AB66: 62.5 | AC66: 4.96 | AD66: Zomato | AE66: Burgrill | AF66: 4523 | AG66: 4523 | AO66: 32 | AP66: 0 | AX66: 276 | BD66: 276 | BE66: 244 | BG66: =BE66+BF66 -> 244 | BI66: 32
A67: Store 1 | B67: 110027 | C67: Outlet | D67: Burgrill | E67: 45962 | F67: RJ390600 | G67: POS | H67: =IF(G67="POS","Direct Sale","Aggregator") -> Direct Sale | K67: 45962.894 | L67: =VALUE(DAY(K67)) -> 1 | M67: =TEXT(K67,"dddd") -> Saturday | N67: =TEXT(K67,"MMMM") -> November | O67: 0.89444444 | P67: =_xlfn.IFS(L67<=7,"Week 1",L67<=15, "Week 2",L67<=23,"Week 3",L67<=30,"Week 4") -> Week 1 | Q67: No | R67: 339.43 | S67: 0 | T67: =ABS((S67/R67)*100) -> 0 | U67: 339.43 | V67: 0 | W67: 16.98 | X67: -0.41 | Y67: 356 | Z67: 356 | AA67: Cash | AB67: 77.59 | AC67: 4.24 | AD67: Burgrill Dine In | AE67: Dine In | AI67: CSNWY5P7 | AJ67: APAR | AK67: 9711820046 | AO67: 0 | AP67: 0 | AR67: 356 | AZ67: 339.43 | BA67: 8.49 | BB67: 339.43 | BC67: 8.49 | BD67: 356 | BE67: 339.43 | BG67: =BE67+BF67 -> 339.43
A68: Store 1 | B68: 110027 | C68: Outlet | D68: Burgrill | E68: 45962 | F68: RJ390603 | G68: POS | H68: =IF(G68="POS","Direct Sale","Aggregator") -> Direct Sale | K68: 45962.896 | L68: =VALUE(DAY(K68)) -> 1 | M68: =TEXT(K68,"dddd") -> Saturday | N68: =TEXT(K68,"MMMM") -> November | O68: 0.89583333 | P68: =_xlfn.IFS(L68<=7,"Week 1",L68<=15, "Week 2",L68<=23,"Week 3",L68<=30,"Week 4") -> Week 1 | Q68: No | R68: 189 | S68: 0 | T68: =ABS((S68/R68)*100) -> 0 | U68: 189 | V68: 0 | W68: 9.46 | X68: -0.46 | Y68: 198 | Z68: 198 | AA68: Cash | AB68: 51.15 | AC68: 1.96 | AD68: Burgrill Dine In | AE68: Dine In | AI68: RJFXN3YM | AJ68: Burgrill | AK68: 8929758003 | AO68: 0 | AP68: 0 | AR68: 198 | AZ68: 189 | BA68: 4.73 | BB68: 189 | BC68: 4.73 | BD68: 198 | BE68: 189 | BG68: =BE68+BF68 -> 189
A69: Store 1 | B69: 110027 | C69: Outlet | D69: Burgrill | E69: 45962 | F69: RJ390599 | G69: POS | H69: =IF(G69="POS","Direct Sale","Aggregator") -> Direct Sale | K69: 45962.897 | L69: =VALUE(DAY(K69)) -> 1 | M69: =TEXT(K69,"dddd") -> Saturday | N69: =TEXT(K69,"MMMM") -> November | O69: 0.89652778 | P69: =_xlfn.IFS(L69<=7,"Week 1",L69<=15, "Week 2",L69<=23,"Week 3",L69<=30,"Week 4") -> Week 1 | Q69: No | R69: 438 | S69: 0 | T69: =ABS((S69/R69)*100) -> 0 | U69: 438 | V69: 0 | W69: 21.9 | X69: 0.1 | Y69: 460 | Z69: 460 | AA69: Card | AB69: 104.26 | AC69: 3.92 | AD69: Burgrill Dine In | AE69: Dine In | AI69: RJFXN3YM | AJ69: Burgrill | AK69: 8929758003 | AO69: 0 | AP69: 0 | AQ69: 460 | AZ69: 438 | BA69: 10.95 | BB69: 438 | BC69: 10.95 | BD69: 460 | BE69: 438 | BG69: =BE69+BF69 -> 438
A70: Store 1 | B70: 110027 | C70: Outlet | D70: Burgrill | E70: 45962 | F70: RJ390581 | G70: POS | H70: =IF(G70="POS","Direct Sale","Aggregator") -> Direct Sale | K70: 45962.897 | L70: =VALUE(DAY(K70)) -> 1 | M70: =TEXT(K70,"dddd") -> Saturday | N70: =TEXT(K70,"MMMM") -> November | O70: 0.89652778 | P70: =_xlfn.IFS(L70<=7,"Week 1",L70<=15, "Week 2",L70<=23,"Week 3",L70<=30,"Week 4") -> Week 1 | Q70: No | R70: 159 | S70: 0 | T70: =ABS((S70/R70)*100) -> 0 | U70: 159 | V70: 0 | W70: 7.96 | X70: 0.04 | Y70: 167 | Z70: 167 | AA70: Card | AB70: 29.83 | AC70: 5.5 | AD70: Takeaway | AI70: RJFXN3YM | AJ70: Burgrill | AK70: 8929758003 | AO70: 0 | AP70: 0 | AQ70: 167 | AZ70: 159 | BA70: 3.98 | BB70: 159 | BC70: 3.98 | BD70: 167 | BE70: 159 | BG70: =BE70+BF70 -> 159
A71: Store 1 | B71: 110027 | C71: Outlet | D71: Burgrill | E71: 45962 | F71: RJ390580 | G71: POS | H71: =IF(G71="POS","Direct Sale","Aggregator") -> Direct Sale | K71: 45962.897 | L71: =VALUE(DAY(K71)) -> 1 | M71: =TEXT(K71,"dddd") -> Saturday | N71: =TEXT(K71,"MMMM") -> November | O71: 0.89722222 | P71: =_xlfn.IFS(L71<=7,"Week 1",L71<=15, "Week 2",L71<=23,"Week 3",L71<=30,"Week 4") -> Week 1 | Q71: No | R71: 109 | S71: 0 | T71: =ABS((S71/R71)*100) -> 0 | U71: 109 | V71: 0 | W71: 5.46 | X71: -0.46 | Y71: 114 | Z71: 114 | AA71: Card | AB71: 24.63 | AC71: 4.96 | AD71: Takeaway | AI71: RJFXN3YM | AJ71: Burgrill | AK71: 8929758003 | AO71: 0 | AP71: 0 | AQ71: 114 | AZ71: 109 | BA71: 2.73 | BB71: 109 | BC71: 2.73 | BD71: 114 | BE71: 109 | BG71: =BE71+BF71 -> 109
A72: Store 1 | B72: 110027 | C72: Outlet | D72: Burgrill | E72: 45962 | F72: RJ390571 | G72: POS | H72: =IF(G72="POS","Direct Sale","Aggregator") -> Direct Sale | K72: 45962.898 | L72: =VALUE(DAY(K72)) -> 1 | M72: =TEXT(K72,"dddd") -> Saturday | N72: =TEXT(K72,"MMMM") -> November | O72: 0.89791667 | P72: =_xlfn.IFS(L72<=7,"Week 1",L72<=15, "Week 2",L72<=23,"Week 3",L72<=30,"Week 4") -> Week 1 | Q72: No | R72: 199 | S72: 0 | T72: =ABS((S72/R72)*100) -> 0 | U72: 199 | V72: 0 | W72: 9.96 | X72: 0.04 | Y72: 209 | Z72: 209 | AA72: Card | AB72: 44.84 | AC72: 2.82 | AD72: Burgrill Dine In | AE72: Dine In | AI72: RJFXN3YM | AJ72: Burgrill | AK72: 8929758003 | AO72: 0 | AP72: 0 | AQ72: 209 | AZ72: 199 | BA72: 4.98 | BB72: 199 | BC72: 4.98 | BD72: 209 | BE72: 199 | BG72: =BE72+BF72 -> 199
A73: Store 1 | B73: 110027 | C73: Outlet | D73: Burgrill | E73: 45962 | F73: RJ390596 | G73: POS | H73: =IF(G73="POS","Direct Sale","Aggregator") -> Direct Sale | K73: 45962.898 | L73: =VALUE(DAY(K73)) -> 1 | M73: =TEXT(K73,"dddd") -> Saturday | N73: =TEXT(K73,"MMMM") -> November | O73: 0.89791667 | P73: =_xlfn.IFS(L73<=7,"Week 1",L73<=15, "Week 2",L73<=23,"Week 3",L73<=30,"Week 4") -> Week 1 | Q73: No | R73: 583.66 | S73: 0 | T73: =ABS((S73/R73)*100) -> 0 | U73: 583.66 | V73: 0 | W73: 29.18 | X73: 0.16 | Y73: 613 | Z73: 613 | AA73: Card | AB73: 141.79 | AC73: 9.14 | AD73: Burgrill Dine In | AE73: Dine In | AI73: RJFXN3YM | AJ73: Burgrill | AK73: 8929758003 | AO73: 0 | AP73: 0 | AQ73: 613 | AZ73: 583.66 | BA73: 14.59 | BB73: 583.66 | BC73: 14.59 | BD73: 613 | BE73: 583.66 | BG73: =BE73+BF73 -> 583.66
A74: Store 1 | B74: 110027 | C74: Outlet | D74: Burgrill | E74: 45962 | F74: RJ390605 | G74: zomato | H74: =IF(G74="POS","Direct Sale","Aggregator") -> Aggregator | I74: 7424855590 | J74: 18528960 | K74: 45962.899 | L74: =VALUE(DAY(K74)) -> 1 | M74: =TEXT(K74,"dddd") -> Saturday | N74: =TEXT(K74,"MMMM") -> November | O74: 0.89861111 | P74: =_xlfn.IFS(L74<=7,"Week 1",L74<=15, "Week 2",L74<=23,"Week 3",L74<=30,"Week 4") -> Week 1 | Q74: No | R74: 557 | S74: -100 | T74: =ABS((S74/R74)*100) -> 17.953321 | U74: 457 | V74: 32 | W74: 0 | X74: 0 | Y74: 489 | Z74: 489 | AA74: Zomato | AB74: 122.27 | AC74: 13.74 | AD74: Zomato | AE74: Burgrill | AF74: 5590 | AG74: 5590 | AO74: 32 | AP74: 0 | AX74: 489 | BD74: 489 | BE74: 457 | BG74: =BE74+BF74 -> 457 | BI74: 32
A75: Store 1 | B75: 110027 | C75: Outlet | D75: Burgrill | E75: 45962 | F75: RJ390606 | G75: swiggy | H75: =IF(G75="POS","Direct Sale","Aggregator") -> Aggregator | I75: 220983000000000 | J75: 29811 | K75: 45962.901 | L75: =VALUE(DAY(K75)) -> 1 | M75: =TEXT(K75,"dddd") -> Saturday | N75: =TEXT(K75,"MMMM") -> November | O75: 0.90069444 | P75: =_xlfn.IFS(L75<=7,"Week 1",L75<=15, "Week 2",L75<=23,"Week 3",L75<=30,"Week 4") -> Week 1 | Q75: No | R75: 258 | S75: -60 | T75: =ABS((S75/R75)*100) -> 23.255814 | U75: 198 | V75: 32 | W75: 0 | X75: 0 | Y75: 230 | Z75: 230 | AA75: Swiggy | AB75: 45.84 | AC75: 3.92 | AD75: Swiggy | AE75: Burgrill | AF75: 7573 | AG75: 7573 | AO75: 32 | AP75: 0 | AW75: 230 | BD75: 230 | BE75: 198 | BG75: =BE75+BF75 -> 198 | BH75: 32
A76: Store 1 | B76: 110027 | C76: Outlet | D76: Burgrill | E76: 45962 | F76: RJ390608 | G76: zomato | H76: =IF(G76="POS","Direct Sale","Aggregator") -> Aggregator | I76: 7436428619 | J76: 18528960 | K76: 45962.906 | L76: =VALUE(DAY(K76)) -> 1 | M76: =TEXT(K76,"dddd") -> Saturday | N76: =TEXT(K76,"MMMM") -> November | O76: 0.90555556 | P76: =_xlfn.IFS(L76<=7,"Week 1",L76<=15, "Week 2",L76<=23,"Week 3",L76<=30,"Week 4") -> Week 1 | Q76: No | R76: 366 | S76: -100 | T76: =ABS((S76/R76)*100) -> 27.322404 | U76: 266 | V76: 32 | W76: 0 | X76: 0 | Y76: 298 | Z76: 298 | AA76: Zomato | AB76: 85.48 | AC76: 4.96 | AD76: Zomato | AE76: Burgrill | AF76: 8619 | AG76: 8619 | AO76: 32 | AP76: 0 | AX76: 298 | BD76: 298 | BE76: 266 | BG76: =BE76+BF76 -> 266 | BI76: 32
A77: Store 1 | B77: 110027 | C77: Outlet | D77: Burgrill | E77: 45962 | F77: RJ390609 | G77: POS | H77: =IF(G77="POS","Direct Sale","Aggregator") -> Direct Sale | K77: 45962.908 | L77: =VALUE(DAY(K77)) -> 1 | M77: =TEXT(K77,"dddd") -> Saturday | N77: =TEXT(K77,"MMMM") -> November | O77: 0.90763889 | P77: =_xlfn.IFS(L77<=7,"Week 1",L77<=15, "Week 2",L77<=23,"Week 3",L77<=30,"Week 4") -> Week 1 | Q77: No | R77: 177 | S77: 0 | T77: =ABS((S77/R77)*100) -> 0 | U77: 177 | V77: 0 | W77: 8.86 | X77: 0.14 | Y77: 186 | Z77: 186 | AA77: Cash | AB77: 46.48 | AC77: 5.88 | AD77: Takeaway | AI77: RJFXN3YM | AJ77: Burgrill | AK77: 8929758003 | AO77: 0 | AP77: 0 | AR77: 186 | AZ77: 177 | BA77: 4.43 | BB77: 177 | BC77: 4.43 | BD77: 186 | BE77: 177 | BG77: =BE77+BF77 -> 177
A78: Store 1 | B78: 110027 | C78: Outlet | D78: Burgrill | E78: 45962 | F78: RJ390610 | G78: swiggy | H78: =IF(G78="POS","Direct Sale","Aggregator") -> Aggregator | I78: 220984000000000 | J78: 29811 | K78: 45962.908 | L78: =VALUE(DAY(K78)) -> 1 | M78: =TEXT(K78,"dddd") -> Saturday | N78: =TEXT(K78,"MMMM") -> November | O78: 0.90833333 | P78: =_xlfn.IFS(L78<=7,"Week 1",L78<=15, "Week 2",L78<=23,"Week 3",L78<=30,"Week 4") -> Week 1 | Q78: No | R78: 646 | S78: -93.75 | T78: =ABS((S78/R78)*100) -> 14.512384 | U78: 552.25 | V78: 32 | W78: 0 | X78: -0.25 | Y78: 584 | Z78: 584 | AA78: Swiggy | AB78: 136.41 | AC78: 8.34 | AD78: Swiggy | AE78: Burgrill | AF78: 8408 | AG78: 8408 | AO78: 32 | AP78: 0 | AW78: 584 | BD78: 584 | BE78: 552.25 | BG78: =BE78+BF78 -> 552.25 | BH78: 32
A79: Store 1 | B79: 110027 | C79: Outlet | D79: Burgrill | E79: 45962 | F79: RJ390604 | G79: POS | H79: =IF(G79="POS","Direct Sale","Aggregator") -> Direct Sale | K79: 45962.909 | L79: =VALUE(DAY(K79)) -> 1 | M79: =TEXT(K79,"dddd") -> Saturday | N79: =TEXT(K79,"MMMM") -> November | O79: 0.90902778 | P79: =_xlfn.IFS(L79<=7,"Week 1",L79<=15, "Week 2",L79<=23,"Week 3",L79<=30,"Week 4") -> Week 1 | Q79: No | R79: 299 | S79: 0 | T79: =ABS((S79/R79)*100) -> 0 | U79: 299 | V79: 0 | W79: 14.96 | X79: 0.04 | Y79: 314 | Z79: 314 | AA79: Cash | AB79: 77.14 | AC79: 8.72 | AD79: Burgrill Dine In | AE79: Dine In | AI79: RJFXN3YM | AJ79: Burgrill | AK79: 8929758003 | AO79: 0 | AP79: 0 | AR79: 314 | AZ79: 299 | BA79: 7.48 | BB79: 299 | BC79: 7.48 | BD79: 314 | BE79: 299 | BG79: =BE79+BF79 -> 299
A80: Store 1 | B80: 110027 | C80: Outlet | D80: Burgrill | E80: 45962 | F80: RJ390612 | G80: swiggy | H80: =IF(G80="POS","Direct Sale","Aggregator") -> Aggregator | I80: 220984000000000 | J80: 29811 | K80: 45962.916 | L80: =VALUE(DAY(K80)) -> 1 | M80: =TEXT(K80,"dddd") -> Saturday | N80: =TEXT(K80,"MMMM") -> November | O80: 0.91597222 | P80: =_xlfn.IFS(L80<=7,"Week 1",L80<=15, "Week 2",L80<=23,"Week 3",L80<=30,"Week 4") -> Week 1 | Q80: No | R80: 404.66 | S80: -93.73 | T80: =ABS((S80/R80)*100) -> 23.162655 | U80: 310.93 | V80: 32 | W80: 0 | X80: 0.07 | Y80: 343 | Z80: 343 | AA80: Swiggy | AB80: 87.21 | AC80: 10.41 | AD80: Swiggy | AE80: Burgrill | AF80: 5963 | AG80: 5963 | AO80: 32 | AP80: 0 | AW80: 343 | BD80: 343 | BE80: 310.93 | BG80: =BE80+BF80 -> 310.93 | BH80: 32
A81: Store 1 | B81: 110027 | C81: Outlet | D81: Burgrill | E81: 45962 | F81: RJ390613 | G81: zomato | H81: =IF(G81="POS","Direct Sale","Aggregator") -> Aggregator | I81: 7434931967 | J81: 18528960 | K81: 45962.916 | L81: =VALUE(DAY(K81)) -> 1 | M81: =TEXT(K81,"dddd") -> Saturday | N81: =TEXT(K81,"MMMM") -> November | O81: 0.91597222 | P81: =_xlfn.IFS(L81<=7,"Week 1",L81<=15, "Week 2",L81<=23,"Week 3",L81<=30,"Week 4") -> Week 1 | Q81: No | R81: 449 | S81: -100 | T81: =ABS((S81/R81)*100) -> 22.271715 | U81: 349 | V81: 32 | W81: 0 | X81: 0 | Y81: 381 | Z81: 381 | AA81: Zomato | AB81: 81.84 | AC81: 9.82 | AD81: Zomato | AE81: Burgrill | AF81: 1967 | AG81: 1967 | AO81: 32 | AP81: 0 | AX81: 381 | BD81: 381 | BE81: 349 | BG81: =BE81+BF81 -> 349 | BI81: 32
A82: Store 1 | B82: 110027 | C82: Outlet | D82: Burgrill | E82: 45962 | F82: RJ390615 | G82: swiggy | H82: =IF(G82="POS","Direct Sale","Aggregator") -> Aggregator | I82: 220984000000000 | J82: 29811 | K82: 45962.919 | L82: =VALUE(DAY(K82)) -> 1 | M82: =TEXT(K82,"dddd") -> Saturday | N82: =TEXT(K82,"MMMM") -> November | O82: 0.91944444 | P82: =_xlfn.IFS(L82<=7,"Week 1",L82<=15, "Week 2",L82<=23,"Week 3",L82<=30,"Week 4") -> Week 1 | Q82: No | R82: 269 | S82: -93.75 | T82: =ABS((S82/R82)*100) -> 34.851301 | U82: 175.25 | V82: 32 | W82: 0 | X82: -0.25 | Y82: 207 | Z82: 207 | AA82: Swiggy | AB82: 70.93 | AC82: 6.51 | AD82: Swiggy | AE82: Burgrill | AF82: 8457 | AG82: 8457 | AO82: 32 | AP82: 0 | AW82: 207 | BD82: 207 | BE82: 175.25 | BG82: =BE82+BF82 -> 175.25 | BH82: 32
A83: Store 1 | B83: 110027 | C83: Outlet | D83: Burgrill | E83: 45962 | F83: RJ390617 | G83: zomato | H83: =IF(G83="POS","Direct Sale","Aggregator") -> Aggregator | I83: 7435517225 | J83: 18528960 | K83: 45962.926 | L83: =VALUE(DAY(K83)) -> 1 | M83: =TEXT(K83,"dddd") -> Saturday | N83: =TEXT(K83,"MMMM") -> November | O83: 0.92569444 | P83: =_xlfn.IFS(L83<=7,"Week 1",L83<=15, "Week 2",L83<=23,"Week 3",L83<=30,"Week 4") -> Week 1 | Q83: No | R83: 646 | S83: -174.5 | T83: =ABS((S83/R83)*100) -> 27.012384 | U83: 471.5 | V83: 32 | W83: 0 | X83: 0 | Y83: 503.5 | Z83: 503.5 | AA83: Zomato | AB83: 127.44 | AC83: 12.36 | AD83: Zomato | AE83: Burgrill | AF83: 7225 | AG83: 7225 | AO83: 32 | AP83: 0 | AX83: 503.5 | BD83: 503.5 | BE83: 471.5 | BG83: =BE83+BF83 -> 471.5 | BI83: 32
A84: Store 1 | B84: 110027 | C84: Outlet | D84: Burgrill | E84: 45962 | F84: RJ390618 | G84: zomato | H84: =IF(G84="POS","Direct Sale","Aggregator") -> Aggregator | I84: 7434136750 | J84: 18528960 | K84: 45962.926 | L84: =VALUE(DAY(K84)) -> 1 | M84: =TEXT(K84,"dddd") -> Saturday | N84: =TEXT(K84,"MMMM") -> November | O84: 0.92638889 | P84: =_xlfn.IFS(L84<=7,"Week 1",L84<=15, "Week 2",L84<=23,"Week 3",L84<=30,"Week 4") -> Week 1 | Q84: No | R84: 458 | S84: -100 | T84: =ABS((S84/R84)*100) -> 21.834061 | U84: 358 | V84: 32 | W84: 0 | X84: 0 | Y84: 390 | Z84: 390 | AA84: Zomato | AB84: 95.27 | AC84: 9.73 | AD84: Zomato | AE84: Burgrill | AF84: 6750 | AG84: 6750 | AO84: 32 | AP84: 0 | AX84: 390 | BD84: 390 | BE84: 358 | BG84: =BE84+BF84 -> 358 | BI84: 32
A85: Store 1 | B85: 110027 | C85: Outlet | D85: Burgrill | E85: 45962 | F85: RJ390619 | G85: swiggy | H85: =IF(G85="POS","Direct Sale","Aggregator") -> Aggregator | I85: 220985000000000 | J85: 29811 | K85: 45962.928 | L85: =VALUE(DAY(K85)) -> 1 | M85: =TEXT(K85,"dddd") -> Saturday | N85: =TEXT(K85,"MMMM") -> November | O85: 0.92777778 | P85: =_xlfn.IFS(L85<=7,"Week 1",L85<=15, "Week 2",L85<=23,"Week 3",L85<=30,"Week 4") -> Week 1 | Q85: No | R85: 238 | S85: -90 | T85: =ABS((S85/R85)*100) -> 37.815126 | U85: 148 | V85: 32 | W85: 0 | X85: 0 | Y85: 180 | Z85: 180 | AA85: Swiggy | AB85: 43.9 | AC85: 3.92 | AD85: Swiggy | AE85: Burgrill | AF85: 9512 | AG85: 9512 | AO85: 32 | AP85: 0 | AW85: 180 | BD85: 180 | BE85: 148 | BG85: =BE85+BF85 -> 148 | BH85: 32
A86: Store 1 | B86: 110027 | C86: Outlet | D86: Burgrill | E86: 45962 | F86: RJ390620 | G86: POS | H86: =IF(G86="POS","Direct Sale","Aggregator") -> Direct Sale | K86: 45962.931 | L86: =VALUE(DAY(K86)) -> 1 | M86: =TEXT(K86,"dddd") -> Saturday | N86: =TEXT(K86,"MMMM") -> November | O86: 0.93125 | P86: =_xlfn.IFS(L86<=7,"Week 1",L86<=15, "Week 2",L86<=23,"Week 3",L86<=30,"Week 4") -> Week 1 | Q86: No | R86: 179 | S86: 0 | T86: =ABS((S86/R86)*100) -> 0 | U86: 179 | V86: 0 | W86: 8.96 | X86: 0.04 | Y86: 188 | Z86: 188 | AA86: Card | AB86: 37.58 | AC86: 2.56 | AD86: Burgrill Dine In | AE86: Dine In | AI86: RJFXN3YM | AJ86: Burgrill | AK86: 8929758003 | AO86: 0 | AP86: 0 | AQ86: 188 | AZ86: 179 | BA86: 4.48 | BB86: 179 | BC86: 4.48 | BD86: 188 | BE86: 179 | BG86: =BE86+BF86 -> 179
A87: Store 1 | B87: 110027 | C87: Outlet | D87: Burgrill | E87: 45962 | F87: RJ390611 | G87: POS | H87: =IF(G87="POS","Direct Sale","Aggregator") -> Direct Sale | K87: 45962.933 | L87: =VALUE(DAY(K87)) -> 1 | M87: =TEXT(K87,"dddd") -> Saturday | N87: =TEXT(K87,"MMMM") -> November | O87: 0.93263889 | P87: =_xlfn.IFS(L87<=7,"Week 1",L87<=15, "Week 2",L87<=23,"Week 3",L87<=30,"Week 4") -> Week 1 | Q87: No | R87: 1023 | S87: 0 | T87: =ABS((S87/R87)*100) -> 0 | U87: 1023 | V87: 0 | W87: 51.16 | X87: -0.16 | Y87: 1074 | Z87: 1074 | AA87: Card | AB87: 268.97 | AC87: 11.54 | AD87: Burgrill Dine In | AE87: Dine In | AI87: RJFXN3YM | AJ87: Burgrill | AK87: 8929758003 | AO87: 0 | AP87: 0 | AQ87: 1074 | AZ87: 1023 | BA87: 25.58 | BB87: 1023 | BC87: 25.58 | BD87: 1074 | BE87: 1023 | BG87: =BE87+BF87 -> 1023
A88: Store 1 | B88: 110027 | C88: Outlet | D88: Burgrill | E88: 45962 | F88: RJ390607 | G88: POS | H88: =IF(G88="POS","Direct Sale","Aggregator") -> Direct Sale | K88: 45962.933 | L88: =VALUE(DAY(K88)) -> 1 | M88: =TEXT(K88,"dddd") -> Saturday | N88: =TEXT(K88,"MMMM") -> November | O88: 0.93263889 | P88: =_xlfn.IFS(L88<=7,"Week 1",L88<=15, "Week 2",L88<=23,"Week 3",L88<=30,"Week 4") -> Week 1 | Q88: No | R88: 625.43 | S88: 0 | T88: =ABS((S88/R88)*100) -> 0 | U88: 625.43 | V88: 0 | W88: 31.28 | X88: 0.29 | Y88: 657 | Z88: 657 | AA88: Card | AB88: 138.79 | AC88: 10.5 | AD88: Burgrill Dine In | AE88: Dine In | AI88: RJFXN3YM | AJ88: Burgrill | AK88: 8929758003 | AO88: 0 | AP88: 0 | AQ88: 657 | AZ88: 625.43 | BA88: 15.64 | BB88: 625.43 | BC88: 15.64 | BD88: 657 | BE88: 625.43 | BG88: =BE88+BF88 -> 625.43
A89: Store 1 | B89: 110027 | C89: Outlet | D89: Burgrill | E89: 45962 | F89: RJ390570 | G89: POS | H89: =IF(G89="POS","Direct Sale","Aggregator") -> Direct Sale | K89: 45962.933 | L89: =VALUE(DAY(K89)) -> 1 | M89: =TEXT(K89,"dddd") -> Saturday | N89: =TEXT(K89,"MMMM") -> November | O89: 0.93263889 | P89: =_xlfn.IFS(L89<=7,"Week 1",L89<=15, "Week 2",L89<=23,"Week 3",L89<=30,"Week 4") -> Week 1 | Q89: No | R89: 1055 | S89: 0 | T89: =ABS((S89/R89)*100) -> 0 | U89: 1055 | V89: 0 | W89: 52.76 | X89: 0.24 | Y89: 1108 | Z89: 1108 | AA89: Card | AB89: 259.15 | AC89: 28.39 | AD89: Takeaway | AI89: GFCWJ7BX | AJ89: karan | AK89: 9818679848 | AO89: 0 | AP89: 0 | AQ89: 1108 | AZ89: 1055 | BA89: 26.38 | BB89: 1055 | BC89: 26.38 | BD89: 1108 | BE89: 1055 | BG89: =BE89+BF89 -> 1055
A90: Store 1 | B90: 110027 | C90: Outlet | D90: Burgrill | E90: 45962 | F90: RJ390616 | G90: POS | H90: =IF(G90="POS","Direct Sale","Aggregator") -> Direct Sale | K90: 45962.935 | L90: =VALUE(DAY(K90)) -> 1 | M90: =TEXT(K90,"dddd") -> Saturday | N90: =TEXT(K90,"MMMM") -> November | O90: 0.93541667 | P90: =_xlfn.IFS(L90<=7,"Week 1",L90<=15, "Week 2",L90<=23,"Week 3",L90<=30,"Week 4") -> Week 1 | Q90: No | R90: 196 | S90: 0 | T90: =ABS((S90/R90)*100) -> 0 | U90: 196 | V90: 0 | W90: 9.8 | X90: 0.2 | Y90: 206 | Z90: 206 | AA90: Card | AB90: 50.23 | AC90: 4.1 | AD90: Burgrill Dine In | AE90: Dine In | AI90: Z3PZWUEE | AJ90: dhruv | AK90: 9213555055 | AO90: 0 | AP90: 0 | AQ90: 206 | AZ90: 196 | BA90: 4.9 | BB90: 196 | BC90: 4.9 | BD90: 206 | BE90: 196 | BG90: =BE90+BF90 -> 196
A91: Store 1 | B91: 110027 | C91: Outlet | D91: Burgrill | E91: 45962 | F91: RJ390614 | G91: POS | H91: =IF(G91="POS","Direct Sale","Aggregator") -> Direct Sale | K91: 45962.936 | L91: =VALUE(DAY(K91)) -> 1 | M91: =TEXT(K91,"dddd") -> Saturday | N91: =TEXT(K91,"MMMM") -> November | O91: 0.93611111 | P91: =_xlfn.IFS(L91<=7,"Week 1",L91<=15, "Week 2",L91<=23,"Week 3",L91<=30,"Week 4") -> Week 1 | Q91: No | R91: 189 | S91: 0 | T91: =ABS((S91/R91)*100) -> 0 | U91: 189 | V91: 0 | W91: 9.46 | X91: -0.46 | Y91: 198 | Z91: 198 | AA91: Cash | AB91: 47.06 | AC91: 1.96 | AD91: Burgrill Dine In | AE91: Dine In | AI91: 7111VIGN | AJ91: burgrill | AK91: 8929728003 | AO91: 0 | AP91: 0 | AR91: 198 | AZ91: 189 | BA91: 4.73 | BB91: 189 | BC91: 4.73 | BD91: 198 | BE91: 189 | BG91: =BE91+BF91 -> 189
A92: Store 1 | B92: 110027 | C92: Outlet | D92: Burgrill | E92: 45962 | F92: RJ390565 | G92: POS | H92: =IF(G92="POS","Direct Sale","Aggregator") -> Direct Sale | K92: 45962.936 | L92: =VALUE(DAY(K92)) -> 1 | M92: =TEXT(K92,"dddd") -> Saturday | N92: =TEXT(K92,"MMMM") -> November | O92: 0.93611111 | P92: =_xlfn.IFS(L92<=7,"Week 1",L92<=15, "Week 2",L92<=23,"Week 3",L92<=30,"Week 4") -> Week 1 | Q92: No | R92: 379 | S92: 0 | T92: =ABS((S92/R92)*100) -> 0 | U92: 379 | V92: 0 | W92: 18.96 | X92: 0.04 | Y92: 398 | Z92: 398 | AA92: Card | AB92: 98.28 | AC92: 8.72 | AD92: Burgrill Dine In | AE92: Dine In | AI92: RZF7ACWG | AJ92: sarabjeet | AK92: 9990003553 | AO92: 0 | AP92: 0 | AQ92: 398 | AZ92: 379 | BA92: 9.48 | BB92: 379 | BC92: 9.48 | BD92: 398 | BE92: 379 | BG92: =BE92+BF92 -> 379
A93: Store 1 | B93: 110027 | C93: Outlet | D93: Burgrill | E93: 45962 | F93: RJ390582 | G93: POS | H93: =IF(G93="POS","Direct Sale","Aggregator") -> Direct Sale | K93: 45962.938 | L93: =VALUE(DAY(K93)) -> 1 | M93: =TEXT(K93,"dddd") -> Saturday | N93: =TEXT(K93,"MMMM") -> November | O93: 0.93819444 | P93: =_xlfn.IFS(L93<=7,"Week 1",L93<=15, "Week 2",L93<=23,"Week 3",L93<=30,"Week 4") -> Week 1 | Q93: No | R93: 356 | S93: 0 | T93: =ABS((S93/R93)*100) -> 0 | U93: 356 | V93: 0 | W93: 17.8 | X93: 0.2 | Y93: 374 | Z93: 374 | AA93: Card | AB93: 95.75 | AC93: 9.26 | AD93: Takeaway | AI93: RJFXN3YM | AJ93: Burgrill | AK93: 8929758003 | AO93: 0 | AP93: 0 | AQ93: 374 | AZ93: 356 | BA93: 8.9 | BB93: 356 | BC93: 8.9 | BD93: 374 | BE93: 356 | BG93: =BE93+BF93 -> 356
A94: Store 1 | B94: 110027 | C94: Outlet | D94: Burgrill | E94: 45962 | F94: RJ390622 | G94: zomato | H94: =IF(G94="POS","Direct Sale","Aggregator") -> Aggregator | I94: 7439223267 | J94: 18528960 | K94: 45962.944 | L94: =VALUE(DAY(K94)) -> 1 | M94: =TEXT(K94,"dddd") -> Saturday | N94: =TEXT(K94,"MMMM") -> November | O94: 0.94375 | P94: =_xlfn.IFS(L94<=7,"Week 1",L94<=15, "Week 2",L94<=23,"Week 3",L94<=30,"Week 4") -> Week 1 | Q94: No | R94: 478.43 | S94: -75 | T94: =ABS((S94/R94)*100) -> 15.676274 | U94: 403.43 | V94: 32 | W94: 0 | X94: 0 | Y94: 435.43 | Z94: 435.43 | AA94: Zomato | AB94: 94.18 | AC94: 10.1 | AD94: Zomato | AE94: Burgrill | AF94: 3267 | AG94: 3267 | AO94: 32 | AP94: 0 | AX94: 435.43 | BD94: 435.43 | BE94: 403.43 | BG94: =BE94+BF94 -> 403.43 | BI94: 32
A95: Store 1 | B95: 110027 | C95: Outlet | D95: Burgrill | E95: 45962 | F95: RJ390626 | G95: swiggy | H95: =IF(G95="POS","Direct Sale","Aggregator") -> Aggregator | I95: 220988000000000 | J95: 29811 | K95: 45962.96 | L95: =VALUE(DAY(K95)) -> 1 | M95: =TEXT(K95,"dddd") -> Saturday | N95: =TEXT(K95,"MMMM") -> November | O95: 0.96041667 | P95: =_xlfn.IFS(L95<=7,"Week 1",L95<=15, "Week 2",L95<=23,"Week 3",L95<=30,"Week 4") -> Week 1 | Q95: No | R95: 417 | S95: -93.75 | T95: =ABS((S95/R95)*100) -> 22.482014 | U95: 323.25 | V95: 32 | W95: 0 | X95: -0.25 | Y95: 355 | Z95: 355 | AA95: Swiggy | AB95: 81.96 | AC95: 10.46 | AD95: Swiggy | AE95: Burgrill | AF95: 4044 | AG95: 4044 | AO95: 32 | AP95: 0 | AW95: 355 | BD95: 355 | BE95: 323.25 | BG95: =BE95+BF95 -> 323.25 | BH95: 32
A96: Store 1 | B96: 110027 | C96: Outlet | D96: Burgrill | E96: 45962 | F96: RJ390627 | G96: POS | H96: =IF(G96="POS","Direct Sale","Aggregator") -> Direct Sale | K96: 45962.968 | L96: =VALUE(DAY(K96)) -> 1 | M96: =TEXT(K96,"dddd") -> Saturday | N96: =TEXT(K96,"MMMM") -> November | O96: 0.96805556 | P96: =_xlfn.IFS(L96<=7,"Week 1",L96<=15, "Week 2",L96<=23,"Week 3",L96<=30,"Week 4") -> Week 1 | Q96: No | R96: 379 | S96: 0 | T96: =ABS((S96/R96)*100) -> 0 | U96: 379 | V96: 0 | W96: 18.96 | X96: 0.04 | Y96: 398 | Z96: 398 | AA96: Cash | AB96: 98.28 | AC96: 8.72 | AD96: Burgrill Dine In | AE96: Dine In | AI96: RJFXN3YM | AJ96: Burgrill | AK96: 8929758003 | AO96: 0 | AP96: 0 | AR96: 398 | AZ96: 379 | BA96: 9.48 | BB96: 379 | BC96: 9.48 | BD96: 398 | BE96: 379 | BG96: =BE96+BF96 -> 379
A97: Store 1 | B97: 110027 | C97: Outlet | D97: Burgrill | E97: 45962 | F97: RJ390630 | G97: swiggy | H97: =IF(G97="POS","Direct Sale","Aggregator") -> Aggregator | I97: 220989000000000 | J97: 29811 | K97: 45962.97 | L97: =VALUE(DAY(K97)) -> 1 | M97: =TEXT(K97,"dddd") -> Saturday | N97: =TEXT(K97,"MMMM") -> November | O97: 0.97013889 | P97: =_xlfn.IFS(L97<=7,"Week 1",L97<=15, "Week 2",L97<=23,"Week 3",L97<=30,"Week 4") -> Week 1 | Q97: No | R97: 218 | S97: -90 | T97: =ABS((S97/R97)*100) -> 41.284404 | U97: 128 | V97: 32 | W97: 0 | X97: 0 | Y97: 160 | Z97: 160 | AA97: Swiggy | AB97: 41.43 | AC97: 3.92 | AD97: Swiggy | AE97: Burgrill | AF97: 2888 | AG97: 2888 | AO97: 32 | AP97: 0 | AW97: 160 | BD97: 160 | BE97: 128 | BG97: =BE97+BF97 -> 128 | BH97: 32
A98: Store 1 | B98: 110027 | C98: Outlet | D98: Burgrill | E98: 45962 | F98: RJ390631 | G98: POS | H98: =IF(G98="POS","Direct Sale","Aggregator") -> Direct Sale | K98: 45962.974 | L98: =VALUE(DAY(K98)) -> 1 | M98: =TEXT(K98,"dddd") -> Saturday | N98: =TEXT(K98,"MMMM") -> November | O98: 0.97361111 | P98: =_xlfn.IFS(L98<=7,"Week 1",L98<=15, "Week 2",L98<=23,"Week 3",L98<=30,"Week 4") -> Week 1 | Q98: No | R98: 239 | S98: 0 | T98: =ABS((S98/R98)*100) -> 0 | U98: 239 | V98: 0 | W98: 11.96 | X98: 0.04 | Y98: 251 | Z98: 251 | AA98: Card | AB98: 67.25 | AC98: 2.9 | AD98: Burgrill Dine In | AE98: Dine In | AI98: RJFXN3YM | AJ98: Burgrill | AK98: 8929758003 | AO98: 0 | AP98: 0 | AQ98: 251 | AZ98: 239 | BA98: 5.98 | BB98: 239 | BC98: 5.98 | BD98: 251 | BE98: 239 | BG98: =BE98+BF98 -> 239
A99: Store 1 | B99: 110027 | C99: Outlet | D99: Burgrill | E99: 45962 | F99: RJ390632 | G99: POS | H99: =IF(G99="POS","Direct Sale","Aggregator") -> Direct Sale | K99: 45962.974 | L99: =VALUE(DAY(K99)) -> 1 | M99: =TEXT(K99,"dddd") -> Saturday | N99: =TEXT(K99,"MMMM") -> November | O99: 0.97361111 | P99: =_xlfn.IFS(L99<=7,"Week 1",L99<=15, "Week 2",L99<=23,"Week 3",L99<=30,"Week 4") -> Week 1 | Q99: No | R99: 179 | S99: 0 | T99: =ABS((S99/R99)*100) -> 0 | U99: 179 | V99: 0 | W99: 8.96 | X99: 0.04 | Y99: 188 | Z99: 188 | AA99: Card | AB99: 35.27 | AC99: 8.05 | AD99: Burgrill Dine In | AE99: Dine In | AI99: RJFXN3YM | AJ99: Burgrill | AK99: 8929758003 | AO99: 0 | AP99: 0 | AQ99: 188 | AZ99: 179 | BA99: 4.48 | BB99: 179 | BC99: 4.48 | BD99: 188 | BE99: 179 | BG99: =BE99+BF99 -> 179
A100: Store 1 | B100: 110027 | C100: Outlet | D100: Burgrill | E100: 45962 | F100: RJ390629 | G100: POS | H100: =IF(G100="POS","Direct Sale","Aggregator") -> Direct Sale | K100: 45962.974 | L100: =VALUE(DAY(K100)) -> 1 | M100: =TEXT(K100,"dddd") -> Saturday | N100: =TEXT(K100,"MMMM") -> November | O100: 0.97430556 | P100: =_xlfn.IFS(L100<=7,"Week 1",L100<=15, "Week 2",L100<=23,"Week 3",L100<=30,"Week 4") -> Week 1 | Q100: No | R100: 627 | S100: 0 | T100: =ABS((S100/R100)*100) -> 0 | U100: 627 | V100: 0 | W100: 31.36 | X100: -0.36 | Y100: 658 | Z100: 658 | AA100: Card | AB100: 188.73 | AC100: 7.76 | AD100: Burgrill Dine In | AE100: Dine In | AI100: RJFXN3YM | AJ100: Burgrill | AK100: 8929758003 | AO100: 0 | AP100: 0 | AQ100: 658 | AZ100: 627 | BA100: 15.68 | BB100: 627 | BC100: 15.68 | BD100: 658 | BE100: 627 | BG100: =BE100+BF100 -> 627
...

Sheet EDA
B2: EDA | AL2: =AJ2-AK2 -> 0
AL3: =AJ3-AK3 -> 0
A5: Objective 1 | B5: What were the Total Revenue, Total Orders, and Average Order Value (AOV) for the month?
B7: Week | C7: Revenue | D7: No. of Orders | E7: Avg Order value
B8: Week 1 | C8: 437093.54 | D8: 1198 | E8: =C8/D8 -> 364.8527
B9: Week 2 | C9: 451309.67 | D9: 1258 | E9: =C9/D9 -> 358.75172
B10: Week 3 | C10: 485338.79 | D10: 1333 | E10: =C10/D10 -> 364.09512
B11: Week 4 | C11: 404741.43 | D11: 1183 | E11: =C11/D11 -> 342.13139
B12: Total | C12: =SUM(C8:C11) -> 1778483.4 | D12: =SUM(D8:D11) -> 4972 | E12: =AVERAGE(E8:E11) -> 357.45773
B14: Note - Pivots were used to achieve the objective
A18: Objective 2 | B18: Which channel has the highest AOV?
A19: Objective 3 | B19: Which channel contributes the most to the total volume of orders?
B21: Channels | C21: Revenue | D21: No. Of Orders | E21: Avg Order value
B22: Burgrill Dine In | C22: 465524 | D22: 1366 | E22: =C22/D22 -> 340.79356
B23: magicpin | C23: 4642.92 | D23: 31 | E23: =C23/D23 -> 149.77161
B24: Swiggy | C24: 666917 | D24: 1913 | E24: =C24/D24 -> 348.62363
B25: Takeaway | C25: 102872 | D25: 251 | E25: =C25/D25 -> 409.84861
B26: TSF Dine In | C26: 1430 | D26: 7 | E26: =C26/D26 -> 204.28571
B27: Zomato | C27: 537097.51 | D27: 1404 | E27: =C27/D27 -> 382.54808
B28: Grand Total | C28: =SUM(C22:C27) -> 1778483.4 | D28: =SUM(D22:D27) -> 4972 | E28: =AVERAGE(E22:E27) -> 305.97853
B30: Note - Pivots were used to achieve the objective
A34: Objective 4 | B34: Compare the performance of Aggregators (Swiggy/Zomato) vs. Direct Channels (POS/Dine-in/Takeaway).
B37: Order Source | C37: Revenue
B38: Aggregator | C38: 1208657.4
B39: Direct Sale | C39: 569826
B41: Note - Column H introduced to classify aggregators VS Direct channels using simple IF formula
A44: Objective 5 | B44: Create a heatmap or bar chart showing transaction volume by Hour of the Day
B48: Hours | C48: Revenue
B49: 00 | C49: 171624.58
B50: 01 | C50: 141850.55
B51: 02 | C51: 102898.95
B52: 03 | C52: 85062.1
B53: 04 | C53: 74693.54
B54: 05 | C54: 7928
B55: 06 | C55: 3802
B56: 11 | C56: 12272.5
B57: 12 | C57: 18813.9
B58: 13 | C58: 33182.5
B59: 14 | C59: 52319.55
B60: 15 | C60: 64927.58
... B68: 23 | C68: 156034.78
B70: Note - Extracted hours from column Invoice Date using delimiter then used Text function to extract hour
A74: Objective 6 | B74: Is there a correlation between high discounts and specific Order Sources (e.g., does Zomato have higher discounting than POS)?
B78: Order Source | C78: Avg Discount %
B79: magicpin | C79: 40.524788
B80: POS | C80: 1.1302953
B81: swiggy | C81: 28.059025
B82: zomato | C82: 28.768841
B83: Grand Total | C83: 19.541479
B85: Note - Discount % calculated using discount/Gross Amount and then pivot table used to summarize
A89: Objective 7 | B89: Identify the top 5 customers by revenue.
B92: Customer Id | C92: Customer NAME | D92: Order value
B93: RJFXN3YM | C93: =VLOOKUP(B92,Main!$AI:$AJ,2,0) -> Customer Name | D93: 307529
B94: CSJG3RLQ | C94: =VLOOKUP(B93,Main!$AI:$AJ,2,0) -> Burgrill | D94: 5457
B95: IHJA8G9L | C95: =VLOOKUP(B94,Main!$AI:$AJ,2,0) -> pritha | D95: 13920
B96: Z2I2I6YH | C96: =VLOOKUP(B95,Main!$AI:$AJ,2,0) -> NOT | D96: 68412
B97: NH1WMWIA | C97: =VLOOKUP(B96,Main!$AI:$AJ,2,0) -> not given by customer | D97: 9063
B99: Note - Unique Customer ID were taken by removing duplicates and then used sumif formula to identify their order value and then conditional formatting used to identify top 5 customers
A103: Objective 8 | B103: Calculate the percentage of "Repeat Customers" (customers who placed more than 1 order in Nov 2025).
B105: Repetition | C105: % repetition | D105: No of orders | E105: Revenue | F105: Avg Order value
B106: Repeated customer | C106: =(Reference_sheet!L2/SUM(Reference_sheet!$L$2:$L$3))*100 -> 78.791541 | D106: =SUMIF(Reference_sheet!$I:$I,EDA!B106,Reference_sheet!$H:$H) -> 1304 | E106: =SUMIF(Reference_sheet!$I:$I,EDA!B106,Reference_sheet!$G:$G) -> 440176.66 | F106: =E106/D106 -> 337.55879
B107: Non Repeated customer | C107: =(Reference_sheet!L3/SUM(Reference_sheet!$L$2:$L$3))*100 -> 21.208459 | D107: =SUMIF(Reference_sheet!$I:$I,EDA!B107,Reference_sheet!$H:$H) -> 351 | E107: =SUMIF(Reference_sheet!$I:$I,EDA!B107,Reference_sheet!$G:$G) -> 134292.26 | F107: =E107/D107 -> 382.59903
B109: Note - Use Reference sheet to understand the approach used to segregate customers into above 2 categories
A113: Objective 9 | B113: Total revenueand No. of Orders by Day
B115: Day | C115: Revenue | D115: No. of Orders
B116: Mon | C116: 240734.72 | D116: 679
B117: Tue | C117: 198570.83 | D117: 575
B118: Wed | C118: 212502.36 | D118: 612
B119: Thur | C119: 228636.77 | D119: 662
B120: Fri | C120: 248251.07 | D120: 672
B121: Sat | C121: 302049.69 | D121: 856
B122: Sun | C122: 347737.99 | D122: 916
B124: Note - Day extracted using Text(Cell_ref , "DDDD") function) and then Pivot table used to achieve the objective

Sheet Conclusion
G2: Burgrill India - Rajouri garden Outlet NOV'25
D13: Analyzing the weekly sales summary by Revenue , No. of Orders and AOV | O13: Analyzing Total revenue by individual Channels of Sale
D32: Key Insights | O32: Key Insights
D33: * Week 4 attracts least customers , Additional discounts can be during week 3 | O33: * Direct channels produce only 1/3 of the Total Sales
D34: * Week 3 attracts highest footfall , so additional inventory can be introduced | O34: * TSF dine in is not producing results , some product in the segment
D35: in order to meet demand | O35: launch may change the game
D39: Analyzing No. of Orders and AOV by Individual channels | O39: Analyzing performance of Aggregators (Swiggy/Zomato) vs.
O40: Direct Channels (POS/Dine-in/Takeaway).
D59: Key Insights | O59: Key Insights
D60: * Swiggy produces highest No. of orders followed by Zomato | O60: * Direct channels produce only 1/3 of the Total Sales
D61: * Magicpin , Takeaway and TSF Dine produces lowest no. of Orders
D67: Analyzing Revenue by Hours of the day | O67: Avg % Discount given by Different channels
D89: Key Insights | O89: Key Insights
D90: * 12-1 am , 8-12 pm are the rush hours so resources can be used efficiently and accordingly | O90: * Dscount given by POS order source is very less compartively ,
D91: * From 5 am till 3 pm , engagement is less so resources can be used accordingly | O91: which can be key reason for less revenue
D98: Analyzing Top 5 customers and Revenue by them | O98: Bifurcation of repeated VS Non repeated customers by No. of Orders
D119: Key Insights | O119: Key Insights
D120: * Top customers can bring more footfall , so they should be given | O120: * Repeated customers % is very high which means the service and product quality is
D121: some extra perks/benefits for organic growth | O121: good which should be maintained going forward
D127: Revenue and No. of orders by Day of the week
D150: Key Insights
D151: * More Workforce should be provided on Weekends
D152: * Tuesday attracts least customers , so some resources can pulled away
D153: in order to manage efficiency

Sheet Notes
B2: Notes | BE2: =BC2-BD2 -> 0
B4: Note No. | C4: Column_Affected | D4: Operations exceuted | BE4: =BC4-BD4 -> 0
B5: 1 | C5: K | D5: Converted column K to custom format i.e., dd-mm-yyyy hh:mm | BE5: =BC5-BD5 -> 0
B6: 2 | C6: O | D6: Extracted hours using delimiter the text function | BE6: =BC6-BD6 -> 0
B7: 3 | C7: P | D7: Formula Used - IFS(L2<=7,"Week 1",L2<=15, "Week 2",L2<=23,"Week 3",L2<=30,"Week 4")
B8: 4 | C8: L , M ,N , O , P | D8: Columns introduced for retrieve deep insights
B9: 5 | C9: AD | D9: Cleaned the data in column Channel by using replacing magicpin-burgrill values to burgrill-magicpin also TSF- Dine In to TSF- TSF Dine In and then used delimiter to make data usable
B10: 6 | C10: H | D10: Added and additional column to distinguish direct sale vs aggregator by passing simple if formula
B11: 7 | D11: Brand - "The Sausage fest contribution is minimal in overall Revenue ,Therefore no points in segregation

Sheet Reference_sheet
A1: Invoice Number | B1: Customer Id | C1: Customer Name | D1: Paid Amount | F1: Customer Id | G1: Revenue | H1: Count Of orders | I1: Customer Repetition | K1: Customer Repetition | L1: Count | M1: Revenue
A2: RJ390531 | D2: 289 | F2: 4VS4ZNEI | G2: =SUMIF($B:$B,F2,$D:$D) -> 124 | H2: =COUNTIF($B:$B,F2) -> 2 | I2: =IF(H2>1,"Repeated customer","Non Repeated customer") -> Repeated customer | K2: Repeated customer | L2: =SUMIF($I:$I,I2,$H:$H) -> 1304 | M2: =SUMIF(I:I,K2,G:G) -> 440176.66
A3: RJ390532 | D3: 514 | F3: R7ZUEYAL | G3: =SUMIF($B:$B,F3,$D:$D) -> 167 | H3: =COUNTIF($B:$B,F3) -> 1 | I3: =IF(H3>1,"Repeated customer","Non Repeated customer") -> Non Repeated customer | K3: Non Repeated customer | L3: =SUMIF($I:$I,I3,$H:$H) -> 351 | M3: =SUMIF(I:I,K3,G:G) -> 134292.26
A4: RJ390530 | B4: 4VS4ZNEI | C4: vipin | D4: 62 | F4: RJFXN3YM | G4: =SUMIF($B:$B,F4,$D:$D) -> 307529 | H4: =COUNTIF($B:$B,F4) -> 927 | I4: =IF(H4>1,"Repeated customer","Non Repeated customer") -> Repeated customer
A5: RJ390529 | B5: R7ZUEYAL | C5: naman | D5: 167 | F5: BCTCUL8A | G5: =SUMIF($B:$B,F5,$D:$D) -> 374 | H5: =COUNTIF($B:$B,F5) -> 1 | I5: =IF(H5>1,"Repeated customer","Non Repeated customer") -> Non Repeated customer
A6: RJ390533 | D6: 375 | F6: E9WZ2UG5 | G6: =SUMIF($B:$B,F6,$D:$D) -> 167 | H6: =COUNTIF($B:$B,F6) -> 1 | I6: =IF(H6>1,"Repeated customer","Non Repeated customer") -> Non Repeated customer
A7: RJ390537 | D7: 316 | F7: GIDIRMS3 | G7: =SUMIF($B:$B,F7,$D:$D) -> 387 | H7: =COUNTIF($B:$B,F7) -> 1 | I7: =IF(H7>1,"Repeated customer","Non Repeated customer") -> Non Repeated customer
A8: RJ390538 | D8: 340 | F8: I8Y3EPU8 | G8: =SUMIF($B:$B,F8,$D:$D) -> 463 | H8: =COUNTIF($B:$B,F8) -> 2 | I8: =IF(H8>1,"Repeated customer","Non Repeated customer") -> Repeated customer
A9: RJ390539 | D9: 240 | F9: MJHTLH2P | G9: =SUMIF($B:$B,F9,$D:$D) -> 627 | H9: =COUNTIF($B:$B,F9) -> 1 | I9: =IF(H9>1,"Repeated customer","Non Repeated customer") -> Non Repeated customer
A10: RJ390540 | D10: 446 | F10: ZQVQWXQQ | G10: =SUMIF($B:$B,F10,$D:$D) -> 387 | H10: =COUNTIF($B:$B,F10) -> 1 | I10: =IF(H10>1,"Repeated customer","Non Repeated customer") -> Non Repeated customer
A11: RJ390541 | D11: 332 | F11: D8MDIGHA | G11: =SUMIF($B:$B,F11,$D:$D) -> 147 | H11: =COUNTIF($B:$B,F11) -> 1 | I11: =IF(H11>1,"Repeated customer","Non Repeated customer") -> Non Repeated customer
A12: RJ390542 | D12: 206 | F12: CSNWY5P7 | G12: =SUMIF($B:$B,F12,$D:$D) -> 356 | H12: =COUNTIF($B:$B,F12) -> 1 | I12: =IF(H12>1,"Repeated customer","Non Repeated customer") -> Non Repeated customer
A13: RJ390543 | D13: 381 | F13: GFCWJ7BX | G13: =SUMIF($B:$B,F13,$D:$D) -> 1108 | H13: =COUNTIF($B:$B,F13) -> 1 | I13: =IF(H13>1,"Repeated customer","Non Repeated customer") -> Non Repeated customer
A14: RJ390544 | D14: 407.16 | F14: Z3PZWUEE | G14: =SUMIF($B:$B,F14,$D:$D) -> 206 | H14: =COUNTIF($B:$B,F14) -> 1 | I14: =IF(H14>1,"Repeated customer","Non Repeated customer") -> Non Repeated customer
A15: RJ390545 | D15: 196 | F15: 7111VIGN | G15: =SUMIF($B:$B,F15,$D:$D) -> 542 | H15: =COUNTIF($B:$B,F15) -> 2 | I15: =IF(H15>1,"Repeated customer","Non Repeated customer") -> Repeated customer
A16: RJ390534 | B16: RJFXN3YM | C16: Burgrill | D16: 302 | F16: RZF7ACWG | G16: =SUMIF($B:$B,F16,$D:$D) -> 398 | H16: =COUNTIF($B:$B,F16) -> 1 | I16: =IF(H16>1,"Repeated customer","Non Repeated customer") -> Non Repeated customer
A17: RJ390535 | B17: BCTCUL8A | C17: ms | D17: 374 | F17: CSJG3RLQ | G17: =SUMIF($B:$B,F17,$D:$D) -> 5457 | H17: =COUNTIF($B:$B,F17) -> 8 | I17: =IF(H17>1,"Repeated customer","Non Repeated customer") -> Repeated customer
A18: RJ390536 | B18: RJFXN3YM | C18: Burgrill | D18: 70 | F18: KDH32EH3 | G18: =SUMIF($B:$B,F18,$D:$D) -> 187 | H18: =COUNTIF($B:$B,F18) -> 1 | I18: =IF(H18>1,"Repeated customer","Non Repeated customer") -> Non Repeated customer
A19: RJ390546 | D19: 447 | F19: TTRZHK6Y | G19: =SUMIF($B:$B,F19,$D:$D) -> 104 | H19: =COUNTIF($B:$B,F19) -> 1 | I19: =IF(H19>1,"Repeated customer","Non Repeated customer") -> Non Repeated customer
A20: RJ390547 | D20: 352 | F20: GPFKCY88 | G20: =SUMIF($B:$B,F20,$D:$D) -> 722 | H20: =COUNTIF($B:$B,F20) -> 3 | I20: =IF(H20>1,"Repeated customer","Non Repeated customer") -> Repeated customer
A21: RJ390549 | B21: E9WZ2UG5 | C21: sidhi | D21: 167 | F21: N3M6HDPP | G21: =SUMIF($B:$B,F21,$D:$D) -> 104 | H21: =COUNTIF($B:$B,F21) -> 1 | I21: =IF(H21>1,"Repeated customer","Non Repeated customer") -> Non Repeated customer
A22: RJ390550 | D22: 584 | F22: 1WSEBUNY | G22: =SUMIF($B:$B,F22,$D:$D) -> 57 | H22: =COUNTIF($B:$B,F22) -> 1 | I22: =IF(H22>1,"Repeated customer","Non Repeated customer") -> Non Repeated customer
A23: RJ390551 | B23: GIDIRMS3 | C23: hare krishna | D23: 387 | F23: XGI6S685 | G23: =SUMIF($B:$B,F23,$D:$D) -> 2488 | H23: =COUNTIF($B:$B,F23) -> 3 | I23: =IF(H23>1,"Repeated customer","Non Repeated customer") -> Repeated customer
A24: RJ390554 | D24: 446.76 | F24: YUL5NDMV | G24: =SUMIF($B:$B,F24,$D:$D) -> 99 | H24: =COUNTIF($B:$B,F24) -> 1 | I24: =IF(H24>1,"Repeated customer","Non Repeated customer") -> Non Repeated customer
A25: RJ390558 | D25: 256 | F25: 2B7VZ2NK | G25: =SUMIF($B:$B,F25,$D:$D) -> 1106 | H25: =COUNTIF($B:$B,F25) -> 2 | I25: =IF(H25>1,"Repeated customer","Non Repeated customer") -> Repeated customer
A26: RJ390559 | D26: 190 | F26: IAMHW9PJ | G26: =SUMIF($B:$B,F26,$D:$D) -> 1256 | H26: =COUNTIF($B:$B,F26) -> 8 | I26: =IF(H26>1,"Repeated customer","Non Repeated customer") -> Repeated customer
A27: RJ390560 | D27: 1068 | F27: 7CA3D6QC | G27: =SUMIF($B:$B,F27,$D:$D) -> 104 | H27: =COUNTIF($B:$B,F27) -> 1 | I27: =IF(H27>1,"Repeated customer","Non Repeated customer") -> Non Repeated customer
A28: RJ390564 | B28: RJFXN3YM | C28: Burgrill | D28: 208 | F28: C4DIIATA | G28: =SUMIF($B:$B,F28,$D:$D) -> 2595 | H28: =COUNTIF($B:$B,F28) -> 2 | I28: =IF(H28>1,"Repeated customer","Non Repeated customer") -> Repeated customer
A29: RJ390563 | B29: I8Y3EPU8 | C29: shivam | D29: 212 | F29: QJVANHWC | G29: =SUMIF($B:$B,F29,$D:$D) -> 706 | H29: =COUNTIF($B:$B,F29) -> 1 | I29: =IF(H29>1,"Repeated customer","Non Repeated customer") -> Non Repeated customer
A30: RJ390562 | B30: RJFXN3YM | C30: Burgrill | D30: 374 | F30: 6RERAT9A | G30: =SUMIF($B:$B,F30,$D:$D) -> 577 | H30: =COUNTIF($B:$B,F30) -> 4 | I30: =IF(H30>1,"Repeated customer","Non Repeated customer") -> Repeated customer
A31: RJ390561 | B31: RJFXN3YM | C31: Burgrill | D31: 365 | F31: CQ9B8ZYA | G31: =SUMIF($B:$B,F31,$D:$D) -> 792 | H31: =COUNTIF($B:$B,F31) -> 3 | I31: =IF(H31>1,"Repeated customer","Non Repeated customer") -> Repeated customer
A32: RJ390557 | B32: MJHTLH2P | C32: asveed | D32: 627 | F32: MT4VY3JL | G32: =SUMIF($B:$B,F32,$D:$D) -> 98 | H32: =COUNTIF($B:$B,F32) -> 1 | I32: =IF(H32>1,"Repeated customer","Non Repeated customer") -> Non Repeated customer
A33: RJ390556 | B33: RJFXN3YM | C33: Burgrill | D33: 624 | F33: 5L1RSBW1 | G33: =SUMIF($B:$B,F33,$D:$D) -> 173 | H33: =COUNTIF($B:$B,F33) -> 6 | I33: =IF(H33>1,"Repeated customer","Non Repeated customer") -> Repeated customer
A34: RJ390553 | B34: ZQVQWXQQ | C34: new | D34: 387 | F34: D9BL92IU | G34: =SUMIF($B:$B,F34,$D:$D) -> 387 | H34: =COUNTIF($B:$B,F34) -> 1 | I34: =IF(H34>1,"Repeated customer","Non Repeated customer") -> Non Repeated customer
A35: RJ390555 | B35: RJFXN3YM | C35: Burgrill | D35: 62 | F35: 44NP19H2 | G35: =SUMIF($B:$B,F35,$D:$D) -> 147.99 | H35: =COUNTIF($B:$B,F35) -> 1 | I35: =IF(H35>1,"Repeated customer","Non Repeated customer") -> Non Repeated customer
A36: RJ390552 | B36: RJFXN3YM | C36: Burgrill | D36: 532 | F36: GZJWYI9E | G36: =SUMIF($B:$B,F36,$D:$D) -> 251 | H36: =COUNTIF($B:$B,F36) -> 1 | I36: =IF(H36>1,"Repeated customer","Non Repeated customer") -> Non Repeated customer
A37: RJ390548 | B37: RJFXN3YM | C37: Burgrill | D37: 418 | F37: 6VV9XTN3 | G37: =SUMIF($B:$B,F37,$D:$D) -> 656 | H37: =COUNTIF($B:$B,F37) -> 1 | I37: =IF(H37>1,"Repeated customer","Non Repeated customer") -> Non Repeated customer
A38: RJ390566 | D38: 206.5 | F38: Q2AU693R | G38: =SUMIF($B:$B,F38,$D:$D) -> 228 | H38: =COUNTIF($B:$B,F38) -> 1 | I38: =IF(H38>1,"Repeated customer","Non Repeated customer") -> Non Repeated customer
A39: RJ390567 | D39: 937.98 | F39: GEUKGFT7 | G39: =SUMIF($B:$B,F39,$D:$D) -> 836 | H39: =COUNTIF($B:$B,F39) -> 2 | I39: =IF(H39>1,"Repeated customer","Non Repeated customer") -> Repeated customer
A40: RJ390568 | D40: 356 | F40: CBXUIKQ3 | G40: =SUMIF($B:$B,F40,$D:$D) -> 397 | H40: =COUNTIF($B:$B,F40) -> 1 | I40: =IF(H40>1,"Repeated customer","Non Repeated customer") -> Non Repeated customer
A41: RJ390569 | D41: 552 | F41: ZI3FFRL4 | G41: =SUMIF($B:$B,F41,$D:$D) -> 520 | H41: =COUNTIF($B:$B,F41) -> 1 | I41: =IF(H41>1,"Repeated customer","Non Repeated customer") -> Non Repeated customer
A42: RJ390572 | D42: 206 | F42: TPNUPRQC | G42: =SUMIF($B:$B,F42,$D:$D) -> 469 | H42: =COUNTIF($B:$B,F42) -> 1 | I42: =IF(H42>1,"Repeated customer","Non Repeated customer") -> Non Repeated customer
A43: RJ390575 | D43: 355 | F43: ZKEJTVV7 | G43: =SUMIF($B:$B,F43,$D:$D) -> 672 | H43: =COUNTIF($B:$B,F43) -> 2 | I43: =IF(H43>1,"Repeated customer","Non Repeated customer") -> Repeated customer
A44: RJ390576 | D44: 249 | F44: 3VEC4KXZ | G44: =SUMIF($B:$B,F44,$D:$D) -> 629 | H44: =COUNTIF($B:$B,F44) -> 1 | I44: =IF(H44>1,"Repeated customer","Non Repeated customer") -> Non Repeated customer
A45: RJ390577 | B45: RJFXN3YM | C45: Burgrill | D45: 124 | F45: IHJA8G9L | G45: =SUMIF($B:$B,F45,$D:$D) -> 13920 | H45: =COUNTIF($B:$B,F45) -> 31 | I45: =IF(H45>1,"Repeated customer","Non Repeated customer") -> Repeated customer
A46: RJ390574 | B46: RJFXN3YM | C46: Burgrill | D46: 83 | F46: ELRIVHC4 | G46: =SUMIF($B:$B,F46,$D:$D) -> 177 | H46: =COUNTIF($B:$B,F46) -> 1 | I46: =IF(H46>1,"Repeated customer","Non Repeated customer") -> Non Repeated customer
A47: RJ390573 | B47: RJFXN3YM | C47: Burgrill | D47: 167 | F47: 65UPMA2G | G47: =SUMIF($B:$B,F47,$D:$D) -> 725 | H47: =COUNTIF($B:$B,F47) -> 1 | I47: =IF(H47>1,"Repeated customer","Non Repeated customer") -> Non Repeated customer
A48: RJ390578 | D48: 381 | F48: G17NPEK4 | G48: =SUMIF($B:$B,F48,$D:$D) -> 595 | H48: =COUNTIF($B:$B,F48) -> 1 | I48: =IF(H48>1,"Repeated customer","Non Repeated customer") -> Non Repeated customer
A49: RJ390579 | D49: 524 | F49: CFD1T9BF | G49: =SUMIF($B:$B,F49,$D:$D) -> 124 | H49: =COUNTIF($B:$B,F49) -> 1 | I49: =IF(H49>1,"Repeated customer","Non Repeated customer") -> Non Repeated customer
A50: RJ390583 | D50: 777 | F50: 1DLHY7WX | G50: =SUMIF($B:$B,F50,$D:$D) -> 667 | H50: =COUNTIF($B:$B,F50) -> 3 | I50: =IF(H50>1,"Repeated customer","Non Repeated customer") -> Repeated customer
A51: RJ390584 | D51: 728 | F51: HJM6URJB | G51: =SUMIF($B:$B,F51,$D:$D) -> 188 | H51: =COUNTIF($B:$B,F51) -> 1 | I51: =IF(H51>1,"Repeated customer","Non Repeated customer") -> Non Repeated customer
A52: RJ390586 | B52: D8MDIGHA | C52: Hargun | D52: 147 | F52: 16C1I1QY | G52: =SUMIF($B:$B,F52,$D:$D) -> 376 | H52: =COUNTIF($B:$B,F52) -> 1 | I52: =IF(H52>1,"Repeated customer","Non Repeated customer") -> Non Repeated customer
A53: RJ390587 | D53: 161 | F53: 7R8KVK5Y | G53: =SUMIF($B:$B,F53,$D:$D) -> 104 | H53: =COUNTIF($B:$B,F53) -> 1 | I53: =IF(H53>1,"Repeated customer","Non Repeated customer") -> Non Repeated customer
A54: RJ390588 | D54: 674 | F54: GMUAXMLK | G54: =SUMIF($B:$B,F54,$D:$D) -> 313 | H54: =COUNTIF($B:$B,F54) -> 1 | I54: =IF(H54>1,"Repeated customer","Non Repeated customer") -> Non Repeated customer
A55: RJ390589 | D55: 306 | F55: Z2I2I6YH | G55: =SUMIF($B:$B,F55,$D:$D) -> 68412 | H55: =COUNTIF($B:$B,F55) -> 198 | I55: =IF(H55>1,"Repeated customer","Non Repeated customer") -> Repeated customer
A56: RJ390590 | D56: 386 | F56: VQ4G7JD7 | G56: =SUMIF($B:$B,F56,$D:$D) -> 137 | H56: =COUNTIF($B:$B,F56) -> 1 | I56: =IF(H56>1,"Repeated customer","Non Repeated customer") -> Non Repeated customer
A57: RJ390585 | B57: RJFXN3YM | C57: Burgrill | D57: 387 | F57: CD4SADMK | G57: =SUMIF($B:$B,F57,$D:$D) -> 666 | H57: =COUNTIF($B:$B,F57) -> 5 | I57: =IF(H57>1,"Repeated customer","Non Repeated customer") -> Repeated customer
A58: RJ390592 | D58: 260 | F58: 79A2CMQH | G58: =SUMIF($B:$B,F58,$D:$D) -> 230 | H58: =COUNTIF($B:$B,F58) -> 1 | I58: =IF(H58>1,"Repeated customer","Non Repeated customer") -> Non Repeated customer
A59: RJ390593 | D59: 285 | F59: 9UENW7DE | G59: =SUMIF($B:$B,F59,$D:$D) -> 829 | H59: =COUNTIF($B:$B,F59) -> 1 | I59: =IF(H59>1,"Repeated customer","Non Repeated customer") -> Non Repeated customer
A60: RJ390594 | D60: 552 | F60: K8BWU9UI | G60: =SUMIF($B:$B,F60,$D:$D) -> 167 | H60: =COUNTIF($B:$B,F60) -> 1 | I60: =IF(H60>1,"Repeated customer","Non Repeated customer") -> Non Repeated customer
A61: RJ390595 | D61: 513.5 | F61: I2KJIFBM | G61: =SUMIF($B:$B,F61,$D:$D) -> 187 | H61: =COUNTIF($B:$B,F61) -> 1 | I61: =IF(H61>1,"Repeated customer","Non Repeated customer") -> Non Repeated customer
A62: RJ390597 | D62: 792.5 | F62: YZHZ2PA9 | G62: =SUMIF($B:$B,F62,$D:$D) -> 124 | H62: =COUNTIF($B:$B,F62) -> 1 | I62: =IF(H62>1,"Repeated customer","Non Repeated customer") -> Non Repeated customer
A63: RJ390598 | B63: RJFXN3YM | C63: Burgrill | D63: 198 | F63: 71BVF7R1 | G63: =SUMIF($B:$B,F63,$D:$D) -> 334 | H63: =COUNTIF($B:$B,F63) -> 1 | I63: =IF(H63>1,"Repeated customer","Non Repeated customer") -> Non Repeated customer
A64: RJ390591 | B64: RJFXN3YM | C64: Burgrill | D64: 322 | F64: XGDB2B6Z | G64: =SUMIF($B:$B,F64,$D:$D) -> 1331 | H64: =COUNTIF($B:$B,F64) -> 5 | I64: =IF(H64>1,"Repeated customer","Non Repeated customer") -> Repeated customer
A65: RJ390601 | D65: 186 | F65: HW8M2P8Q | G65: =SUMIF($B:$B,F65,$D:$D) -> 775 | H65: =COUNTIF($B:$B,F65) -> 1 | I65: =IF(H65>1,"Repeated customer","Non Repeated customer") -> Non Repeated customer
A66: RJ390602 | D66: 276 | F66: KIJ6XFKT | G66: =SUMIF($B:$B,F66,$D:$D) -> 129 | H66: =COUNTIF($B:$B,F66) -> 1 | I66: =IF(H66>1,"Repeated customer","Non Repeated customer") -> Non Repeated customer
A67: RJ390600 | B67: CSNWY5P7 | C67: APAR | D67: 356 | F67: 3GAWT8FS | G67: =SUMIF($B:$B,F67,$D:$D) -> 167 | H67: =COUNTIF($B:$B,F67) -> 1 | I67: =IF(H67>1,"Repeated customer","Non Repeated customer") -> Non Repeated customer
A68: RJ390603 | B68: RJFXN3YM | C68: Burgrill | D68: 198 | F68: G9SEYLHC | G68: =SUMIF($B:$B,F68,$D:$D) -> 397 | H68: =COUNTIF($B:$B,F68) -> 1 | I68: =IF(H68>1,"Repeated customer","Non Repeated customer") -> Non Repeated customer
A69: RJ390599 | B69: RJFXN3YM | C69: Burgrill | D69: 460 | F69: X7HBD6E4 | G69: =SUMIF($B:$B,F69,$D:$D) -> 1348 | H69: =COUNTIF($B:$B,F69) -> 2 | I69: =IF(H69>1,"Repeated customer","Non Repeated customer") -> Repeated customer
A70: RJ390581 | B70: RJFXN3YM | C70: Burgrill | D70: 167 | F70: YBA7KARP | G70: =SUMIF($B:$B,F70,$D:$D) -> 209 | H70: =COUNTIF($B:$B,F70) -> 1 | I70: =IF(H70>1,"Repeated customer","Non Repeated customer") -> Non Repeated customer
A71: RJ390580 | B71: RJFXN3YM | C71: Burgrill | D71: 114 | F71: 2SURHYLP | G71: =SUMIF($B:$B,F71,$D:$D) -> 1147 | H71: =COUNTIF($B:$B,F71) -> 3 | I71: =IF(H71>1,"Repeated customer","Non Repeated customer") -> Repeated customer
A72: RJ390571 | B72: RJFXN3YM | C72: Burgrill | D72: 209 | F72: Z61GKRBS | G72: =SUMIF($B:$B,F72,$D:$D) -> 62 | H72: =COUNTIF($B:$B,F72) -> 1 | I72: =IF(H72>1,"Repeated customer","Non Repeated customer") -> Non Repeated customer
A73: RJ390596 | B73: RJFXN3YM | C73: Burgrill | D73: 613 | F73: YZYHT7U6 | G73: =SUMIF($B:$B,F73,$D:$D) -> 1322 | H73: =COUNTIF($B:$B,F73) -> 2 | I73: =IF(H73>1,"Repeated customer","Non Repeated customer") -> Repeated customer
A74: RJ390605 | D74: 489 | F74: I5IAXI4G | G74: =SUMIF($B:$B,F74,$D:$D) -> 230 | H74: =COUNTIF($B:$B,F74) -> 1 | I74: =IF(H74>1,"Repeated customer","Non Repeated customer") -> Non Repeated customer
A75: RJ390606 | D75: 230 | F75: XPBBA4UJ | G75: =SUMIF($B:$B,F75,$D:$D) -> 310 | H75: =COUNTIF($B:$B,F75) -> 1 | I75: =IF(H75>1,"Repeated customer","Non Repeated customer") -> Non Repeated customer
A76: RJ390608 | D76: 298 | F76: RHQXQW95 | G76: =SUMIF($B:$B,F76,$D:$D) -> 436 | H76: =COUNTIF($B:$B,F76) -> 1 | I76: =IF(H76>1,"Repeated customer","Non Repeated customer") -> Non Repeated customer
A77: RJ390609 | B77: RJFXN3YM | C77: Burgrill | D77: 186 | F77: 67P1UTK5 | G77: =SUMIF($B:$B,F77,$D:$D) -> 366 | H77: =COUNTIF($B:$B,F77) -> 1 | I77: =IF(H77>1,"Repeated customer","Non Repeated customer") -> Non Repeated customer
A78: RJ390610 | D78: 584 | F78: 9ZVPXZ4S | G78: =SUMIF($B:$B,F78,$D:$D) -> 291 | H78: =COUNTIF($B:$B,F78) -> 1 | I78: =IF(H78>1,"Repeated customer","Non Repeated customer") -> Non Repeated customer
A79: RJ390604 | B79: RJFXN3YM | C79: Burgrill | D79: 314 | F79: XRBT7WRQ | G79: =SUMIF($B:$B,F79,$D:$D) -> 198 | H79: =COUNTIF($B:$B,F79) -> 1 | I79: =IF(H79>1,"Repeated customer","Non Repeated customer") -> Non Repeated customer
A80: RJ390612 | D80: 343 | F80: H7Y5I4BA | G80: =SUMIF($B:$B,F80,$D:$D) -> 1549 | H80: =COUNTIF($B:$B,F80) -> 9 | I80: =IF(H80>1,"Repeated customer","Non Repeated customer") -> Repeated customer
A81: RJ390613 | D81: 381 | F81: V3132BLT | G81: =SUMIF($B:$B,F81,$D:$D) -> 62 | H81: =COUNTIF($B:$B,F81) -> 1 | I81: =IF(H81>1,"Repeated customer","Non Repeated customer") -> Non Repeated customer
A82: RJ390615 | D82: 207 | F82: NH1WMWIA | G82: =SUMIF($B:$B,F82,$D:$D) -> 9063 | H82: =COUNTIF($B:$B,F82) -> 23 | I82: =IF(H82>1,"Repeated customer","Non Repeated customer") -> Repeated customer
A83: RJ390617 | D83: 503.5 | F83: G1ZUH5Z4 | G83: =SUMIF($B:$B,F83,$D:$D) -> 83 | H83: =COUNTIF($B:$B,F83) -> 1 | I83: =IF(H83>1,"Repeated customer","Non Repeated customer") -> Non Repeated customer
A84: RJ390618 | D84: 390 | F84: TFCZUXAL | G84: =SUMIF($B:$B,F84,$D:$D) -> 1081 | H84: =COUNTIF($B:$B,F84) -> 1 | I84: =IF(H84>1,"Repeated customer","Non Repeated customer") -> Non Repeated customer
A85: RJ390619 | D85: 180 | F85: QAKICTX9 | G85: =SUMIF($B:$B,F85,$D:$D) -> 689 | H85: =COUNTIF($B:$B,F85) -> 1 | I85: =IF(H85>1,"Repeated customer","Non Repeated customer") -> Non Repeated customer
A86: RJ390620 | B86: RJFXN3YM | C86: Burgrill | D86: 188 | F86: 2EN4UYUD | G86: =SUMIF($B:$B,F86,$D:$D) -> 3039 | H86: =COUNTIF($B:$B,F86) -> 3 | I86: =IF(H86>1,"Repeated customer","Non Repeated customer") -> Repeated customer
A87: RJ390611 | B87: RJFXN3YM | C87: Burgrill | D87: 1074 | F87: 8FI9BQ6Q | G87: =SUMIF($B:$B,F87,$D:$D) -> 376 | H87: =COUNTIF($B:$B,F87) -> 1 | I87: =IF(H87>1,"Repeated customer","Non Repeated customer") -> Non Repeated customer
A88: RJ390607 | B88: RJFXN3YM | C88: Burgrill | D88: 657 | F88: 6KL73ZBA | G88: =SUMIF($B:$B,F88,$D:$D) -> 167 | H88: =COUNTIF($B:$B,F88) -> 1 | I88: =IF(H88>1,"Repeated customer","Non Repeated customer") -> Non Repeated customer
A89: RJ390570 | B89: GFCWJ7BX | C89: karan | D89: 1108 | F89: 9RQL9PDE | G89: =SUMIF($B:$B,F89,$D:$D) -> 1018 | H89: =COUNTIF($B:$B,F89) -> 2 | I89: =IF(H89>1,"Repeated customer","Non Repeated customer") -> Repeated customer
A90: RJ390616 | B90: Z3PZWUEE | C90: dhruv | D90: 206 | F90: 4DA592P3 | G90: =SUMIF($B:$B,F90,$D:$D) -> 1896 | H90: =COUNTIF($B:$B,F90) -> 3 | I90: =IF(H90>1,"Repeated customer","Non Repeated customer") -> Repeated customer
A91: RJ390614 | B91: 7111VIGN | C91: burgrill | D91: 198 | F91: 91UL6L8E | G91: =SUMIF($B:$B,F91,$D:$D) -> 428 | H91: =COUNTIF($B:$B,F91) -> 1 | I91: =IF(H91>1,"Repeated customer","Non Repeated customer") -> Non Repeated customer
A92: RJ390565 | B92: RZF7ACWG | C92: sarabjeet | D92: 398 | F92: EY4H1UDS | G92: =SUMIF($B:$B,F92,$D:$D) -> 416 | H92: =COUNTIF($B:$B,F92) -> 1 | I92: =IF(H92>1,"Repeated customer","Non Repeated customer") -> Non Repeated customer
A93: RJ390582 | B93: RJFXN3YM | C93: Burgrill | D93: 374 | F93: VYS7K6XG | G93: =SUMIF($B:$B,F93,$D:$D) -> 561 | H93: =COUNTIF($B:$B,F93) -> 1 | I93: =IF(H93>1,"Repeated customer","Non Repeated customer") -> Non Repeated customer
A94: RJ390622 | D94: 435.43 | F94: U2E3413W | G94: =SUMIF($B:$B,F94,$D:$D) -> 236 | H94: =COUNTIF($B:$B,F94) -> 2 | I94: =IF(H94>1,"Repeated customer","Non Repeated customer") -> Repeated customer
A95: RJ390626 | D95: 355 | F95: JLJXLIY5 | G95: =SUMIF($B:$B,F95,$D:$D) -> 711 | H95: =COUNTIF($B:$B,F95) -> 1 | I95: =IF(H95>1,"Repeated customer","Non Repeated customer") -> Non Repeated customer
A96: RJ390627 | B96: RJFXN3YM | C96: Burgrill | D96: 398 | F96: MCL41JNW | G96: =SUMIF($B:$B,F96,$D:$D) -> 228 | H96: =COUNTIF($B:$B,F96) -> 1 | I96: =IF(H96>1,"Repeated customer","Non Repeated customer") -> Non Repeated customer
A97: RJ390630 | D97: 160 | F97: MDB27PEW | G97: =SUMIF($B:$B,F97,$D:$D) -> 311 | H97: =COUNTIF($B:$B,F97) -> 2 | I97: =IF(H97>1,"Repeated customer","Non Repeated customer") -> Repeated customer
A98: RJ390631 | B98: RJFXN3YM | C98: Burgrill | D98: 251 | F98: J6R8SM7P | G98: =SUMIF($B:$B,F98,$D:$D) -> 186 | H98: =COUNTIF($B:$B,F98) -> 1 | I98: =IF(H98>1,"Repeated customer","Non Repeated customer") -> Non Repeated customer
A99: RJ390632 | B99: RJFXN3YM | C99: Burgrill | D99: 188 | F99: W69Q73NE | G99: =SUMIF($B:$B,F99,$D:$D) -> 942 | H99: =COUNTIF($B:$B,F99) -> 2 | I99: =IF(H99>1,"Repeated customer","Non Repeated customer") -> Repeated customer
A100: RJ390629 | B100: RJFXN3YM | C100: Burgrill | D100: 658 | F100: UQN7GB2F | G100: =SUMIF($B:$B,F100,$D:$D) -> 732 | H100: =COUNTIF($B:$B,F100) -> 1 | I100: =IF(H100>1,"Repeated customer","Non Repeated customer") -> Non Repeated customer
...
